Workbook

Sheet BS
A1: ='BS Data'!C1 -> Allure of Peru
A2: Balance Sheet Analysis
A3: ='BS Data'!B3 -> As Of 12/31/2025
B5: CURRENT PERIOD
B6: Actual $
A7: Current Assets
A8: Cash | B8: =VLOOKUP(A8,'BS Data'!A8:B48,2,FALSE) -> 22699
A9: Accounts Receivable | B9: =VLOOKUP(A9,'BS Data'!A9:B49,2,FALSE) -> 1715902
A10: Allowance for Doubtful Account | B10: =VLOOKUP(A10,'BS Data'!A10:B50,2,FALSE) -> -50489
A11: Prepaid Expense | B11: =VLOOKUP(A11,'BS Data'!A11:B51,2,FALSE) -> 156097
A12: Intercompany Receivable | B12: =VLOOKUP(A12,'DTF & QuickCalc'!A57:B58,2,FALSE) -> 1279660.1
A13: Other Current Assets | B13: =VLOOKUP(A13,'BS Data'!A13:B53,2,FALSE) -> 1783
A14: TOTAL Current Assets | B14: =SUM(B8:B13) -> 3125652.1
A15: Fixed Assets
A16: Building and Land | B16: =VLOOKUP(A16,'BS Data'!A16:B56,2,FALSE) -> 3416
A17: Equipment | B17: =VLOOKUP(A17,'BS Data'!A17:B57,2,FALSE) -> 131927
A18: Furniture and Fixtures | B18: =VLOOKUP(A18,'BS Data'!A18:B58,2,FALSE) -> 4749
A19: Leasehold Improvements | B19: =VLOOKUP(A19,'BS Data'!A19:B59,2,FALSE) -> 685794
A20: CIP - Leasehold Improvements | B20: =VLOOKUP(A20,'BS Data'!A20:B60,2,FALSE) -> 0
A21: Vehicles | B21: =VLOOKUP(A21,'BS Data'!A21:B61,2,FALSE) -> 1099
A22: Organization Costs | B22: =VLOOKUP(A22,'BS Data'!A22:B62,2,FALSE) -> 23124
A23: Replacement Reserve | B23: =VLOOKUP(A23,'BS Data'!A23:B63,2,FALSE) -> 31590
A24: Loan Costs | B24: =VLOOKUP(A24,'BS Data'!A24:B64,2,FALSE) -> 0
A25: Less Accumulated Depreciation | B25: =VLOOKUP(A25,'BS Data'!A25:B65,2,FALSE) -> -180889
A26: TOTAL Fixed Assets | B26: =SUM(B16:B25) -> 700810
A27: Total Assets | B27: =B26+B14 -> 3826462.1
A28: Current Liabilities
A29: Accounts Payable | B29: =VLOOKUP(A29,'BS Data'!A29:B69,2,FALSE) -> 782460
A30: Credit Card Payable | B30: =VLOOKUP(A30,'BS Data'!A30:B70,2,FALSE) -> 0
A31: Accrued Expenses | B31: =VLOOKUP(A31,'BS Data'!A31:B71,2,FALSE) -> 231834
A32: Payroll Accruals and Liabilities | B32: =VLOOKUP(A32,'DTF & QuickCalc'!A63:B66,2,FALSE) -> 116658
A33: Line of Credit | B33: =VLOOKUP(A33,'BS Data'!A33:B73,2,FALSE) -> 850000
A34: Intercompany Payable | B34: =VLOOKUP(A34,'DTF & QuickCalc'!A57:B58,2,FALSE)-2 -> 1890823.7
A35: Other Current Liabilities | B35: =VLOOKUP(A35,'BS Data'!A35:B75,2,FALSE) -> 1446
A36: Resident Security Deposits | B36: =VLOOKUP(A36,'BS Data'!A36:B76,2,FALSE) -> 0
A37: TOTAL Current Liabilities | B37: =SUM(B29:B36) -> 3873221.7
A38: Long Term Liabilities | B38: =VLOOKUP(A38,'BS Data'!A38:B78,2,FALSE) -> 0
A39: TOTAL Liabilities | B39: =B37+B38 -> 3873221.7
A40: Equity
A41: Equity | B41: =VLOOKUP(A41,'BS Data'!A41:B81,2,FALSE) -> 759644
A42: Distributions | B42: =VLOOKUP(A42,'BS Data'!A42:B82,2,FALSE) -> -1145000
A43: Net Income | B43: =VLOOKUP(A43,'BS Data'!A43:B83,2,FALSE) -> 338596
A44: TOTAL Equity | B44: =SUM(B41:B43) -> -46760
A45: Total Liabilities and Equity | B45: =B39+B44 -> 3826461.7
D46: =B45-B27 -> -0.42

Sheet P&L
A1: =BS!A1 -> Allure of Peru
A2: Income Statement Detail
A3: ='P&L Data'!B3 -> 1/1/2025 to 12/31/2025
B5: CURRENT PERIOD | D5: YEAR TO DATE
B6: Actual $ | C6: Actual / Day | D6: Actual $ | E6: Actual / Day
A7: Revenue
A8: Medicaid | B8: =VLOOKUP(A8,'P&L Data'!A8:E150,2,FALSE) -> 4650290 | C8: =VLOOKUP(A8,'P&L Data'!A8:E150,3,FALSE) -> 279.75 | D8: =VLOOKUP(A8,'P&L Data'!A8:E150,4,FALSE) -> 4650290 | E8: =VLOOKUP(A8,'P&L Data'!A8:E150,5,FALSE) -> 279.75
A9: Hospice | B9: =VLOOKUP(A9,'P&L Data'!A9:E151,2,FALSE) -> 404354 | C9: =VLOOKUP(A9,'P&L Data'!A9:E151,3,FALSE) -> 278.29 | D9: =VLOOKUP(A9,'P&L Data'!A9:E151,4,FALSE) -> 404354 | E9: =VLOOKUP(A9,'P&L Data'!A9:E151,5,FALSE) -> 278.29
A10: Medicare A | B10: =VLOOKUP(A10,'P&L Data'!A10:E152,2,FALSE) -> 2480638 | C10: =VLOOKUP(A10,'P&L Data'!A10:E152,3,FALSE) -> 682.43 | D10: =VLOOKUP(A10,'P&L Data'!A10:E152,4,FALSE) -> 2480638 | E10: =VLOOKUP(A10,'P&L Data'!A10:E152,5,FALSE) -> 682.43
A11: Commercial Insurance | B11: =VLOOKUP(A11,'P&L Data'!A11:E153,2,FALSE) -> 924175 | C11: =VLOOKUP(A11,'P&L Data'!A11:E153,3,FALSE) -> 458.65 | D11: =VLOOKUP(A11,'P&L Data'!A11:E153,4,FALSE) -> 924175 | E11: =VLOOKUP(A11,'P&L Data'!A11:E153,5,FALSE) -> 458.65
A12: Private Pay | B12: =VLOOKUP(A12,'P&L Data'!A12:E154,2,FALSE) -> 1446974 | C12: =VLOOKUP(A12,'P&L Data'!A12:E154,3,FALSE) -> 295.24 | D12: =VLOOKUP(A12,'P&L Data'!A12:E154,4,FALSE) -> 1446974 | E12: =VLOOKUP(A12,'P&L Data'!A12:E154,5,FALSE) -> 295.24
A13: Veteran Affairs | B13: =VLOOKUP(A13,'P&L Data'!A13:E155,2,FALSE) -> 0 | C13: =VLOOKUP(A13,'P&L Data'!A13:E155,3,FALSE) -> 0 | D13: =VLOOKUP(A13,'P&L Data'!A13:E155,4,FALSE) -> 0 | E13: =VLOOKUP(A13,'P&L Data'!A13:E155,5,FALSE) -> 0
A14: Medicare / Managed Care B | B14: =VLOOKUP(A14,'P&L Data'!A14:E156,2,FALSE) -> 297113 | C14: =VLOOKUP(A14,'P&L Data'!A14:E156,3,FALSE) -> 0 | D14: =VLOOKUP(A14,'P&L Data'!A14:E156,4,FALSE) -> 297113 | E14: =VLOOKUP(A14,'P&L Data'!A14:E156,5,FALSE) -> 0
A15: Private Pay Independent Living | B15: =VLOOKUP(A15,'P&L Data'!A15:E157,2,FALSE) -> 0 | C15: =VLOOKUP(A15,'P&L Data'!A15:E157,3,FALSE) -> 0 | D15: =VLOOKUP(A15,'P&L Data'!A15:E157,4,FALSE) -> 0 | E15: =VLOOKUP(A15,'P&L Data'!A15:E157,5,FALSE) -> 0
A16: Home Care Income | B16: =VLOOKUP(A16,'P&L Data'!A16:E158,2,FALSE) -> 0 | C16: =VLOOKUP(A16,'P&L Data'!A16:E158,3,FALSE) -> 0 | D16: =VLOOKUP(A16,'P&L Data'!A16:E158,4,FALSE) -> 0 | E16: =VLOOKUP(A16,'P&L Data'!A16:E158,5,FALSE) -> 0
A17: Daily Training Program | B17: =VLOOKUP(A17,'P&L Data'!A17:E159,2,FALSE) -> 0 | C17: =VLOOKUP(A17,'P&L Data'!A17:E159,3,FALSE) -> 0 | D17: =VLOOKUP(A17,'P&L Data'!A17:E159,4,FALSE) -> 0 | E17: =VLOOKUP(A17,'P&L Data'!A17:E159,5,FALSE) -> 0
A18: Other | B18: =VLOOKUP(A18,'P&L Data'!A18:E160,2,FALSE) -> 5276 | C18: =VLOOKUP(A18,'P&L Data'!A18:E160,3,FALSE) -> 0 | D18: =VLOOKUP(A18,'P&L Data'!A18:E160,4,FALSE) -> 5276 | E18: =VLOOKUP(A18,'P&L Data'!A18:E160,5,FALSE) -> 0
A19: Stimulus Income | B19: =VLOOKUP(A19,'P&L Data'!A19:E161,2,FALSE) -> 0 | C19: =VLOOKUP(A19,'P&L Data'!A19:E161,3,FALSE) -> 0 | D19: =VLOOKUP(A19,'P&L Data'!A19:E161,4,FALSE) -> 0 | E19: =VLOOKUP(A19,'P&L Data'!A19:E161,5,FALSE) -> 0
... A21: TOTAL Revenue | B21: =VLOOKUP(A21,'P&L Data'!A21:E163,2,FALSE) -> 10424247 | C21: =VLOOKUP(A21,'P&L Data'!A21:E163,3,FALSE) -> 364.14 | D21: =VLOOKUP(A21,'P&L Data'!A21:E163,4,FALSE) -> 10424247 | E21: =VLOOKUP(A21,'P&L Data'!A21:E163,5,FALSE) -> 364.14
A22: Patient Days
A23: Medicaid | B23: =VLOOKUP(A23,'P&L Data'!A23:E165,2,FALSE) -> 16663 | C23: =VLOOKUP(A23,'P&L Data'!A23:E165,3,FALSE) -> 0 | D23: =VLOOKUP(A23,'P&L Data'!A23:E165,4,FALSE) -> 16663 | E23: =VLOOKUP(A23,'P&L Data'!A23:E165,5,FALSE) -> 0
A24: Hospice | B24: =VLOOKUP(A24,'P&L Data'!A24:E166,2,FALSE) -> 1453 | C24: =VLOOKUP(A24,'P&L Data'!A24:E166,3,FALSE) -> 0 | D24: =VLOOKUP(A24,'P&L Data'!A24:E166,4,FALSE) -> 1453 | E24: =VLOOKUP(A24,'P&L Data'!A24:E166,5,FALSE) -> 0
A25: Medicare A | B25: =VLOOKUP(A25,'P&L Data'!A25:E167,2,FALSE) -> 3635 | C25: =VLOOKUP(A25,'P&L Data'!A25:E167,3,FALSE) -> 0 | D25: =VLOOKUP(A25,'P&L Data'!A25:E167,4,FALSE) -> 3635 | E25: =VLOOKUP(A25,'P&L Data'!A25:E167,5,FALSE) -> 0
A26: Commercial Insurance | B26: =VLOOKUP(A26,'P&L Data'!A26:E168,2,FALSE) -> 2015 | C26: =VLOOKUP(A26,'P&L Data'!A26:E168,3,FALSE) -> 0 | D26: =VLOOKUP(A26,'P&L Data'!A26:E168,4,FALSE) -> 2015 | E26: =VLOOKUP(A26,'P&L Data'!A26:E168,5,FALSE) -> 0
A27: Private Pay | B27: =VLOOKUP(A27,'P&L Data'!A27:E169,2,FALSE) -> 4894 | C27: =VLOOKUP(A27,'P&L Data'!A27:E169,3,FALSE) -> 0 | D27: =VLOOKUP(A27,'P&L Data'!A27:E169,4,FALSE) -> 4894 | E27: =VLOOKUP(A27,'P&L Data'!A27:E169,5,FALSE) -> 0
A28: Veteran Affairs | B28: =VLOOKUP(A28,'P&L Data'!A28:E170,2,FALSE) -> 0 | C28: =VLOOKUP(A28,'P&L Data'!A28:E170,3,FALSE) -> 0 | D28: =VLOOKUP(A28,'P&L Data'!A28:E170,4,FALSE) -> 0 | E28: =VLOOKUP(A28,'P&L Data'!A28:E170,5,FALSE) -> 0
A29: Independent Living | B29: =VLOOKUP(A29,'P&L Data'!A29:E171,2,FALSE) -> 0 | C29: =VLOOKUP(A29,'P&L Data'!A29:E171,3,FALSE) -> 0 | D29: =VLOOKUP(A29,'P&L Data'!A29:E171,4,FALSE) -> 0 | E29: =VLOOKUP(A29,'P&L Data'!A29:E171,5,FALSE) -> 0
A30: TOTAL Patient Days | B30: =VLOOKUP(A30,'P&L Data'!A30:E172,2,FALSE) -> 28660 | C30: =VLOOKUP(A30,'P&L Data'!A30:E172,3,FALSE) -> 0 | D30: =VLOOKUP(A30,'P&L Data'!A30:E172,4,FALSE) -> 28660 | E30: =VLOOKUP(A30,'P&L Data'!A30:E172,5,FALSE) -> 0
A31: Nursing & Medical
A32: Director Of Nursing | B32: =VLOOKUP(A32,'P&L Data'!A32:E174,2,FALSE) -> 105946 | C32: =VLOOKUP(A32,'P&L Data'!A32:E174,3,FALSE) -> 3.7 | D32: =VLOOKUP(A32,'P&L Data'!A32:E174,4,FALSE) -> 105946 | E32: =VLOOKUP(A32,'P&L Data'!A32:E174,5,FALSE) -> 3.7
A33: Assistant Director Of Nursing | B33: =VLOOKUP(A33,'P&L Data'!A33:E175,2,FALSE) -> 85613 | C33: =VLOOKUP(A33,'P&L Data'!A33:E175,3,FALSE) -> 2.99 | D33: =VLOOKUP(A33,'P&L Data'!A33:E175,4,FALSE) -> 85613 | E33: =VLOOKUP(A33,'P&L Data'!A33:E175,5,FALSE) -> 2.99
A34: Payroll RN | B34: =VLOOKUP(A34,'P&L Data'!A34:E176,2,FALSE) -> 800771 | C34: =VLOOKUP(A34,'P&L Data'!A34:E176,3,FALSE) -> 27.97 | D34: =VLOOKUP(A34,'P&L Data'!A34:E176,4,FALSE) -> 800771 | E34: =VLOOKUP(A34,'P&L Data'!A34:E176,5,FALSE) -> 27.97
A35: Payroll LPN | B35: =VLOOKUP(A35,'P&L Data'!A35:E177,2,FALSE) -> 442824 | C35: =VLOOKUP(A35,'P&L Data'!A35:E177,3,FALSE) -> 15.47 | D35: =VLOOKUP(A35,'P&L Data'!A35:E177,4,FALSE) -> 442824 | E35: =VLOOKUP(A35,'P&L Data'!A35:E177,5,FALSE) -> 15.47
A36: Payroll Aides & Orderlies | B36: =VLOOKUP(A36,'P&L Data'!A36:E178,2,FALSE) -> 1861774 | C36: =VLOOKUP(A36,'P&L Data'!A36:E178,3,FALSE) -> 65.04 | D36: =VLOOKUP(A36,'P&L Data'!A36:E178,4,FALSE) -> 1861774 | E36: =VLOOKUP(A36,'P&L Data'!A36:E178,5,FALSE) -> 65.04
A37: Payroll Nursing Clerical | B37: =VLOOKUP(A37,'P&L Data'!A37:E179,2,FALSE) -> 92496 | C37: =VLOOKUP(A37,'P&L Data'!A37:E179,3,FALSE) -> 3.23 | D37: =VLOOKUP(A37,'P&L Data'!A37:E179,4,FALSE) -> 92496 | E37: =VLOOKUP(A37,'P&L Data'!A37:E179,5,FALSE) -> 3.23
A38: Payroll Medical Records | B38: =VLOOKUP(A38,'P&L Data'!A38:E180,2,FALSE) -> 0 | C38: =VLOOKUP(A38,'P&L Data'!A38:E180,3,FALSE) -> 0 | D38: =VLOOKUP(A38,'P&L Data'!A38:E180,4,FALSE) -> 0 | E38: =VLOOKUP(A38,'P&L Data'!A38:E180,5,FALSE) -> 0
A39: Contract RN | B39: =VLOOKUP(A39,'P&L Data'!A39:E181,2,FALSE) -> 177691 | C39: =VLOOKUP(A39,'P&L Data'!A39:E181,3,FALSE) -> 6.21 | D39: =VLOOKUP(A39,'P&L Data'!A39:E181,4,FALSE) -> 177691 | E39: =VLOOKUP(A39,'P&L Data'!A39:E181,5,FALSE) -> 6.21
A40: Contract LPN | B40: =VLOOKUP(A40,'P&L Data'!A40:E182,2,FALSE) -> 18418 | C40: =VLOOKUP(A40,'P&L Data'!A40:E182,3,FALSE) -> 0.64 | D40: =VLOOKUP(A40,'P&L Data'!A40:E182,4,FALSE) -> 18418 | E40: =VLOOKUP(A40,'P&L Data'!A40:E182,5,FALSE) -> 0.64
A41: Contract Aides & Orderlies | B41: =VLOOKUP(A41,'P&L Data'!A41:E183,2,FALSE) -> 167869 | C41: =VLOOKUP(A41,'P&L Data'!A41:E183,3,FALSE) -> 5.86 | D41: =VLOOKUP(A41,'P&L Data'!A41:E183,4,FALSE) -> 167869 | E41: =VLOOKUP(A41,'P&L Data'!A41:E183,5,FALSE) -> 5.86
A42: Medical Supplies | B42: =VLOOKUP(A42,'P&L Data'!A42:E184,2,FALSE) -> 107643 | C42: =VLOOKUP(A42,'P&L Data'!A42:E184,3,FALSE) -> 3.76 | D42: =VLOOKUP(A42,'P&L Data'!A42:E184,4,FALSE) -> 107643 | E42: =VLOOKUP(A42,'P&L Data'!A42:E184,5,FALSE) -> 3.76
A43: Covid-19 Medical Supplies | B43: =VLOOKUP(A43,'P&L Data'!A43:E185,2,FALSE) -> 8298 | C43: =VLOOKUP(A43,'P&L Data'!A43:E185,3,FALSE) -> 0.29 | D43: =VLOOKUP(A43,'P&L Data'!A43:E185,4,FALSE) -> 8298 | E43: =VLOOKUP(A43,'P&L Data'!A43:E185,5,FALSE) -> 0.29
... A53: TOTAL Nursing & Medical | B53: =VLOOKUP(A53,'P&L Data'!A53:E195,2,FALSE) -> 4107575 | C53: =VLOOKUP(A53,'P&L Data'!A53:E195,3,FALSE) -> 143.49 | D53: =VLOOKUP(A53,'P&L Data'!A53:E195,4,FALSE) -> 4107575 | E53: =VLOOKUP(A53,'P&L Data'!A53:E195,5,FALSE) -> 143.49
A54: Therapy & Ancillary Services
A55: Physical Therapy Services | B55: =VLOOKUP(A55,'P&L Data'!A55:E197,2,FALSE) -> 273865 | C55: =VLOOKUP(A55,'P&L Data'!A55:E197,3,FALSE) -> 9.57 | D55: =VLOOKUP(A55,'P&L Data'!A55:E197,4,FALSE) -> 273865 | E55: =VLOOKUP(A55,'P&L Data'!A55:E197,5,FALSE) -> 9.57
A56: Occupational Therapy Services | B56: =VLOOKUP(A56,'P&L Data'!A56:E198,2,FALSE) -> 240239 | C56: =VLOOKUP(A56,'P&L Data'!A56:E198,3,FALSE) -> 8.39 | D56: =VLOOKUP(A56,'P&L Data'!A56:E198,4,FALSE) -> 240239 | E56: =VLOOKUP(A56,'P&L Data'!A56:E198,5,FALSE) -> 8.39
A57: Speech Therapy Services | B57: =VLOOKUP(A57,'P&L Data'!A57:E199,2,FALSE) -> 33775 | C57: =VLOOKUP(A57,'P&L Data'!A57:E199,3,FALSE) -> 1.18 | D57: =VLOOKUP(A57,'P&L Data'!A57:E199,4,FALSE) -> 33775 | E57: =VLOOKUP(A57,'P&L Data'!A57:E199,5,FALSE) -> 1.18
A58: Pharmacy Consultant | B58: =VLOOKUP(A58,'P&L Data'!A58:E200,2,FALSE) -> 14341 | C58: =VLOOKUP(A58,'P&L Data'!A58:E200,3,FALSE) -> 0.5 | D58: =VLOOKUP(A58,'P&L Data'!A58:E200,4,FALSE) -> 14341 | E58: =VLOOKUP(A58,'P&L Data'!A58:E200,5,FALSE) -> 0.5
A59: RX Drugs | B59: =VLOOKUP(A59,'P&L Data'!A59:E201,2,FALSE) -> 71025 | C59: =VLOOKUP(A59,'P&L Data'!A59:E201,3,FALSE) -> 2.48 | D59: =VLOOKUP(A59,'P&L Data'!A59:E201,4,FALSE) -> 71025 | E59: =VLOOKUP(A59,'P&L Data'!A59:E201,5,FALSE) -> 2.48
A60: Drugs Managed Care | B60: =VLOOKUP(A60,'P&L Data'!A60:E202,2,FALSE) -> 38945 | C60: =VLOOKUP(A60,'P&L Data'!A60:E202,3,FALSE) -> 1.36 | D60: =VLOOKUP(A60,'P&L Data'!A60:E202,4,FALSE) -> 38945 | E60: =VLOOKUP(A60,'P&L Data'!A60:E202,5,FALSE) -> 1.36
A61: VA - Drugs | B61: =VLOOKUP(A61,'P&L Data'!A61:E203,2,FALSE) -> 0 | C61: =VLOOKUP(A61,'P&L Data'!A61:E203,3,FALSE) -> 0 | D61: =VLOOKUP(A61,'P&L Data'!A61:E203,4,FALSE) -> 0 | E61: =VLOOKUP(A61,'P&L Data'!A61:E203,5,FALSE) -> 0
A62: Radiology | B62: =VLOOKUP(A62,'P&L Data'!A62:E204,2,FALSE) -> 5946 | C62: =VLOOKUP(A62,'P&L Data'!A62:E204,3,FALSE) -> 0.21 | D62: =VLOOKUP(A62,'P&L Data'!A62:E204,4,FALSE) -> 5946 | E62: =VLOOKUP(A62,'P&L Data'!A62:E204,5,FALSE) -> 0.21
A63: Laboratory | B63: =VLOOKUP(A63,'P&L Data'!A63:E205,2,FALSE) -> 17083 | C63: =VLOOKUP(A63,'P&L Data'!A63:E205,3,FALSE) -> 0.6 | D63: =VLOOKUP(A63,'P&L Data'!A63:E205,4,FALSE) -> 17083 | E63: =VLOOKUP(A63,'P&L Data'!A63:E205,5,FALSE) -> 0.6
A64: TOTAL Therapy & Ancillary Services | B64: =VLOOKUP(A64,'P&L Data'!A64:E206,2,FALSE) -> 695220 | C64: =VLOOKUP(A64,'P&L Data'!A64:E206,3,FALSE) -> 24.29 | D64: =VLOOKUP(A64,'P&L Data'!A64:E206,4,FALSE) -> 695220 | E64: =VLOOKUP(A64,'P&L Data'!A64:E206,5,FALSE) -> 24.29
A65: Social Services
A66: Payroll Social Services | B66: =VLOOKUP(A66,'P&L Data'!A66:E208,2,FALSE) -> 69813 | C66: =VLOOKUP(A66,'P&L Data'!A66:E208,3,FALSE) -> 2.44 | D66: =VLOOKUP(A66,'P&L Data'!A66:E208,4,FALSE) -> 69813 | E66: =VLOOKUP(A66,'P&L Data'!A66:E208,5,FALSE) -> 2.44
A67: Payroll Admissions | B67: =VLOOKUP(A67,'P&L Data'!A67:E209,2,FALSE) -> 39025 | C67: =VLOOKUP(A67,'P&L Data'!A67:E209,3,FALSE) -> 1.36 | D67: =VLOOKUP(A67,'P&L Data'!A67:E209,4,FALSE) -> 39025 | E67: =VLOOKUP(A67,'P&L Data'!A67:E209,5,FALSE) -> 1.36
A68: Social Service Supplies | B68: =VLOOKUP(A68,'P&L Data'!A68:E210,2,FALSE) -> 0 | C68: =VLOOKUP(A68,'P&L Data'!A68:E210,3,FALSE) -> 0 | D68: =VLOOKUP(A68,'P&L Data'!A68:E210,4,FALSE) -> 0 | E68: =VLOOKUP(A68,'P&L Data'!A68:E210,5,FALSE) -> 0
A69: Social Service Consultant | B69: =VLOOKUP(A69,'P&L Data'!A69:E211,2,FALSE) -> 5565 | C69: =VLOOKUP(A69,'P&L Data'!A69:E211,3,FALSE) -> 0.19 | D69: =VLOOKUP(A69,'P&L Data'!A69:E211,4,FALSE) -> 5565 | E69: =VLOOKUP(A69,'P&L Data'!A69:E211,5,FALSE) -> 0.19
A70: TOTAL Social Services | B70: =VLOOKUP(A70,'P&L Data'!A70:E212,2,FALSE) -> 114403 | C70: =VLOOKUP(A70,'P&L Data'!A70:E212,3,FALSE) -> 4 | D70: =VLOOKUP(A70,'P&L Data'!A70:E212,4,FALSE) -> 114403 | E70: =VLOOKUP(A70,'P&L Data'!A70:E212,5,FALSE) -> 4
A71: Leisure Time & Activities
A72: Payroll Activity | B72: =VLOOKUP(A72,'P&L Data'!A72:E214,2,FALSE) -> 142657 | C72: =VLOOKUP(A72,'P&L Data'!A72:E214,3,FALSE) -> 4.98 | D72: =VLOOKUP(A72,'P&L Data'!A72:E214,4,FALSE) -> 142657 | E72: =VLOOKUP(A72,'P&L Data'!A72:E214,5,FALSE) -> 4.98
A73: Activity Supplies | B73: =VLOOKUP(A73,'P&L Data'!A73:E215,2,FALSE) -> 19289 | C73: =VLOOKUP(A73,'P&L Data'!A73:E215,3,FALSE) -> 0.67 | D73: =VLOOKUP(A73,'P&L Data'!A73:E215,4,FALSE) -> 19289 | E73: =VLOOKUP(A73,'P&L Data'!A73:E215,5,FALSE) -> 0.67
A74: TOTAL Leisure Time & Activities | B74: =VLOOKUP(A74,'P&L Data'!A74:E216,2,FALSE) -> 161946 | C74: =VLOOKUP(A74,'P&L Data'!A74:E216,3,FALSE) -> 5.66 | D74: =VLOOKUP(A74,'P&L Data'!A74:E216,4,FALSE) -> 161946 | E74: =VLOOKUP(A74,'P&L Data'!A74:E216,5,FALSE) -> 5.66
A75: House & Plant Costs
A76: Payroll Housekeeping | B76: =VLOOKUP(A76,'P&L Data'!A76:E218,2,FALSE) -> 133497 | C76: =VLOOKUP(A76,'P&L Data'!A76:E218,3,FALSE) -> 4.66 | D76: =VLOOKUP(A76,'P&L Data'!A76:E218,4,FALSE) -> 133497 | E76: =VLOOKUP(A76,'P&L Data'!A76:E218,5,FALSE) -> 4.66
A77: Payroll Laundry | B77: =VLOOKUP(A77,'P&L Data'!A77:E219,2,FALSE) -> 70169 | C77: =VLOOKUP(A77,'P&L Data'!A77:E219,3,FALSE) -> 2.45 | D77: =VLOOKUP(A77,'P&L Data'!A77:E219,4,FALSE) -> 70169 | E77: =VLOOKUP(A77,'P&L Data'!A77:E219,5,FALSE) -> 2.45
A78: Payroll Maintenance | B78: =VLOOKUP(A78,'P&L Data'!A78:E220,2,FALSE) -> 143776 | C78: =VLOOKUP(A78,'P&L Data'!A78:E220,3,FALSE) -> 5.02 | D78: =VLOOKUP(A78,'P&L Data'!A78:E220,4,FALSE) -> 143776 | E78: =VLOOKUP(A78,'P&L Data'!A78:E220,5,FALSE) -> 5.02
A79: Payroll Security | B79: =VLOOKUP(A79,'P&L Data'!A79:E221,2,FALSE) -> 0 | C79: =VLOOKUP(A79,'P&L Data'!A79:E221,3,FALSE) -> 0 | D79: =VLOOKUP(A79,'P&L Data'!A79:E221,4,FALSE) -> 0 | E79: =VLOOKUP(A79,'P&L Data'!A79:E221,5,FALSE) -> 0
A80: Housekeeping Supplies | B80: =VLOOKUP(A80,'P&L Data'!A80:E222,2,FALSE) -> 20397 | C80: =VLOOKUP(A80,'P&L Data'!A80:E222,3,FALSE) -> 0.71 | D80: =VLOOKUP(A80,'P&L Data'!A80:E222,4,FALSE) -> 20397 | E80: =VLOOKUP(A80,'P&L Data'!A80:E222,5,FALSE) -> 0.71
A81: Covid-19 Housekeeping Supplies | B81: =VLOOKUP(A81,'P&L Data'!A81:E223,2,FALSE) -> 0 | C81: =VLOOKUP(A81,'P&L Data'!A81:E223,3,FALSE) -> 0 | D81: =VLOOKUP(A81,'P&L Data'!A81:E223,4,FALSE) -> 0 | E81: =VLOOKUP(A81,'P&L Data'!A81:E223,5,FALSE) -> 0
A82: Laundry Supplies | B82: =VLOOKUP(A82,'P&L Data'!A82:E224,2,FALSE) -> 4667 | C82: =VLOOKUP(A82,'P&L Data'!A82:E224,3,FALSE) -> 0.16 | D82: =VLOOKUP(A82,'P&L Data'!A82:E224,4,FALSE) -> 4667 | E82: =VLOOKUP(A82,'P&L Data'!A82:E224,5,FALSE) -> 0.16
A83: Linen Replacement | B83: =VLOOKUP(A83,'P&L Data'!A83:E225,2,FALSE) -> 8525 | C83: =VLOOKUP(A83,'P&L Data'!A83:E225,3,FALSE) -> 0.3 | D83: =VLOOKUP(A83,'P&L Data'!A83:E225,4,FALSE) -> 8525 | E83: =VLOOKUP(A83,'P&L Data'!A83:E225,5,FALSE) -> 0.3
A84: Maintenance Supplies | B84: =VLOOKUP(A84,'P&L Data'!A84:E226,2,FALSE) -> 30250 | C84: =VLOOKUP(A84,'P&L Data'!A84:E226,3,FALSE) -> 1.06 | D84: =VLOOKUP(A84,'P&L Data'!A84:E226,4,FALSE) -> 30250 | E84: =VLOOKUP(A84,'P&L Data'!A84:E226,5,FALSE) -> 1.06
A85: Maintenance Services | B85: =VLOOKUP(A85,'P&L Data'!A85:E227,2,FALSE) -> 207209 | C85: =VLOOKUP(A85,'P&L Data'!A85:E227,3,FALSE) -> 7.24 | D85: =VLOOKUP(A85,'P&L Data'!A85:E227,4,FALSE) -> 207209 | E85: =VLOOKUP(A85,'P&L Data'!A85:E227,5,FALSE) -> 7.24
A86: Lawn & Snow Removal Services | B86: =VLOOKUP(A86,'P&L Data'!A86:E228,2,FALSE) -> 8600 | C86: =VLOOKUP(A86,'P&L Data'!A86:E228,3,FALSE) -> 0.3 | D86: =VLOOKUP(A86,'P&L Data'!A86:E228,4,FALSE) -> 8600 | E86: =VLOOKUP(A86,'P&L Data'!A86:E228,5,FALSE) -> 0.3
A87: Scavenger | B87: =VLOOKUP(A87,'P&L Data'!A87:E229,2,FALSE) -> 16218 | C87: =VLOOKUP(A87,'P&L Data'!A87:E229,3,FALSE) -> 0.57 | D87: =VLOOKUP(A87,'P&L Data'!A87:E229,4,FALSE) -> 16218 | E87: =VLOOKUP(A87,'P&L Data'!A87:E229,5,FALSE) -> 0.57
... A91: TOTAL House & Plant Costs | B91: =VLOOKUP(A91,'P&L Data'!A91:E233,2,FALSE) -> 733852 | C91: =VLOOKUP(A91,'P&L Data'!A91:E233,3,FALSE) -> 25.63 | D91: =VLOOKUP(A91,'P&L Data'!A91:E233,4,FALSE) -> 733852 | E91: =VLOOKUP(A91,'P&L Data'!A91:E233,5,FALSE) -> 25.63
A92: Food & Nutrition
A93: Payroll Dietary | B93: =VLOOKUP(A93,'P&L Data'!A93:E235,2,FALSE) -> 336433 | C93: =VLOOKUP(A93,'P&L Data'!A93:E235,3,FALSE) -> 11.75 | D93: =VLOOKUP(A93,'P&L Data'!A93:E235,4,FALSE) -> 336433 | E93: =VLOOKUP(A93,'P&L Data'!A93:E235,5,FALSE) -> 11.75
A94: Food | B94: =VLOOKUP(A94,'P&L Data'!A94:E236,2,FALSE) -> 229970 | C94: =VLOOKUP(A94,'P&L Data'!A94:E236,3,FALSE) -> 8.03 | D94: =VLOOKUP(A94,'P&L Data'!A94:E236,4,FALSE) -> 229970 | E94: =VLOOKUP(A94,'P&L Data'!A94:E236,5,FALSE) -> 8.03
A95: Food Supplements | B95: =VLOOKUP(A95,'P&L Data'!A95:E237,2,FALSE) -> 16972 | C95: =VLOOKUP(A95,'P&L Data'!A95:E237,3,FALSE) -> 0.59 | D95: =VLOOKUP(A95,'P&L Data'!A95:E237,4,FALSE) -> 16972 | E95: =VLOOKUP(A95,'P&L Data'!A95:E237,5,FALSE) -> 0.59
A96: Dietary Supplies | B96: =VLOOKUP(A96,'P&L Data'!A96:E238,2,FALSE) -> 27844 | C96: =VLOOKUP(A96,'P&L Data'!A96:E238,3,FALSE) -> 0.97 | D96: =VLOOKUP(A96,'P&L Data'!A96:E238,4,FALSE) -> 27844 | E96: =VLOOKUP(A96,'P&L Data'!A96:E238,5,FALSE) -> 0.97
A97: Covid-19 Dietary Supplies | B97: =VLOOKUP(A97,'P&L Data'!A97:E239,2,FALSE) -> 0 | C97: =VLOOKUP(A97,'P&L Data'!A97:E239,3,FALSE) -> 0 | D97: =VLOOKUP(A97,'P&L Data'!A97:E239,4,FALSE) -> 0 | E97: =VLOOKUP(A97,'P&L Data'!A97:E239,5,FALSE) -> 0
A98: Dietary Consultant | B98: =VLOOKUP(A98,'P&L Data'!A98:E240,2,FALSE) -> 760 | C98: =VLOOKUP(A98,'P&L Data'!A98:E240,3,FALSE) -> 0.03 | D98: =VLOOKUP(A98,'P&L Data'!A98:E240,4,FALSE) -> 760 | E98: =VLOOKUP(A98,'P&L Data'!A98:E240,5,FALSE) -> 0.03
A99: TOTAL Food & Nutrition | B99: =VLOOKUP(A99,'P&L Data'!A99:E241,2,FALSE) -> 611979 | C99: =VLOOKUP(A99,'P&L Data'!A99:E241,3,FALSE) -> 21.38 | D99: =VLOOKUP(A99,'P&L Data'!A99:E241,4,FALSE) -> 611979 | E99: =VLOOKUP(A99,'P&L Data'!A99:E241,5,FALSE) -> 21.38
A100: Employee Welfare Costs
A101: Payroll Taxes | B101: =VLOOKUP(A101,'P&L Data'!A101:E243,2,FALSE) -> 396658 | C101: =VLOOKUP(A101,'P&L Data'!A101:E243,3,FALSE) -> 13.86 | D101: =VLOOKUP(A101,'P&L Data'!A101:E243,4,FALSE) -> 396658 | E101: =VLOOKUP(A101,'P&L Data'!A101:E243,5,FALSE) -> 13.86
A102: Workmans Comp Insurance | B102: =VLOOKUP(A102,'P&L Data'!A102:E244,2,FALSE) -> 37669 | C102: =VLOOKUP(A102,'P&L Data'!A102:E244,3,FALSE) -> 1.32 | D102: =VLOOKUP(A102,'P&L Data'!A102:E244,4,FALSE) -> 37669 | E102: =VLOOKUP(A102,'P&L Data'!A102:E244,5,FALSE) -> 1.32
A103: Employee Benefits | B103: =VLOOKUP(A103,'P&L Data'!A103:E245,2,FALSE) -> 18006 | C103: =VLOOKUP(A103,'P&L Data'!A103:E245,3,FALSE) -> 0.63 | D103: =VLOOKUP(A103,'P&L Data'!A103:E245,4,FALSE) -> 18006 | E103: =VLOOKUP(A103,'P&L Data'!A103:E245,5,FALSE) -> 0.63
A104: Employee Insurance | B104: =VLOOKUP(A104,'P&L Data'!A104:E246,2,FALSE) -> 119935 | C104: =VLOOKUP(A104,'P&L Data'!A104:E246,3,FALSE) -> 4.19 | D104: =VLOOKUP(A104,'P&L Data'!A104:E246,4,FALSE) -> 119935 | E104: =VLOOKUP(A104,'P&L Data'!A104:E246,5,FALSE) -> 4.19
A105: Education & Seminars | B105: =VLOOKUP(A105,'P&L Data'!A105:E247,2,FALSE) -> 6635 | C105: =VLOOKUP(A105,'P&L Data'!A105:E247,3,FALSE) -> 0.23 | D105: =VLOOKUP(A105,'P&L Data'!A105:E247,4,FALSE) -> 6635 | E105: =VLOOKUP(A105,'P&L Data'!A105:E247,5,FALSE) -> 0.23
A106: Pension | B106: =VLOOKUP(A106,'P&L Data'!A106:E248,2,FALSE) -> 32297 | C106: =VLOOKUP(A106,'P&L Data'!A106:E248,3,FALSE) -> 1.13 | D106: =VLOOKUP(A106,'P&L Data'!A106:E248,4,FALSE) -> 32297 | E106: =VLOOKUP(A106,'P&L Data'!A106:E248,5,FALSE) -> 1.13
A107: TOTAL Employee Welfare Costs | B107: =VLOOKUP(A107,'P&L Data'!A107:E249,2,FALSE) -> 611200 | C107: =VLOOKUP(A107,'P&L Data'!A107:E249,3,FALSE) -> 21.35 | D107: =VLOOKUP(A107,'P&L Data'!A107:E249,4,FALSE) -> 611200 | E107: =VLOOKUP(A107,'P&L Data'!A107:E249,5,FALSE) -> 21.35
A108: General & Administrative
A109: Payroll Administrative | B109: =VLOOKUP(A109,'P&L Data'!A109:E251,2,FALSE) -> 150615 | C109: =VLOOKUP(A109,'P&L Data'!A109:E251,3,FALSE) -> 5.26 | D109: =VLOOKUP(A109,'P&L Data'!A109:E251,4,FALSE) -> 150615 | E109: =VLOOKUP(A109,'P&L Data'!A109:E251,5,FALSE) -> 5.26
A110: Payroll Office | B110: =VLOOKUP(A110,'P&L Data'!A110:E252,2,FALSE) -> 101094 | C110: =VLOOKUP(A110,'P&L Data'!A110:E252,3,FALSE) -> 3.53 | D110: =VLOOKUP(A110,'P&L Data'!A110:E252,4,FALSE) -> 101094 | E110: =VLOOKUP(A110,'P&L Data'!A110:E252,5,FALSE) -> 3.53
A111: Payroll Marketing | B111: =VLOOKUP(A111,'P&L Data'!A111:E253,2,FALSE) -> 0 | C111: =VLOOKUP(A111,'P&L Data'!A111:E253,3,FALSE) -> 0 | D111: =VLOOKUP(A111,'P&L Data'!A111:E253,4,FALSE) -> 0 | E111: =VLOOKUP(A111,'P&L Data'!A111:E253,5,FALSE) -> 0
A112: Marketing Consultant | B112: =VLOOKUP(A112,'P&L Data'!A112:E254,2,FALSE) -> 11292 | C112: =VLOOKUP(A112,'P&L Data'!A112:E254,3,FALSE) -> 0.39 | D112: =VLOOKUP(A112,'P&L Data'!A112:E254,4,FALSE) -> 11292 | E112: =VLOOKUP(A112,'P&L Data'!A112:E254,5,FALSE) -> 0.39
A113: General Insurance | B113: =VLOOKUP(A113,'P&L Data'!A113:E255,2,FALSE) -> 68480 | C113: =VLOOKUP(A113,'P&L Data'!A113:E255,3,FALSE) -> 2.39 | D113: =VLOOKUP(A113,'P&L Data'!A113:E255,4,FALSE) -> 68480 | E113: =VLOOKUP(A113,'P&L Data'!A113:E255,5,FALSE) -> 2.39
A114: Office Supplies | B114: =VLOOKUP(A114,'P&L Data'!A114:E256,2,FALSE) -> 11708 | C114: =VLOOKUP(A114,'P&L Data'!A114:E256,3,FALSE) -> 0.41 | D114: =VLOOKUP(A114,'P&L Data'!A114:E256,4,FALSE) -> 11708 | E114: =VLOOKUP(A114,'P&L Data'!A114:E256,5,FALSE) -> 0.41
...

Sheet P&L Detail Trending
A1: =BS!A1 -> Allure of Peru
A2: Income Statement Detail Trending
A3: ='P&L Trending Data'!B4 -> 1/1/2025 to 12/31/2025
B5: ='DTF & QuickCalc'!A72 -> 45658 | D5: =EDATE(B5,1) -> 45689 | F5: =EDATE(D5,1) -> 45717 | H5: =EDATE(F5,1) -> 45748 | J5: =EDATE(H5,1) -> 45778 | L5: =EDATE(J5,1) -> 45809 | N5: =EDATE(L5,1) -> 45839 | P5: =EDATE(N5,1) -> 45870 | R5: =EDATE(P5,1) -> 45901 | T5: =EDATE(R5,1) -> 45931 | V5: =EDATE(T5,1) -> 45962 | X5: =EDATE(V5,1) -> 45992 | Z5: TOTALS
B6: Actual $ | C6: Actual / Day | D6: Actual $ | E6: Actual / Day | F6: Actual $ | G6: Actual / Day | H6: Actual $ | I6: Actual / Day | J6: Actual $ | K6: Actual / Day | L6: Actual $ | M6: Actual / Day | N6: Actual $ | O6: Actual / Day | P6: Actual $ | Q6: Actual / Day | R6: Actual $ | S6: Actual / Day | T6: Actual $ | U6: Actual / Day | V6: Actual $ | W6: Actual / Day | X6: Actual $ | Y6: Actual / Day | Z6: Actual $ | AA6: Actual / Day
A7: Revenue
A8: Medicaid | B8: {=_xlfn.XLOOKUP(A8,'P&L Trending Data'!A9:A149,'P&L Trending Data'!B9:Y149)} -> 388276 | C8: 276.75 | D8: 408258 | E8: 279.82 | F8: 406113 | G8: 278.35 | H8: 370960 | I8: 282.53 | J8: 371972 | K8: 282.87 | L8: 407087 | M8: 282.11 | N8: 395127 | O8: 295.98 | P8: 413088 | Q8: 295.7 | R8: 410913 | S8: 296.05 | T8: 369135 | U8: 262.73 | V8: 320350 | W8: 261.3 | X8: 389012 | Y8: 262.85 | Z8: =B8+D8+F8+H8+J8+L8+N8+P8+R8+T8+V8+X8 -> 4650291 | AA8: =C8+E8+G8+I8+K8+M8+O8+Q8+S8+U8+W8+Y8 -> 3357.04
A9: Hospice | B9: {=_xlfn.XLOOKUP(A9,'P&L Trending Data'!A10:A150,'P&L Trending Data'!B10:Y150)} -> 23801 | C9: 276.76 | D9: 26023 | E9: 279.82 | F9: 33402 | G9: 278.35 | H9: 32504 | I9: 282.64 | J9: 37308 | K9: 282.64 | L9: 18649 | M9: 286.91 | N9: 27562 | O9: 296.37 | P9: 41492 | Q9: 296.37 | R9: 42085 | S9: 296.37 | T9: 37000 | U9: 262.41 | V9: 30470 | W9: 253.92 | X9: 54056 | Y9: 262.41 | Z9: =B9+D9+F9+H9+J9+L9+N9+P9+R9+T9+V9+X9 -> 404352 | AA9: =C9+E9+G9+I9+K9+M9+O9+Q9+S9+U9+W9+Y9 -> 3354.97
A10: Medicare A | B10: {=_xlfn.XLOOKUP(A10,'P&L Trending Data'!A11:A151,'P&L Trending Data'!B11:Y151)} -> 276629 | C10: 726.06 | D10: 190410 | E10: 721.25 | F10: 271459 | G10: 696.05 | H10: 231688 | I10: 675.47 | J10: 234861 | K10: 727.13 | L10: 188683 | M10: 681.16 | N10: 195908 | O10: 653.03 | P10: 150286 | Q10: 615.93 | R10: 180454 | S10: 649.11 | T10: 173470 | U10: 649.7 | V10: 165678 | W10: 676.24 | X10: 221112 | Y10: 684.56 | Z10: =B10+D10+F10+H10+J10+L10+N10+P10+R10+T10+V10+X10 -> 2480638 | AA10: =C10+E10+G10+I10+K10+M10+O10+Q10+S10+U10+W10+Y10 -> 8155.69
A11: Commercial Insurance | B11: {=_xlfn.XLOOKUP(A11,'P&L Trending Data'!A12:A152,'P&L Trending Data'!B12:Y152)} -> 106231 | C11: 440.79 | D11: 113904 | E11: 433.09 | F11: 112617 | G11: 415.56 | H11: 58193 | I11: 476.99 | J11: 45675 | K11: 400.66 | L11: 43336 | M11: 577.81 | N11: 52479 | O11: 460.34 | P11: 77254 | Q11: 508.25 | R11: 91873 | S11: 419.51 | T11: 53007 | U11: 486.3 | V11: 50226 | W11: 469.41 | X11: 119379 | Y11: 523.59 | Z11: =B11+D11+F11+H11+J11+L11+N11+P11+R11+T11+V11+X11 -> 924174 | AA11: =C11+E11+G11+I11+K11+M11+O11+Q11+S11+U11+W11+Y11 -> 5612.3
A12: Private Pay | B12: {=_xlfn.XLOOKUP(A12,'P&L Trending Data'!A13:A153,'P&L Trending Data'!B13:Y153)} -> 138594 | C12: 304.6 | D12: 98035 | E12: 304.46 | F12: 102135 | G12: 289.34 | H12: 103587 | I12: 287.74 | J12: 167586 | K12: 287.95 | L12: 140418 | M12: 312.04 | N12: 155881 | O12: 292.46 | P12: 123863 | Q12: 306.59 | R12: 130438 | S12: 299.86 | T12: 104916 | U12: 303.22 | V12: 120531 | W12: 269.64 | X12: 60990 | Y12: 285 | Z12: =B12+D12+F12+H12+J12+L12+N12+P12+R12+T12+V12+X12 -> 1446974 | AA12: =C12+E12+G12+I12+K12+M12+O12+Q12+S12+U12+W12+Y12 -> 3542.9
A13: Veteran Affairs | B13: {=_xlfn.XLOOKUP(A13,'P&L Trending Data'!A14:A154,'P&L Trending Data'!B14:Y154)} -> 0 | C13: 0 | D13: 0 | E13: 0 | F13: 0 | G13: 0 | H13: 0 | I13: 0 | J13: 0 | K13: 0 | L13: 0 | M13: 0 | N13: 0 | O13: 0 | P13: 0 | Q13: 0 | R13: 0 | S13: 0 | T13: 0 | U13: 0 | V13: 0 | W13: 0 | X13: 0 | Y13: 0 | Z13: =B13+D13+F13+H13+J13+L13+N13+P13+R13+T13+V13+X13 -> 0 | AA13: =C13+E13+G13+I13+K13+M13+O13+Q13+S13+U13+W13+Y13 -> 0
A14: Medicare / Managed Care B | B14: {=_xlfn.XLOOKUP(A14,'P&L Trending Data'!A15:A155,'P&L Trending Data'!B15:Y155)} -> 22407 | C14: 0 | D14: 1600 | E14: 0 | F14: 38819 | G14: 0 | H14: 21411 | I14: 0 | J14: 26503 | K14: 0 | L14: 27290 | M14: 0 | N14: 31718 | O14: 0 | P14: 29662 | Q14: 0 | R14: 24022 | S14: 0 | T14: 32306 | U14: 0 | V14: 18907 | W14: 0 | X14: 22468 | Y14: 0 | Z14: =B14+D14+F14+H14+J14+L14+N14+P14+R14+T14+V14+X14 -> 297113 | AA14: =C14+E14+G14+I14+K14+M14+O14+Q14+S14+U14+W14+Y14 -> 0
A15: Private Pay Independent Living | B15: {=_xlfn.XLOOKUP(A15,'P&L Trending Data'!A16:A156,'P&L Trending Data'!B16:Y156)} -> 0 | C15: 0 | D15: 0 | E15: 0 | F15: 0 | G15: 0 | H15: 0 | I15: 0 | J15: 0 | K15: 0 | L15: 0 | M15: 0 | N15: 0 | O15: 0 | P15: 0 | Q15: 0 | R15: 0 | S15: 0 | T15: 0 | U15: 0 | V15: 0 | W15: 0 | X15: 0 | Y15: 0 | Z15: =B15+D15+F15+H15+J15+L15+N15+P15+R15+T15+V15+X15 -> 0 | AA15: =C15+E15+G15+I15+K15+M15+O15+Q15+S15+U15+W15+Y15 -> 0
A16: Home Care Income | B16: {=_xlfn.XLOOKUP(A16,'P&L Trending Data'!A17:A157,'P&L Trending Data'!B17:Y157)} -> 0 | C16: 0 | D16: 0 | E16: 0 | F16: 0 | G16: 0 | H16: 0 | I16: 0 | J16: 0 | K16: 0 | L16: 0 | M16: 0 | N16: 0 | O16: 0 | P16: 0 | Q16: 0 | R16: 0 | S16: 0 | T16: 0 | U16: 0 | V16: 0 | W16: 0 | X16: 0 | Y16: 0 | Z16: =B16+D16+F16+H16+J16+L16+N16+P16+R16+T16+V16+X16 -> 0 | AA16: =C16+E16+G16+I16+K16+M16+O16+Q16+S16+U16+W16+Y16 -> 0
A17: Daily Training Program | B17: {=_xlfn.XLOOKUP(A17,'P&L Trending Data'!A18:A158,'P&L Trending Data'!B18:Y158)} -> 0 | C17: 0 | D17: 0 | E17: 0 | F17: 0 | G17: 0 | H17: 0 | I17: 0 | J17: 0 | K17: 0 | L17: 0 | M17: 0 | N17: 0 | O17: 0 | P17: 0 | Q17: 0 | R17: 0 | S17: 0 | T17: 0 | U17: 0 | V17: 0 | W17: 0 | X17: 0 | Y17: 0 | Z17: =B17+D17+F17+H17+J17+L17+N17+P17+R17+T17+V17+X17 -> 0 | AA17: =C17+E17+G17+I17+K17+M17+O17+Q17+S17+U17+W17+Y17 -> 0
A18: Other | B18: {=_xlfn.XLOOKUP(A18,'P&L Trending Data'!A19:A159,'P&L Trending Data'!B19:Y159)} -> 313 | C18: 0 | D18: 1116 | E18: 0 | F18: 84 | G18: 0 | H18: 82 | I18: 0 | J18: 96 | K18: 0 | L18: 114 | M18: 0 | N18: 87 | O18: 0 | P18: 1923 | Q18: 0 | R18: 139 | S18: 0 | T18: 635 | U18: 0 | V18: 578 | W18: 0 | X18: 108 | Y18: 0 | Z18: =B18+D18+F18+H18+J18+L18+N18+P18+R18+T18+V18+X18 -> 5275 | AA18: =C18+E18+G18+I18+K18+M18+O18+Q18+S18+U18+W18+Y18 -> 0
A19: Stimulus Income | B19: {=_xlfn.XLOOKUP(A19,'P&L Trending Data'!A20:A160,'P&L Trending Data'!B20:Y160)} -> 0 | C19: 0 | D19: 0 | E19: 0 | F19: 0 | G19: 0 | H19: 0 | I19: 0 | J19: 0 | K19: 0 | L19: 0 | M19: 0 | N19: 0 | O19: 0 | P19: 0 | Q19: 0 | R19: 0 | S19: 0 | T19: 0 | U19: 0 | V19: 0 | W19: 0 | X19: 0 | Y19: 0 | Z19: =B19+D19+F19+H19+J19+L19+N19+P19+R19+T19+V19+X19 -> 0 | AA19: =C19+E19+G19+I19+K19+M19+O19+Q19+S19+U19+W19+Y19 -> 0
... A21: TOTAL Revenue | B21: {=_xlfn.XLOOKUP(A21,'P&L Trending Data'!A22:A162,'P&L Trending Data'!B22:Y162)} -> 974758 | C21: 379.87 | D21: 857852 | E21: 357.29 | F21: 983136 | G21: 379.15 | H21: 835326 | I21: 370.76 | J21: 900903 | K21: 365.33 | L21: 842479 | M21: 364.71 | N21: 877308 | O21: 369.39 | P21: 856113 | Q21: 366.33 | R21: 898468 | S21: 364.93 | T21: 789014 | U21: 347.89 | V21: 723906 | W21: 337.49 | X21: 884982 | Y21: 361.07 | Z21: =B21+D21+F21+H21+J21+L21+N21+P21+R21+T21+V21+X21 -> 10424245 | AA21: =C21+E21+G21+I21+K21+M21+O21+Q21+S21+U21+W21+Y21 -> 4364.21
A22: Patient Days
A23: Medicaid | B23: {=_xlfn.XLOOKUP(A23,'P&L Trending Data'!A24:A164,'P&L Trending Data'!B24:Y164)} -> 1445 | C23: 0 | D23: 1459 | E23: 0 | F23: 1452 | G23: 0 | H23: 1313 | I23: 0 | J23: 1315 | K23: 0 | L23: 1449 | M23: 0 | N23: 1335 | O23: 0 | P23: 1397 | Q23: 0 | R23: 1388 | S23: 0 | T23: 1405 | U23: 0 | V23: 1225 | W23: 0 | X23: 1480 | Y23: 0 | Z23: =B23+D23+F23+H23+J23+L23+N23+P23+R23+T23+V23+X23 -> 16663 | AA23: -
A24: Hospice | B24: {=_xlfn.XLOOKUP(A24,'P&L Trending Data'!A25:A165,'P&L Trending Data'!B25:Y165)} -> 86 | C24: 0 | D24: 93 | E24: 0 | F24: 120 | G24: 0 | H24: 115 | I24: 0 | J24: 132 | K24: 0 | L24: 65 | M24: 0 | N24: 93 | O24: 0 | P24: 140 | Q24: 0 | R24: 142 | S24: 0 | T24: 141 | U24: 0 | V24: 120 | W24: 0 | X24: 206 | Y24: 0 | Z24: =B24+D24+F24+H24+J24+L24+N24+P24+R24+T24+V24+X24 -> 1453 | AA24: -
A25: Medicare A | B25: {=_xlfn.XLOOKUP(A25,'P&L Trending Data'!A26:A166,'P&L Trending Data'!B26:Y166)} -> 381 | C25: 0 | D25: 264 | E25: 0 | F25: 390 | G25: 0 | H25: 343 | I25: 0 | J25: 323 | K25: 0 | L25: 277 | M25: 0 | N25: 300 | O25: 0 | P25: 244 | Q25: 0 | R25: 278 | S25: 0 | T25: 267 | U25: 0 | V25: 245 | W25: 0 | X25: 323 | Y25: 0 | Z25: =B25+D25+F25+H25+J25+L25+N25+P25+R25+T25+V25+X25 -> 3635 | AA25: -
A26: Commercial Insurance | B26: {=_xlfn.XLOOKUP(A26,'P&L Trending Data'!A27:A167,'P&L Trending Data'!B27:Y167)} -> 241 | C26: 0 | D26: 263 | E26: 0 | F26: 271 | G26: 0 | H26: 122 | I26: 0 | J26: 114 | K26: 0 | L26: 75 | M26: 0 | N26: 114 | O26: 0 | P26: 152 | Q26: 0 | R26: 219 | S26: 0 | T26: 109 | U26: 0 | V26: 107 | W26: 0 | X26: 228 | Y26: 0 | Z26: =B26+D26+F26+H26+J26+L26+N26+P26+R26+T26+V26+X26 -> 2015 | AA26: -
A27: Private Pay | B27: {=_xlfn.XLOOKUP(A27,'P&L Trending Data'!A28:A168,'P&L Trending Data'!B28:Y168)} -> 455 | C27: 0 | D27: 322 | E27: 0 | F27: 353 | G27: 0 | H27: 360 | I27: 0 | J27: 582 | K27: 0 | L27: 450 | M27: 0 | N27: 533 | O27: 0 | P27: 404 | Q27: 0 | R27: 435 | S27: 0 | T27: 340 | U27: 0 | V27: 442 | W27: 0 | X27: 218 | Y27: 0 | Z27: =B27+D27+F27+H27+J27+L27+N27+P27+R27+T27+V27+X27 -> 4894 | AA27: -
A28: Veteran Affairs | B28: {=_xlfn.XLOOKUP(A28,'P&L Trending Data'!A29:A169,'P&L Trending Data'!B29:Y169)} -> 0 | C28: 0 | D28: 0 | E28: 0 | F28: 0 | G28: 0 | H28: 0 | I28: 0 | J28: 0 | K28: 0 | L28: 0 | M28: 0 | N28: 0 | O28: 0 | P28: 0 | Q28: 0 | R28: 0 | S28: 0 | T28: 0 | U28: 0 | V28: 0 | W28: 0 | X28: 0 | Y28: 0 | Z28: =B28+D28+F28+H28+J28+L28+N28+P28+R28+T28+V28+X28 -> 0 | AA28: -
A29: Independent Living | B29: {=_xlfn.XLOOKUP(A29,'P&L Trending Data'!A30:A170,'P&L Trending Data'!B30:Y170)} -> 0 | C29: 0 | D29: 0 | E29: 0 | F29: 0 | G29: 0 | H29: 0 | I29: 0 | J29: 0 | K29: 0 | L29: 0 | M29: 0 | N29: 0 | O29: 0 | P29: 0 | Q29: 0 | R29: 0 | S29: 0 | T29: 0 | U29: 0 | V29: 0 | W29: 0 | X29: 0 | Y29: 0 | Z29: =B29+D29+F29+H29+J29+L29+N29+P29+R29+T29+V29+X29 -> 0 | AA29: -
A30: TOTAL Patient Days | B30: {=_xlfn.XLOOKUP(A30,'P&L Trending Data'!A31:A171,'P&L Trending Data'!B31:Y171)} -> 2608 | C30: 0 | D30: 2401 | E30: 0 | F30: 2586 | G30: 0 | H30: 2253 | I30: 0 | J30: 2466 | K30: 0 | L30: 2316 | M30: 0 | N30: 2375 | O30: 0 | P30: 2337 | Q30: 0 | R30: 2462 | S30: 0 | T30: 2262 | U30: 0 | V30: 2139 | W30: 0 | X30: 2455 | Y30: 0 | Z30: =B30+D30+F30+H30+J30+L30+N30+P30+R30+T30+V30+X30 -> 28660 | AA30: =C30+E30+G30+I30+K30+M30+O30+Q30+S30+U30+W30+Y30 -> 0
A31: Nursing & Medical
A32: Director Of Nursing | B32: {=_xlfn.XLOOKUP(A32,'P&L Trending Data'!A33:A173,'P&L Trending Data'!B33:Y173)} -> 9212 | C32: 3.59 | D32: 7717 | E32: 3.21 | F32: 8952 | G32: 3.45 | H32: 8492 | I32: 3.77 | J32: 8997 | K32: 3.65 | L32: 8509 | M32: 3.68 | N32: 10067 | O32: 4.24 | P32: 8597 | Q32: 3.68 | R32: 8438 | S32: 3.43 | T32: 9040 | U32: 3.99 | V32: 9054 | W32: 4.22 | X32: 8871 | Y32: 3.62 | Z32: =B32+D32+F32+H32+J32+L32+N32+P32+R32+T32+V32+X32 -> 105946 | AA32: =C32+E32+G32+I32+K32+M32+O32+Q32+S32+U32+W32+Y32 -> 44.53
A33: Assistant Director Of Nursing | B33: {=_xlfn.XLOOKUP(A33,'P&L Trending Data'!A34:A174,'P&L Trending Data'!B34:Y174)} -> 7877 | C33: 3.07 | D33: 7354 | E33: 3.06 | F33: 7832 | G33: 3.02 | H33: 7552 | I33: 3.35 | J33: 8298 | K33: 3.36 | L33: 7532 | M33: 3.26 | N33: 7601 | O33: 3.2 | P33: 7638 | Q33: 3.27 | R33: 6659 | S33: 2.7 | T33: 1904 | U33: 0.84 | V33: 6738 | W33: 3.14 | X33: 8630 | Y33: 3.52 | Z33: =B33+D33+F33+H33+J33+L33+N33+P33+R33+T33+V33+X33 -> 85615 | AA33: =C33+E33+G33+I33+K33+M33+O33+Q33+S33+U33+W33+Y33 -> 35.79
A34: Payroll RN | B34: {=_xlfn.XLOOKUP(A34,'P&L Trending Data'!A35:A175,'P&L Trending Data'!B35:Y175)} -> 65236 | C34: 25.42 | D34: 60365 | E34: 25.14 | F34: 68632 | G34: 26.47 | H34: 69671 | I34: 30.92 | J34: 71475 | K34: 28.98 | L34: 69227 | M34: 29.97 | N34: 72869 | O34: 30.68 | P34: 66824 | Q34: 28.59 | R34: 64087 | S34: 26.03 | T34: 66427 | U34: 29.29 | V34: 64275 | W34: 29.97 | X34: 61682 | Y34: 25.17 | Z34: =B34+D34+F34+H34+J34+L34+N34+P34+R34+T34+V34+X34 -> 800770 | AA34: =C34+E34+G34+I34+K34+M34+O34+Q34+S34+U34+W34+Y34 -> 336.63
A35: Payroll LPN | B35: {=_xlfn.XLOOKUP(A35,'P&L Trending Data'!A36:A176,'P&L Trending Data'!B36:Y176)} -> 36740 | C35: 14.32 | D35: 36131 | E35: 15.05 | F35: 35983 | G35: 13.88 | H35: 33791 | I35: 15 | J35: 33989 | K35: 13.78 | L35: 40210 | M35: 17.41 | N35: 34691 | O35: 14.61 | P35: 34825 | Q35: 14.9 | R35: 35716 | S35: 14.51 | T35: 40897 | U35: 18.03 | V35: 39372 | W35: 18.36 | X35: 40479 | Y35: 16.52 | Z35: =B35+D35+F35+H35+J35+L35+N35+P35+R35+T35+V35+X35 -> 442824 | AA35: =C35+E35+G35+I35+K35+M35+O35+Q35+S35+U35+W35+Y35 -> 186.37
A36: Payroll Aides & Orderlies | B36: {=_xlfn.XLOOKUP(A36,'P&L Trending Data'!A37:A177,'P&L Trending Data'!B37:Y177)} -> 158997 | C36: 61.96 | D36: 131266 | E36: 54.67 | F36: 156709 | G36: 60.44 | H36: 157935 | I36: 70.1 | J36: 171345 | K36: 69.48 | L36: 162985 | M36: 70.56 | N36: 155904 | O36: 65.64 | P36: 145993 | Q36: 62.47 | R36: 154712 | S36: 62.84 | T36: 142246 | U36: 62.72 | V36: 151314 | W36: 70.54 | X36: 172369 | Y36: 70.33 | Z36: =B36+D36+F36+H36+J36+L36+N36+P36+R36+T36+V36+X36 -> 1861775 | AA36: =C36+E36+G36+I36+K36+M36+O36+Q36+S36+U36+W36+Y36 -> 781.75
A37: Payroll Nursing Clerical | B37: {=_xlfn.XLOOKUP(A37,'P&L Trending Data'!A38:A178,'P&L Trending Data'!B38:Y178)} -> 7723 | C37: 3.01 | D37: 7800 | E37: 3.25 | F37: 7670 | G37: 2.96 | H37: 7340 | I37: 3.26 | J37: 8444 | K37: 3.42 | L37: 7123 | M37: 3.08 | N37: 7715 | O37: 3.25 | P37: 7615 | Q37: 3.26 | R37: 7479 | S37: 3.04 | T37: 7624 | U37: 3.36 | V37: 7485 | W37: 3.49 | X37: 8478 | Y37: 3.46 | Z37: =B37+D37+F37+H37+J37+L37+N37+P37+R37+T37+V37+X37 -> 92496 | AA37: =C37+E37+G37+I37+K37+M37+O37+Q37+S37+U37+W37+Y37 -> 38.84
A38: Payroll Medical Records | B38: {=_xlfn.XLOOKUP(A38,'P&L Trending Data'!A39:A179,'P&L Trending Data'!B39:Y179)} -> 0 | C38: 0 | D38: 0 | E38: 0 | F38: 0 | G38: 0 | H38: 0 | I38: 0 | J38: 0 | K38: 0 | L38: 0 | M38: 0 | N38: 0 | O38: 0 | P38: 0 | Q38: 0 | R38: 0 | S38: 0 | T38: 0 | U38: 0 | V38: 0 | W38: 0 | X38: 0 | Y38: 0 | Z38: =B38+D38+F38+H38+J38+L38+N38+P38+R38+T38+V38+X38 -> 0 | AA38: =C38+E38+G38+I38+K38+M38+O38+Q38+S38+U38+W38+Y38 -> 0
A39: Contract RN | B39: {=_xlfn.XLOOKUP(A39,'P&L Trending Data'!A40:A180,'P&L Trending Data'!B40:Y180)} -> 24990 | C39: 9.74 | D39: 10031 | E39: 4.18 | F39: 15243 | G39: 5.88 | H39: 4530 | I39: 2.01 | J39: 15581 | K39: 6.32 | L39: 13713 | M39: 5.94 | N39: 13755 | O39: 5.79 | P39: 5793 | Q39: 2.48 | R39: 26888 | S39: 10.92 | T39: 12299 | U39: 5.42 | V39: 8223 | W39: 3.83 | X39: 26644 | Y39: 10.87 | Z39: =B39+D39+F39+H39+J39+L39+N39+P39+R39+T39+V39+X39 -> 177690 | AA39: =C39+E39+G39+I39+K39+M39+O39+Q39+S39+U39+W39+Y39 -> 73.38
A40: Contract LPN | B40: {=_xlfn.XLOOKUP(A40,'P&L Trending Data'!A41:A181,'P&L Trending Data'!B41:Y181)} -> 7758 | C40: 3.02 | D40: 1974 | E40: 0.82 | F40: 3687 | G40: 1.42 | H40: 0 | I40: 0 | J40: 1264 | K40: 0.51 | L40: 193 | M40: 0.08 | N40: 882 | O40: 0.37 | P40: 0 | Q40: 0 | R40: 0 | S40: 0 | T40: 260 | U40: 0.11 | V40: 0 | W40: 0 | X40: 2399 | Y40: 0.98 | Z40: =B40+D40+F40+H40+J40+L40+N40+P40+R40+T40+V40+X40 -> 18417 | AA40: =C40+E40+G40+I40+K40+M40+O40+Q40+S40+U40+W40+Y40 -> 7.31
A41: Contract Aides & Orderlies | B41: {=_xlfn.XLOOKUP(A41,'P&L Trending Data'!A42:A182,'P&L Trending Data'!B42:Y182)} -> 17567 | C41: 6.85 | D41: 28226 | E41: 11.76 | F41: 33572 | G41: 12.95 | H41: 11167 | I41: 4.96 | J41: 10005 | K41: 4.06 | L41: 7191 | M41: 3.11 | N41: 4771 | O41: 2.01 | P41: 3121 | Q41: 1.34 | R41: 24585 | S41: 9.99 | T41: 11843 | U41: 5.22 | V41: 3955 | W41: 1.84 | X41: 11865 | Y41: 4.84 | Z41: =B41+D41+F41+H41+J41+L41+N41+P41+R41+T41+V41+X41 -> 167868 | AA41: =C41+E41+G41+I41+K41+M41+O41+Q41+S41+U41+W41+Y41 -> 68.93
A42: Medical Supplies | B42: {=_xlfn.XLOOKUP(A42,'P&L Trending Data'!A43:A183,'P&L Trending Data'!B43:Y183)} -> 9096 | C42: 3.54 | D42: 8183 | E42: 3.41 | F42: 11766 | G42: 4.54 | H42: 8005 | I42: 3.55 | J42: 9016 | K42: 3.66 | L42: 7306 | M42: 3.16 | N42: 8808 | O42: 3.71 | P42: 7412 | Q42: 3.17 | R42: 10819 | S42: 4.39 | T42: 8067 | U42: 3.56 | V42: 8778 | W42: 4.09 | X42: 10387 | Y42: 4.24 | Z42: =B42+D42+F42+H42+J42+L42+N42+P42+R42+T42+V42+X42 -> 107643 | AA42: =C42+E42+G42+I42+K42+M42+O42+Q42+S42+U42+W42+Y42 -> 45.02
A43: Covid-19 Medical Supplies | B43: {=_xlfn.XLOOKUP(A43,'P&L Trending Data'!A44:A184,'P&L Trending Data'!B44:Y184)} -> 1662 | C43: 0.65 | D43: 372 | E43: 0.16 | F43: 0 | G43: 0 | H43: 158 | I43: 0.07 | J43: 320 | K43: 0.13 | L43: 30 | M43: 0.01 | N43: 285 | O43: 0.12 | P43: 384 | Q43: 0.16 | R43: 383 | S43: 0.16 | T43: 712 | U43: 0.31 | V43: 2534 | W43: 1.18 | X43: 1459 | Y43: 0.6 | Z43: =B43+D43+F43+H43+J43+L43+N43+P43+R43+T43+V43+X43 -> 8299 | AA43: =C43+E43+G43+I43+K43+M43+O43+Q43+S43+U43+W43+Y43 -> 3.55
... A53: TOTAL Nursing & Medical | B53: {=_xlfn.XLOOKUP(A53,'P&L Trending Data'!A54:A194,'P&L Trending Data'!B54:Y194)} -> 365224 | C53: 142.33 | D53: 325396 | E53: 135.53 | F53: 380608 | G53: 146.78 | H53: 322574 | I53: 143.18 | J53: 355789 | K53: 144.28 | L53: 340922 | M53: 147.59 | N53: 348318 | O53: 146.66 | P53: 307417 | Q53: 131.54 | R53: 359100 | S53: 145.86 | T53: 318835 | U53: 140.58 | V53: 315529 | W53: 147.1 | X53: 367862 | Y53: 150.09 | Z53: =B53+D53+F53+H53+J53+L53+N53+P53+R53+T53+V53+X53 -> 4107574 | AA53: =C53+E53+G53+I53+K53+M53+O53+Q53+S53+U53+W53+Y53 -> 1721.52
A54: Therapy & Ancillary Services
A55: Physical Therapy Services | B55: {=_xlfn.XLOOKUP(A55,'P&L Trending Data'!A56:A196,'P&L Trending Data'!B56:Y196)} -> 28242 | C55: 11.01 | D55: 23273 | E55: 9.69 | F55: 25243 | G55: 9.74 | H55: 20942 | I55: 9.29 | J55: 21526 | K55: 8.73 | L55: 19019 | M55: 8.23 | N55: 22612 | O55: 9.52 | P55: 22122 | Q55: 9.47 | R55: 23626 | S55: 9.6 | T55: 22170 | U55: 9.78 | V55: 20119 | W55: 9.38 | X55: 24973 | Y55: 10.19 | Z55: =B55+D55+F55+H55+J55+L55+N55+P55+R55+T55+V55+X55 -> 273867 | AA55: =C55+E55+G55+I55+K55+M55+O55+Q55+S55+U55+W55+Y55 -> 114.63
A56: Occupational Therapy Services | B56: {=_xlfn.XLOOKUP(A56,'P&L Trending Data'!A57:A197,'P&L Trending Data'!B57:Y197)} -> 23197 | C56: 9.04 | D56: 19030 | E56: 7.93 | F56: 23212 | G56: 8.95 | H56: 19320 | I56: 8.58 | J56: 20289 | K56: 8.23 | L56: 17772 | M56: 7.69 | N56: 19961 | O56: 8.4 | P56: 19396 | Q56: 8.3 | R56: 19165 | S56: 7.78 | T56: 19990 | U56: 8.81 | V56: 17380 | W56: 8.1 | X56: 21528 | Y56: 8.78 | Z56: =B56+D56+F56+H56+J56+L56+N56+P56+R56+T56+V56+X56 -> 240240 | AA56: =C56+E56+G56+I56+K56+M56+O56+Q56+S56+U56+W56+Y56 -> 100.59
A57: Speech Therapy Services | B57: {=_xlfn.XLOOKUP(A57,'P&L Trending Data'!A58:A198,'P&L Trending Data'!B58:Y198)} -> 3409 | C57: 1.33 | D57: 2320 | E57: 0.97 | F57: 3156 | G57: 1.22 | H57: 2119 | I57: 0.94 | J57: 1956 | K57: 0.79 | L57: 2444 | M57: 1.06 | N57: 4217 | O57: 1.78 | P57: 4109 | Q57: 1.76 | R57: 3235 | S57: 1.31 | T57: 3345 | U57: 1.47 | V57: 2008 | W57: 0.94 | X57: 1457 | Y57: 0.59 | Z57: =B57+D57+F57+H57+J57+L57+N57+P57+R57+T57+V57+X57 -> 33775 | AA57: =C57+E57+G57+I57+K57+M57+O57+Q57+S57+U57+W57+Y57 -> 14.16
A58: Pharmacy Consultant | B58: {=_xlfn.XLOOKUP(A58,'P&L Trending Data'!A59:A199,'P&L Trending Data'!B59:Y199)} -> 700 | C58: 0.27 | D58: 1512 | E58: 0.63 | F58: 1436 | G58: 0.55 | H58: 1356 | I58: 0.6 | J58: 1356 | K58: 0.55 | L58: 1300 | M58: 0.56 | N58: 1265 | O58: 0.53 | P58: 1340 | Q58: 0.57 | R58: 1292 | S58: 0.52 | T58: 1384 | U58: 0.61 | V58: 700 | W58: 0.33 | X58: 700 | Y58: 0.29 | Z58: =B58+D58+F58+H58+J58+L58+N58+P58+R58+T58+V58+X58 -> 14341 | AA58: =C58+E58+G58+I58+K58+M58+O58+Q58+S58+U58+W58+Y58 -> 6.01
A59: RX Drugs | B59: {=_xlfn.XLOOKUP(A59,'P&L Trending Data'!A60:A200,'P&L Trending Data'!B60:Y200)} -> 8000 | C59: 3.12 | D59: 8176 | E59: 3.41 | F59: 13497 | G59: 5.21 | H59: 7056 | I59: 3.13 | J59: 12407 | K59: 5.03 | L59: 4554 | M59: 1.97 | N59: 5755 | O59: 2.42 | P59: 5131 | Q59: 2.2 | R59: 3564 | S59: 1.45 | T59: 2884 | U59: 1.27 | V59: 0 | W59: 0 | X59: 0 | Y59: 0 | Z59: =B59+D59+F59+H59+J59+L59+N59+P59+R59+T59+V59+X59 -> 71024 | AA59: =C59+E59+G59+I59+K59+M59+O59+Q59+S59+U59+W59+Y59 -> 29.21
A60: Drugs Managed Care | B60: {=_xlfn.XLOOKUP(A60,'P&L Trending Data'!A61:A201,'P&L Trending Data'!B61:Y201)} -> 4000 | C60: 1.56 | D60: 6518 | E60: 2.71 | F60: 1000 | G60: 0.39 | H60: 2745 | I60: 1.22 | J60: 0 | K60: 0 | L60: 0 | M60: 0 | N60: 6057 | O60: 2.55 | P60: 6843 | Q60: 2.93 | R60: 5215 | S60: 2.12 | T60: 6566 | U60: 2.9 | V60: 0 | W60: 0 | X60: 0 | Y60: 0 | Z60: =B60+D60+F60+H60+J60+L60+N60+P60+R60+T60+V60+X60 -> 38944 | AA60: =C60+E60+G60+I60+K60+M60+O60+Q60+S60+U60+W60+Y60 -> 16.38
A61: VA - Drugs | B61: {=_xlfn.XLOOKUP(A61,'P&L Trending Data'!A62:A202,'P&L Trending Data'!B62:Y202)} -> 0 | C61: 0 | D61: 0 | E61: 0 | F61: 0 | G61: 0 | H61: 0 | I61: 0 | J61: 0 | K61: 0 | L61: 0 | M61: 0 | N61: 0 | O61: 0 | P61: 0 | Q61: 0 | R61: 0 | S61: 0 | T61: 0 | U61: 0 | V61: 0 | W61: 0 | X61: 0 | Y61: 0 | Z61: =B61+D61+F61+H61+J61+L61+N61+P61+R61+T61+V61+X61 -> 0 | AA61: =C61+E61+G61+I61+K61+M61+O61+Q61+S61+U61+W61+Y61 -> 0
A62: Radiology | B62: {=_xlfn.XLOOKUP(A62,'P&L Trending Data'!A63:A203,'P&L Trending Data'!B63:Y203)} -> 586 | C62: 0.23 | D62: 58 | E62: 0.02 | F62: 431 | G62: 0.17 | H62: 654 | I62: 0.29 | J62: 543 | K62: 0.22 | L62: 762 | M62: 0.33 | N62: 216 | O62: 0.09 | P62: 433 | Q62: 0.19 | R62: 760 | S62: 0.31 | T62: 378 | U62: 0.17 | V62: 245 | W62: 0.11 | X62: 880 | Y62: 0.36 | Z62: =B62+D62+F62+H62+J62+L62+N62+P62+R62+T62+V62+X62 -> 5946 | AA62: =C62+E62+G62+I62+K62+M62+O62+Q62+S62+U62+W62+Y62 -> 2.49
A63: Laboratory | B63: {=_xlfn.XLOOKUP(A63,'P&L Trending Data'!A64:A204,'P&L Trending Data'!B64:Y204)} -> 774 | C63: 0.3 | D63: 4102 | E63: 1.71 | F63: 2142 | G63: 0.83 | H63: 685 | I63: 0.3 | J63: 1258 | K63: 0.51 | L63: 2600 | M63: 1.13 | N63: 47 | O63: 0.02 | P63: 1753 | Q63: 0.75 | R63: 1624 | S63: 0.66 | T63: 1454 | U63: 0.64 | V63: 605 | W63: 0.28 | X63: 40 | Y63: 0.02 | Z63: =B63+D63+F63+H63+J63+L63+N63+P63+R63+T63+V63+X63 -> 17084 | AA63: =C63+E63+G63+I63+K63+M63+O63+Q63+S63+U63+W63+Y63 -> 7.15
A64: TOTAL Therapy & Ancillary Services | B64: {=_xlfn.XLOOKUP(A64,'P&L Trending Data'!A65:A205,'P&L Trending Data'!B65:Y205)} -> 68908 | C64: 26.85 | D64: 64989 | E64: 27.07 | F64: 70117 | G64: 27.04 | H64: 54877 | I64: 24.36 | J64: 59335 | K64: 24.06 | L64: 48450 | M64: 20.97 | N64: 60131 | O64: 25.32 | P64: 61126 | Q64: 26.16 | R64: 58481 | S64: 23.75 | T64: 58173 | U64: 25.65 | V64: 41056 | W64: 19.14 | X64: 49577 | Y64: 20.23 | Z64: =B64+D64+F64+H64+J64+L64+N64+P64+R64+T64+V64+X64 -> 695220 | AA64: =C64+E64+G64+I64+K64+M64+O64+Q64+S64+U64+W64+Y64 -> 290.6
A65: Social Services
A66: Payroll Social Services | B66: {=_xlfn.XLOOKUP(A66,'P&L Trending Data'!A67:A207,'P&L Trending Data'!B67:Y207)} -> 5958 | C66: 2.32 | D66: 5176 | E66: 2.16 | F66: 5881 | G66: 2.27 | H66: 5760 | I66: 2.56 | J66: 5854 | K66: 2.37 | L66: 5563 | M66: 2.41 | N66: 5970 | O66: 2.51 | P66: 5762 | Q66: 2.47 | R66: 6067 | S66: 2.46 | T66: 6109 | U66: 2.69 | V66: 5845 | W66: 2.73 | X66: 5870 | Y66: 2.39 | Z66: =B66+D66+F66+H66+J66+L66+N66+P66+R66+T66+V66+X66 -> 69815 | AA66: =C66+E66+G66+I66+K66+M66+O66+Q66+S66+U66+W66+Y66 -> 29.34
A67: Payroll Admissions | B67: {=_xlfn.XLOOKUP(A67,'P&L Trending Data'!A68:A208,'P&L Trending Data'!B68:Y208)} -> 0 | C67: 0 | D67: 0 | E67: 0 | F67: 5007 | G67: 1.93 | H67: 0 | I67: 0 | J67: 0 | K67: 0 | L67: 865 | M67: 0.37 | N67: 0 | O67: 0 | P67: 10570 | Q67: 4.52 | R67: 4636 | S67: 1.88 | T67: 5935 | U67: 2.62 | V67: 5935 | W67: 2.77 | X67: 6078 | Y67: 2.48 | Z67: =B67+D67+F67+H67+J67+L67+N67+P67+R67+T67+V67+X67 -> 39026 | AA67: =C67+E67+G67+I67+K67+M67+O67+Q67+S67+U67+W67+Y67 -> 16.57
A68: Social Service Supplies | B68: {=_xlfn.XLOOKUP(A68,'P&L Trending Data'!A69:A209,'P&L Trending Data'!B69:Y209)} -> 0 | C68: 0 | D68: 0 | E68: 0 | F68: 0 | G68: 0 | H68: 0 | I68: 0 | J68: 0 | K68: 0 | L68: 0 | M68: 0 | N68: 0 | O68: 0 | P68: 0 | Q68: 0 | R68: 0 | S68: 0 | T68: 0 | U68: 0 | V68: 0 | W68: 0 | X68: 0 | Y68: 0 | Z68: =B68+D68+F68+H68+J68+L68+N68+P68+R68+T68+V68+X68 -> 0 | AA68: =C68+E68+G68+I68+K68+M68+O68+Q68+S68+U68+W68+Y68 -> 0
A69: Social Service Consultant | B69: {=_xlfn.XLOOKUP(A69,'P&L Trending Data'!A70:A210,'P&L Trending Data'!B70:Y210)} -> 735 | C69: 0.29 | D69: 490 | E69: 0.2 | F69: 245 | G69: 0.09 | H69: 140 | I69: 0.06 | J69: 0 | K69: 0 | L69: 490 | M69: 0.21 | N69: 770 | O69: 0.32 | P69: 0 | Q69: 0 | R69: 770 | S69: 0.31 | T69: 840 | U69: 0.37 | V69: 0 | W69: 0 | X69: 1085 | Y69: 0.44 | Z69: =B69+D69+F69+H69+J69+L69+N69+P69+R69+T69+V69+X69 -> 5565 | AA69: =C69+E69+G69+I69+K69+M69+O69+Q69+S69+U69+W69+Y69 -> 2.29
A70: TOTAL Social Services | B70: {=_xlfn.XLOOKUP(A70,'P&L Trending Data'!A71:A211,'P&L Trending Data'!B71:Y211)} -> 6693 | C70: 2.61 | D70: 5666 | E70: 2.36 | F70: 11133 | G70: 4.29 | H70: 5900 | I70: 2.62 | J70: 5854 | K70: 2.37 | L70: 6918 | M70: 2.99 | N70: 6740 | O70: 2.84 | P70: 16332 | Q70: 6.99 | R70: 11472 | S70: 4.66 | T70: 12884 | U70: 5.68 | V70: 11780 | W70: 5.49 | X70: 13033 | Y70: 5.32 | Z70: =B70+D70+F70+H70+J70+L70+N70+P70+R70+T70+V70+X70 -> 114405 | AA70: =C70+E70+G70+I70+K70+M70+O70+Q70+S70+U70+W70+Y70 -> 48.22
A71: Leisure Time & Activities
A72: Payroll Activity | B72: {=_xlfn.XLOOKUP(A72,'P&L Trending Data'!A73:A213,'P&L Trending Data'!B73:Y213)} -> 11503 | C72: 4.48 | D72: 10884 | E72: 4.53 | F72: 11803 | G72: 4.55 | H72: 12040 | I72: 5.34 | J72: 12039 | K72: 4.88 | L72: 11998 | M72: 5.19 | N72: 12085 | O72: 5.09 | P72: 12009 | Q72: 5.14 | R72: 11764 | S72: 4.78 | T72: 11970 | U72: 5.28 | V72: 11860 | W72: 5.53 | X72: 12702 | Y72: 5.18 | Z72: =B72+D72+F72+H72+J72+L72+N72+P72+R72+T72+V72+X72 -> 142657 | AA72: =C72+E72+G72+I72+K72+M72+O72+Q72+S72+U72+W72+Y72 -> 59.97
A73: Activity Supplies | B73: {=_xlfn.XLOOKUP(A73,'P&L Trending Data'!A74:A214,'P&L Trending Data'!B74:Y214)} -> 1008 | C73: 0.39 | D73: 1436 | E73: 0.6 | F73: 2736 | G73: 1.06 | H73: 946 | I73: 0.42 | J73: 1770 | K73: 0.72 | L73: 2096 | M73: 0.91 | N73: 936 | O73: 0.39 | P73: 1814 | Q73: 0.78 | R73: 1211 | S73: 0.49 | T73: 1291 | U73: 0.57 | V73: 1284 | W73: 0.6 | X73: 2760 | Y73: 1.13 | Z73: =B73+D73+F73+H73+J73+L73+N73+P73+R73+T73+V73+X73 -> 19288 | AA73: =C73+E73+G73+I73+K73+M73+O73+Q73+S73+U73+W73+Y73 -> 8.06
A74: TOTAL Leisure Time & Activities | B74: {=_xlfn.XLOOKUP(A74,'P&L Trending Data'!A75:A215,'P&L Trending Data'!B75:Y215)} -> 12511 | C74: 4.88 | D74: 12320 | E74: 5.13 | F74: 14540 | G74: 5.61 | H74: 12986 | I74: 5.76 | J74: 13810 | K74: 5.6 | L74: 14094 | M74: 6.1 | N74: 13021 | O74: 5.48 | P74: 13823 | Q74: 5.91 | R74: 12975 | S74: 5.27 | T74: 13261 | U74: 5.85 | V74: 13144 | W74: 6.13 | X74: 15462 | Y74: 6.31 | Z74: =B74+D74+F74+H74+J74+L74+N74+P74+R74+T74+V74+X74 -> 161947 | AA74: =C74+E74+G74+I74+K74+M74+O74+Q74+S74+U74+W74+Y74 -> 68.03
A75: House & Plant Costs
A76: Payroll Housekeeping | B76: {=_xlfn.XLOOKUP(A76,'P&L Trending Data'!A77:A217,'P&L Trending Data'!B77:Y217)} -> 10125 | C76: 3.95 | D76: 7116 | E76: 2.96 | F76: 7596 | G76: 2.93 | H76: 7423 | I76: 3.29 | J76: 10263 | K76: 4.16 | L76: 11343 | M76: 4.91 | N76: 11976 | O76: 5.04 | P76: 12031 | Q76: 5.15 | R76: 10548 | S76: 4.28 | T76: 13059 | U76: 5.76 | V76: 15390 | W76: 7.17 | X76: 16629 | Y76: 6.78 | Z76: =B76+D76+F76+H76+J76+L76+N76+P76+R76+T76+V76+X76 -> 133499 | AA76: =C76+E76+G76+I76+K76+M76+O76+Q76+S76+U76+W76+Y76 -> 56.38
A77: Payroll Laundry | B77: {=_xlfn.XLOOKUP(A77,'P&L Trending Data'!A78:A218,'P&L Trending Data'!B78:Y218)} -> 6134 | C77: 2.39 | D77: 5539 | E77: 2.31 | F77: 7460 | G77: 2.88 | H77: 5610 | I77: 2.49 | J77: 5575 | K77: 2.26 | L77: 5347 | M77: 2.31 | N77: 5608 | O77: 2.36 | P77: 5467 | Q77: 2.34 | R77: 6371 | S77: 2.59 | T77: 5931 | U77: 2.62 | V77: 5481 | W77: 2.56 | X77: 5645 | Y77: 2.3 | Z77: =B77+D77+F77+H77+J77+L77+N77+P77+R77+T77+V77+X77 -> 70168 | AA77: =C77+E77+G77+I77+K77+M77+O77+Q77+S77+U77+W77+Y77 -> 29.41
A78: Payroll Maintenance | B78: {=_xlfn.XLOOKUP(A78,'P&L Trending Data'!A79:A219,'P&L Trending Data'!B79:Y219)} -> 10874 | C78: 4.24 | D78: 7612 | E78: 3.17 | F78: 19147 | G78: 7.38 | H78: 9814 | I78: 4.36 | J78: 13985 | K78: 5.67 | L78: 25889 | M78: 11.21 | N78: 16046 | O78: 6.76 | P78: -1433 | Q78: -0.61 | R78: 14114 | S78: 5.73 | T78: 11113 | U78: 4.9 | V78: 7486 | W78: 3.49 | X78: 9129 | Y78: 3.72 | Z78: =B78+D78+F78+H78+J78+L78+N78+P78+R78+T78+V78+X78 -> 143776 | AA78: =C78+E78+G78+I78+K78+M78+O78+Q78+S78+U78+W78+Y78 -> 60.02
A79: Payroll Security | B79: {=_xlfn.XLOOKUP(A79,'P&L Trending Data'!A80:A220,'P&L Trending Data'!B80:Y220)} -> 0 | C79: 0 | D79: 0 | E79: 0 | F79: 0 | G79: 0 | H79: 0 | I79: 0 | J79: 0 | K79: 0 | L79: 0 | M79: 0 | N79: 0 | O79: 0 | P79: 0 | Q79: 0 | R79: 0 | S79: 0 | T79: 0 | U79: 0 | V79: 0 | W79: 0 | X79: 0 | Y79: 0 | Z79: =B79+D79+F79+H79+J79+L79+N79+P79+R79+T79+V79+X79 -> 0 | AA79: =C79+E79+G79+I79+K79+M79+O79+Q79+S79+U79+W79+Y79 -> 0
A80: Housekeeping Supplies | B80: {=_xlfn.XLOOKUP(A80,'P&L Trending Data'!A81:A221,'P&L Trending Data'!B81:Y221)} -> 2074 | C80: 0.81 | D80: 1885 | E80: 0.78 | F80: 1324 | G80: 0.51 | H80: 1679 | I80: 0.75 | J80: 1929 | K80: 0.78 | L80: 1259 | M80: 0.54 | N80: 1315 | O80: 0.55 | P80: 2583 | Q80: 1.11 | R80: 1501 | S80: 0.61 | T80: 1516 | U80: 0.67 | V80: 1519 | W80: 0.71 | X80: 1815 | Y80: 0.74 | Z80: =B80+D80+F80+H80+J80+L80+N80+P80+R80+T80+V80+X80 -> 20399 | AA80: =C80+E80+G80+I80+K80+M80+O80+Q80+S80+U80+W80+Y80 -> 8.56
A81: Covid-19 Housekeeping Supplies | B81: {=_xlfn.XLOOKUP(A81,'P&L Trending Data'!A82:A222,'P&L Trending Data'!B82:Y222)} -> 0 | C81: 0 | D81: 0 | E81: 0 | F81: 0 | G81: 0 | H81: 0 | I81: 0 | J81: 0 | K81: 0 | L81: 0 | M81: 0 | N81: 0 | O81: 0 | P81: 0 | Q81: 0 | R81: 0 | S81: 0 | T81: 0 | U81: 0 | V81: 0 | W81: 0 | X81: 0 | Y81: 0 | Z81: =B81+D81+F81+H81+J81+L81+N81+P81+R81+T81+V81+X81 -> 0 | AA81: =C81+E81+G81+I81+K81+M81+O81+Q81+S81+U81+W81+Y81 -> 0
A82: Laundry Supplies | B82: {=_xlfn.XLOOKUP(A82,'P&L Trending Data'!A83:A223,'P&L Trending Data'!B83:Y223)} -> 767 | C82: 0.3 | D82: 360 | E82: 0.15 | F82: 373 | G82: 0.14 | H82: 338 | I82: 0.15 | J82: 370 | K82: 0.15 | L82: 348 | M82: 0.15 | N82: 356 | O82: 0.15 | P82: 608 | Q82: 0.26 | R82: 457 | S82: 0.19 | T82: 0 | U82: 0 | V82: 321 | W82: 0.15 | X82: 368 | Y82: 0.15 | Z82: =B82+D82+F82+H82+J82+L82+N82+P82+R82+T82+V82+X82 -> 4666 | AA82: =C82+E82+G82+I82+K82+M82+O82+Q82+S82+U82+W82+Y82 -> 1.94
A83: Linen Replacement | B83: {=_xlfn.XLOOKUP(A83,'P&L Trending Data'!A84:A224,'P&L Trending Data'!B84:Y224)} -> 1386 | C83: 0.54 | D83: 480 | E83: 0.2 | F83: 175 | G83: 0.07 | H83: 1139 | I83: 0.51 | J83: 783 | K83: 0.32 | L83: 506 | M83: 0.22 | N83: 464 | O83: 0.2 | P83: 156 | Q83: 0.07 | R83: 1237 | S83: 0.5 | T83: 275 | U83: 0.12 | V83: 1028 | W83: 0.48 | X83: 896 | Y83: 0.37 | Z83: =B83+D83+F83+H83+J83+L83+N83+P83+R83+T83+V83+X83 -> 8525 | AA83: =C83+E83+G83+I83+K83+M83+O83+Q83+S83+U83+W83+Y83 -> 3.6
A84: Maintenance Supplies | B84: {=_xlfn.XLOOKUP(A84,'P&L Trending Data'!A85:A225,'P&L Trending Data'!B85:Y225)} -> 4214 | C84: 1.64 | D84: 857 | E84: 0.36 | F84: 1519 | G84: 0.59 | H84: 1930 | I84: 0.86 | J84: 2080 | K84: 0.84 | L84: 6002 | M84: 2.6 | N84: 2199 | O84: 0.93 | P84: 2526 | Q84: 1.08 | R84: 1924 | S84: 0.78 | T84: 3238 | U84: 1.43 | V84: 2338 | W84: 1.09 | X84: 1423 | Y84: 0.58 | Z84: =B84+D84+F84+H84+J84+L84+N84+P84+R84+T84+V84+X84 -> 30250 | AA84: =C84+E84+G84+I84+K84+M84+O84+Q84+S84+U84+W84+Y84 -> 12.78
A85: Maintenance Services | B85: {=_xlfn.XLOOKUP(A85,'P&L Trending Data'!A86:A226,'P&L Trending Data'!B86:Y226)} -> 4664 | C85: 1.82 | D85: 9838 | E85: 4.1 | F85: 8537 | G85: 3.29 | H85: 3775 | I85: 1.68 | J85: 5261 | K85: 2.13 | L85: 9813 | M85: 4.25 | N85: 7832 | O85: 3.3 | P85: 12358 | Q85: 5.29 | R85: 11690 | S85: 4.75 | T85: 14930 | U85: 6.58 | V85: 2820 | W85: 1.31 | X85: 115691 | Y85: 47.2 | Z85: =B85+D85+F85+H85+J85+L85+N85+P85+R85+T85+V85+X85 -> 207209 | AA85: =C85+E85+G85+I85+K85+M85+O85+Q85+S85+U85+W85+Y85 -> 85.7
A86: Lawn & Snow Removal Services | B86: {=_xlfn.XLOOKUP(A86,'P&L Trending Data'!A87:A227,'P&L Trending Data'!B87:Y227)} -> 0 | C86: 0 | D86: 0 | E86: 0 | F86: 1350 | G86: 0.52 | H86: 320 | I86: 0.14 | J86: 0 | K86: 0 | L86: 400 | M86: 0.17 | N86: 0 | O86: 0 | P86: 2320 | Q86: 0.99 | R86: 400 | S86: 0.16 | T86: 240 | U86: 0.11 | V86: 0 | W86: 0 | X86: 3570 | Y86: 1.46 | Z86: =B86+D86+F86+H86+J86+L86+N86+P86+R86+T86+V86+X86 -> 8600 | AA86: =C86+E86+G86+I86+K86+M86+O86+Q86+S86+U86+W86+Y86 -> 3.55
A87: Scavenger | B87: {=_xlfn.XLOOKUP(A87,'P&L Trending Data'!A88:A228,'P&L Trending Data'!B88:Y228)} -> 949 | C87: 0.37 | D87: 665 | E87: 0.28 | F87: 1933 | G87: 0.75 | H87: 1146 | I87: 0.51 | J87: 1021 | K87: 0.41 | L87: 989 | M87: 0.43 | N87: 565 | O87: 0.24 | P87: 2716 | Q87: 1.16 | R87: 1265 | S87: 0.51 | T87: 2419 | U87: 1.07 | V87: 1545 | W87: 0.72 | X87: 1005 | Y87: 0.41 | Z87: =B87+D87+F87+H87+J87+L87+N87+P87+R87+T87+V87+X87 -> 16218 | AA87: =C87+E87+G87+I87+K87+M87+O87+Q87+S87+U87+W87+Y87 -> 6.86
... A90: Water & Sewer | B90: {=_xlfn.XLOOKUP(A90,'P&L Trending Data'!A91:A231,'P&L Trending Data'!B91:Y231)} -> 3000 | C90: 1.17 | D90: 6719 | E90: 2.8 | F90: 5962 | G90: 2.3 | H90: 0 | I90: 0 | J90: 0 | K90: 0 | L90: 1893 | M90: 0.82 | N90: 2737 | O90: 1.15 | P90: 5531 | Q90: 2.37 | R90: 0 | S90: 0 | T90: 0 | U90: 0 | V90: 3543 | W90: 1.65 | X90: 1973 | Y90: 0.8 | Z90: =B90+D90+F90+H90+J90+L90+N90+P90+R90+T90+V90+X90 -> 31358 | AA90: =C90+E90+G90+I90+K90+M90+O90+Q90+S90+U90+W90+Y90 -> 13.06
A91: TOTAL House & Plant Costs | B91: {=_xlfn.XLOOKUP(A91,'P&L Trending Data'!A92:A232,'P&L Trending Data'!B92:Y232)} -> 52158 | C91: 20.33 | D91: 38718 | E91: 16.13 | F91: 55679 | G91: 21.47 | H91: 38854 | I91: 17.25 | J91: 52868 | K91: 21.44 | L91: 67346 | M91: 29.15 | N91: 52594 | O91: 22.14 | P91: 49029 | Q91: 20.98 | R91: 57766 | S91: 23.46 | T91: 58976 | U91: 26 | V91: 44924 | W91: 20.94 | X91: 164941 | Y91: 67.3 | Z91: =SUM(Z76:Z90) -> 733857 | AA91: =SUM(AA76:AA90) -> 306.61
A92: Food & Nutrition
A93: Payroll Dietary | B93: {=_xlfn.XLOOKUP(A93,'P&L Trending Data'!A94:A234,'P&L Trending Data'!B94:Y234)} -> 30789 | C93: 12 | D93: 27795 | E93: 11.58 | F93: 28398 | G93: 10.95 | H93: 27975 | I93: 12.42 | J93: 30931 | K93: 12.54 | L93: 32852 | M93: 14.22 | N93: 27171 | O93: 11.44 | P93: 28137 | Q93: 12.04 | R93: 27808 | S93: 11.29 | T93: 26559 | U93: 11.71 | V93: 23191 | W93: 10.81 | X93: 24827 | Y93: 10.13 | Z93: =B93+D93+F93+H93+J93+L93+N93+P93+R93+T93+V93+X93 -> 336433 | AA93: =C93+E93+G93+I93+K93+M93+O93+Q93+S93+U93+W93+Y93 -> 141.13
A94: Food | B94: {=_xlfn.XLOOKUP(A94,'P&L Trending Data'!A95:A235,'P&L Trending Data'!B95:Y235)} -> 20999 | C94: 8.18 | D94: 17824 | E94: 7.42 | F94: 17292 | G94: 6.67 | H94: 18014 | I94: 8 | J94: 20361 | K94: 8.26 | L94: 18023 | M94: 7.8 | N94: 17811 | O94: 7.5 | P94: 27496 | Q94: 11.77 | R94: 16725 | S94: 6.79 | T94: 19302 | U94: 8.51 | V94: 18234 | W94: 8.5 | X94: 17889 | Y94: 7.3 | Z94: =B94+D94+F94+H94+J94+L94+N94+P94+R94+T94+V94+X94 -> 229970 | AA94: =C94+E94+G94+I94+K94+M94+O94+Q94+S94+U94+W94+Y94 -> 96.7
A95: Food Supplements | B95: {=_xlfn.XLOOKUP(A95,'P&L Trending Data'!A96:A236,'P&L Trending Data'!B96:Y236)} -> 1328 | C95: 0.52 | D95: 600 | E95: 0.25 | F95: 1386 | G95: 0.53 | H95: 1457 | I95: 0.65 | J95: 1933 | K95: 0.78 | L95: 1093 | M95: 0.47 | N95: 1749 | O95: 0.74 | P95: 1258 | Q95: 0.54 | R95: 1558 | S95: 0.63 | T95: 1554 | U95: 0.69 | V95: 1811 | W95: 0.84 | X95: 1243 | Y95: 0.51 | Z95: =B95+D95+F95+H95+J95+L95+N95+P95+R95+T95+V95+X95 -> 16970 | AA95: =C95+E95+G95+I95+K95+M95+O95+Q95+S95+U95+W95+Y95 -> 7.15
A96: Dietary Supplies | B96: {=_xlfn.XLOOKUP(A96,'P&L Trending Data'!A97:A237,'P&L Trending Data'!B97:Y237)} -> 1982 | C96: 0.77 | D96: 2310 | E96: 0.96 | F96: 2253 | G96: 0.87 | H96: 1398 | I96: 0.62 | J96: 1914 | K96: 0.78 | L96: 5400 | M96: 2.34 | N96: 1490 | O96: 0.63 | P96: 1973 | Q96: 0.84 | R96: 2284 | S96: 0.93 | T96: 1537 | U96: 0.68 | V96: 3564 | W96: 1.66 | X96: 1739 | Y96: 0.71 | Z96: =B96+D96+F96+H96+J96+L96+N96+P96+R96+T96+V96+X96 -> 27844 | AA96: =C96+E96+G96+I96+K96+M96+O96+Q96+S96+U96+W96+Y96 -> 11.79
A97: Covid-19 Dietary Supplies | B97: {=_xlfn.XLOOKUP(A97,'P&L Trending Data'!A98:A238,'P&L Trending Data'!B98:Y238)} -> 0 | C97: 0 | D97: 0 | E97: 0 | F97: 0 | G97: 0 | H97: 0 | I97: 0 | J97: 0 | K97: 0 | L97: 0 | M97: 0 | N97: 0 | O97: 0 | P97: 0 | Q97: 0 | R97: 0 | S97: 0 | T97: 0 | U97: 0 | V97: 0 | W97: 0 | X97: 0 | Y97: 0 | Z97: =B97+D97+F97+H97+J97+L97+N97+P97+R97+T97+V97+X97 -> 0 | AA97: =C97+E97+G97+I97+K97+M97+O97+Q97+S97+U97+W97+Y97 -> 0
A98: Dietary Consultant | B98: {=_xlfn.XLOOKUP(A98,'P&L Trending Data'!A99:A239,'P&L Trending Data'!B99:Y239)} -> -625 | C98: -0.24 | D98: 53 | E98: 0.02 | F98: 54 | G98: 0.02 | H98: 55 | I98: 0.02 | J98: 53 | K98: 0.02 | L98: 53 | M98: 0.02 | N98: 53 | O98: 0.02 | P98: 634 | Q98: 0.27 | R98: 53 | S98: 0.02 | T98: 126 | U98: 0.06 | V98: 126 | W98: 0.06 | X98: 127 | Y98: 0.05 | Z98: =B98+D98+F98+H98+J98+L98+N98+P98+R98+T98+V98+X98 -> 762 | AA98: =C98+E98+G98+I98+K98+M98+O98+Q98+S98+U98+W98+Y98 -> 0.34
A99: TOTAL Food & Nutrition | B99: {=_xlfn.XLOOKUP(A99,'P&L Trending Data'!A100:A240,'P&L Trending Data'!B100:Y240)} -> 54473 | C99: 21.23 | D99: 48582 | E99: 20.23 | F99: 49383 | G99: 19.04 | H99: 48899 | I99: 21.7 | J99: 55191 | K99: 22.38 | L99: 57421 | M99: 24.86 | N99: 48274 | O99: 20.33 | P99: 59498 | Q99: 25.46 | R99: 48427 | S99: 19.67 | T99: 49078 | U99: 21.64 | V99: 46926 | W99: 21.88 | X99: 45826 | Y99: 18.7 | Z99: =B99+D99+F99+H99+J99+L99+N99+P99+R99+T99+V99+X99 -> 611978 | AA99: =C99+E99+G99+I99+K99+M99+O99+Q99+S99+U99+W99+Y99 -> 257.12
A100: Employee Welfare Costs
A101: Payroll Taxes | B101: {=_xlfn.XLOOKUP(A101,'P&L Trending Data'!A102:A242,'P&L Trending Data'!B102:Y242)} -> 43661 | C101: 17.02 | D101: 35768 | E101: 14.9 | F101: 36963 | G101: 14.25 | H101: 34129 | I101: 15.15 | J101: 35621 | K101: 14.44 | L101: 33348 | M101: 14.44 | N101: 31531 | O101: 13.28 | P101: 29560 | Q101: 12.65 | R101: 29738 | S101: 12.08 | T101: 25028 | U101: 11.04 | V101: 29128 | W101: 13.58 | X101: 32183 | Y101: 13.13 | Z101: =B101+D101+F101+H101+J101+L101+N101+P101+R101+T101+V101+X101 -> 396658 | AA101: =C101+E101+G101+I101+K101+M101+O101+Q101+S101+U101+W101+Y101 -> 165.96
A102: Workmans Comp Insurance | B102: {=_xlfn.XLOOKUP(A102,'P&L Trending Data'!A103:A243,'P&L Trending Data'!B103:Y243)} -> 2748 | C102: 1.07 | D102: 1939 | E102: 0.81 | F102: 2295 | G102: 0.89 | H102: 6660 | I102: 2.96 | J102: 2256 | K102: 0.91 | L102: 4063 | M102: 1.76 | N102: 2009 | O102: 0.85 | P102: 2033 | Q102: 0.87 | R102: 1988 | S102: 0.81 | T102: 2442 | U102: 1.08 | V102: 2490 | W102: 1.16 | X102: 6748 | Y102: 2.75 | Z102: =B102+D102+F102+H102+J102+L102+N102+P102+R102+T102+V102+X102 -> 37671 | AA102: =C102+E102+G102+I102+K102+M102+O102+Q102+S102+U102+W102+Y102 -> 15.92
A103: Employee Benefits | B103: {=_xlfn.XLOOKUP(A103,'P&L Trending Data'!A104:A244,'P&L Trending Data'!B104:Y244)} -> 480 | C103: 0.19 | D103: -833 | E103: -0.35 | F103: 331 | G103: 0.13 | H103: 1663 | I103: 0.74 | J103: 2339 | K103: 0.95 | L103: -871 | M103: -0.38 | N103: 161 | O103: 0.07 | P103: 695 | Q103: 0.3 | R103: 435 | S103: 0.18 | T103: 8143 | U103: 3.59 | V103: 4568 | W103: 2.13 | X103: 894 | Y103: 0.36 | Z103: =B103+D103+F103+H103+J103+L103+N103+P103+R103+T103+V103+X103 -> 18005 | AA103: =C103+E103+G103+I103+K103+M103+O103+Q103+S103+U103+W103+Y103 -> 7.91
A104: Employee Insurance | B104: {=_xlfn.XLOOKUP(A104,'P&L Trending Data'!A105:A245,'P&L Trending Data'!B105:Y245)} -> -18713 | C104: -7.29 | D104: 9590 | E104: 3.99 | F104: 15316 | G104: 5.91 | H104: 7535 | I104: 3.34 | J104: 17326 | K104: 7.03 | L104: 12098 | M104: 5.24 | N104: 13951 | O104: 5.87 | P104: 13405 | Q104: 5.74 | R104: 14323 | S104: 5.82 | T104: 7063 | U104: 3.11 | V104: 12788 | W104: 5.96 | X104: 15253 | Y104: 6.22 | Z104: =B104+D104+F104+H104+J104+L104+N104+P104+R104+T104+V104+X104 -> 119935 | AA104: =C104+E104+G104+I104+K104+M104+O104+Q104+S104+U104+W104+Y104 -> 50.94
A105: Education & Seminars | B105: {=_xlfn.XLOOKUP(A105,'P&L Trending Data'!A106:A246,'P&L Trending Data'!B106:Y246)} -> 545 | C105: 0.21 | D105: 0 | E105: 0 | F105: 0 | G105: 0 | H105: 1070 | I105: 0.47 | J105: 0 | K105: 0 | L105: 0 | M105: 0 | N105: 5005 | O105: 2.11 | P105: 455 | Q105: 0.19 | R105: -440 | S105: -0.18 | T105: 0 | U105: 0 | V105: 0 | W105: 0 | X105: 0 | Y105: 0 | Z105: =B105+D105+F105+H105+J105+L105+N105+P105+R105+T105+V105+X105 -> 6635 | AA105: =C105+E105+G105+I105+K105+M105+O105+Q105+S105+U105+W105+Y105 -> 2.8
A106: Pension | B106: {=_xlfn.XLOOKUP(A106,'P&L Trending Data'!A107:A247,'P&L Trending Data'!B107:Y247)} -> 2473 | C106: 0.96 | D106: 4006 | E106: 1.67 | F106: 6772 | G106: 2.61 | H106: -495 | I106: -0.22 | J106: 1006 | K106: 0.41 | L106: 4932 | M106: 2.13 | N106: 3549 | O106: 1.49 | P106: 3309 | Q106: 1.42 | R106: 3410 | S106: 1.38 | T106: -1126 | U106: -0.5 | V106: -307 | W106: -0.14 | X106: 4766 | Y106: 1.94 | Z106: =B106+D106+F106+H106+J106+L106+N106+P106+R106+T106+V106+X106 -> 32295 | AA106: =C106+E106+G106+I106+K106+M106+O106+Q106+S106+U106+W106+Y106 -> 13.15
A107: TOTAL Employee Welfare Costs | B107: {=_xlfn.XLOOKUP(A107,'P&L Trending Data'!A108:A248,'P&L Trending Data'!B108:Y248)} -> 31194 | C107: 12.16 | D107: 50470 | E107: 21.02 | F107: 61677 | G107: 23.79 | H107: 50563 | I107: 22.44 | J107: 58548 | K107: 23.74 | L107: 53571 | M107: 23.19 | N107: 56207 | O107: 23.67 | P107: 49458 | Q107: 21.16 | R107: 49454 | S107: 20.09 | T107: 41549 | U107: 18.32 | V107: 48667 | W107: 22.69 | X107: 59844 | Y107: 24.42 | Z107: =B107+D107+F107+H107+J107+L107+N107+P107+R107+T107+V107+X107 -> 611202 | AA107: =C107+E107+G107+I107+K107+M107+O107+Q107+S107+U107+W107+Y107 -> 256.69
A108: General & Administrative
A109: Payroll Administrative | B109: {=_xlfn.XLOOKUP(A109,'P&L Trending Data'!A110:A250,'P&L Trending Data'!B110:Y250)} -> 12143 | C109: 4.73 | D109: 10719 | E109: 4.46 | F109: 10354 | G109: 3.99 | H109: 12475 | I109: 5.54 | J109: 12135 | K109: 4.92 | L109: 12059 | M109: 5.22 | N109: 11541 | O109: 4.86 | P109: 12268 | Q109: 5.25 | R109: 10491 | S109: 4.26 | T109: 12133 | U109: 5.35 | V109: 10847 | W109: 5.06 | X109: 23449 | Y109: 9.57 | Z109: =B109+D109+F109+H109+J109+L109+N109+P109+R109+T109+V109+X109 -> 150614 | AA109: =C109+E109+G109+I109+K109+M109+O109+Q109+S109+U109+W109+Y109 -> 63.21
A110: Payroll Office | B110: {=_xlfn.XLOOKUP(A110,'P&L Trending Data'!A111:A251,'P&L Trending Data'!B111:Y251)} -> 6021 | C110: 2.35 | D110: 6629 | E110: 2.76 | F110: 9495 | G110: 3.66 | H110: 7342 | I110: 3.26 | J110: 7915 | K110: 3.21 | L110: 11168 | M110: 4.83 | N110: 6978 | O110: 2.94 | P110: 9585 | Q110: 4.1 | R110: 9165 | S110: 3.72 | T110: 9333 | U110: 4.12 | V110: 8737 | W110: 4.07 | X110: 8725 | Y110: 3.56 | Z110: =B110+D110+F110+H110+J110+L110+N110+P110+R110+T110+V110+X110 -> 101093 | AA110: =C110+E110+G110+I110+K110+M110+O110+Q110+S110+U110+W110+Y110 -> 42.58
A111: Payroll Marketing | B111: {=_xlfn.XLOOKUP(A111,'P&L Trending Data'!A112:A252,'P&L Trending Data'!B112:Y252)} -> 0 | C111: 0 | D111: 0 | E111: 0 | F111: 0 | G111: 0 | H111: 0 | I111: 0 | J111: 0 | K111: 0 | L111: 0 | M111: 0 | N111: 0 | O111: 0 | P111: 0 | Q111: 0 | R111: 0 | S111: 0 | T111: 0 | U111: 0 | V111: 0 | W111: 0 | X111: 0 | Y111: 0 | Z111: =B111+D111+F111+H111+J111+L111+N111+P111+R111+T111+V111+X111 -> 0 | AA111: =C111+E111+G111+I111+K111+M111+O111+Q111+S111+U111+W111+Y111 -> 0
A112: Marketing Consultant | B112: {=_xlfn.XLOOKUP(A112,'P&L Trending Data'!A113:A253,'P&L Trending Data'!B113:Y253)} -> 850 | C112: 0.33 | D112: 850 | E112: 0.35 | F112: 850 | G112: 0.33 | H112: 1942 | I112: 0.86 | J112: 850 | K112: 0.34 | L112: 850 | M112: 0.37 | N112: 850 | O112: 0.36 | P112: 850 | Q112: 0.36 | R112: 850 | S112: 0.35 | T112: 850 | U112: 0.37 | V112: 850 | W112: 0.4 | X112: 850 | Y112: 0.35 | Z112: =B112+D112+F112+H112+J112+L112+N112+P112+R112+T112+V112+X112 -> 11292 | AA112: =C112+E112+G112+I112+K112+M112+O112+Q112+S112+U112+W112+Y112 -> 4.77
A113: General Insurance | B113: {=_xlfn.XLOOKUP(A113,'P&L Trending Data'!A114:A254,'P&L Trending Data'!B114:Y254)} -> 5665 | C113: 2.21 | D113: 0 | E113: 0 | F113: 0 | G113: 0 | H113: 16995 | I113: 7.54 | J113: 5665 | K113: 2.3 | L113: 5665 | M113: 2.45 | N113: 6165 | O113: 2.6 | P113: 5665 | Q113: 2.42 | R113: 5665 | S113: 2.3 | T113: 5665 | U113: 2.5 | V113: 5665 | W113: 2.64 | X113: 5665 | Y113: 2.31 | Z113: =B113+D113+F113+H113+J113+L113+N113+P113+R113+T113+V113+X113 -> 68480 | AA113: =C113+E113+G113+I113+K113+M113+O113+Q113+S113+U113+W113+Y113 -> 29.27
...

Sheet PR Detail Trending
A1: =BS!A1 -> Allure of Peru
A2: Payroll Summary Detail Trending
A3: ='PR Trending Data'!B3 -> 1/1/2025 to 12/31/2025
B5: ='P&L Detail Trending'!B5 -> 45658 | D5: =EDATE(B5,1) -> 45689 | F5: =EDATE(D5,1) -> 45717 | H5: =EDATE(F5,1) -> 45748 | J5: =EDATE(H5,1) -> 45778 | L5: =EDATE(J5,1) -> 45809 | N5: =EDATE(L5,1) -> 45839 | P5: =EDATE(N5,1) -> 45870 | R5: =EDATE(P5,1) -> 45901 | T5: =EDATE(R5,1) -> 45931 | V5: =EDATE(T5,1) -> 45962 | X5: =EDATE(V5,1) -> 45992 | Z5: TOTALS
B6: Actual $ | C6: Actual / Day | D6: Actual $ | E6: Actual / Day | F6: Actual $ | G6: Actual / Day | H6: Actual $ | I6: Actual / Day | J6: Actual $ | K6: Actual / Day | L6: Actual $ | M6: Actual / Day | N6: Actual $ | O6: Actual / Day | P6: Actual $ | Q6: Actual / Day | R6: Actual $ | S6: Actual / Day | T6: Actual $ | U6: Actual / Day | V6: Actual $ | W6: Actual / Day | X6: Actual $ | Y6: Actual / Day | Z6: Actual $ | AA6: Actual / Day
A7: Payroll Summary
A8: P/R Administrator | B8: {=_xlfn.XLOOKUP(A8,'PR Trending Data'!A9:A74,'PR Trending Data'!B9:Y74)} -> 10221 | C8: 3.98 | D8: 9232 | E8: 3.85 | F8: 10241 | G8: 3.95 | H8: 10188 | I8: 4.52 | J8: 10528 | K8: 4.27 | L8: 10188 | M8: 4.41 | N8: 10528 | O8: 4.43 | P8: 10528 | Q8: 4.5 | R8: 10188 | S8: 4.14 | T8: 10528 | U8: 4.64 | V8: 10188 | W8: 4.75 | X8: 11658 | Y8: 4.76 | Z8: =B8+D8+F8+H8+J8+L8+N8+P8+R8+T8+V8+X8 -> 124216 | AA8: =C8+E8+G8+I8+K8+M8+O8+Q8+S8+U8+W8+Y8 -> 52.2
A9: P/R Administrator Covid | B9: {=_xlfn.XLOOKUP(A9,'PR Trending Data'!A10:A75,'PR Trending Data'!B10:Y75)} -> 1922 | C9: 0.75 | D9: 1487 | E9: 0.62 | F9: 113 | G9: 0.04 | H9: 2287 | I9: 1.02 | J9: 1608 | K9: 0.65 | L9: 1871 | M9: 0.81 | N9: 1014 | O9: 0.43 | P9: 1741 | Q9: 0.74 | R9: 303 | S9: 0.12 | T9: 1606 | U9: 0.71 | V9: 659 | W9: 0.31 | X9: 0 | Y9: 0 | Z9: =B9+D9+F9+H9+J9+L9+N9+P9+R9+T9+V9+X9 -> 14611 | AA9: =C9+E9+G9+I9+K9+M9+O9+Q9+S9+U9+W9+Y9 -> 6.2
A10: P/R Assistant Admin Covid | B10: {=_xlfn.XLOOKUP(A10,'PR Trending Data'!A11:A76,'PR Trending Data'!B11:Y76)} -> 0 | C10: 0 | D10: 0 | E10: 0 | F10: 0 | G10: 0 | H10: 0 | I10: 0 | J10: 0 | K10: 0 | L10: 0 | M10: 0 | N10: 0 | O10: 0 | P10: 0 | Q10: 0 | R10: 0 | S10: 0 | T10: 0 | U10: 0 | V10: 0 | W10: 0 | X10: 0 | Y10: 0 | Z10: =B10+D10+F10+H10+J10+L10+N10+P10+R10+T10+V10+X10 -> 0 | AA10: =C10+E10+G10+I10+K10+M10+O10+Q10+S10+U10+W10+Y10 -> 0
A11: P/R Assistant Administrator | B11: {=_xlfn.XLOOKUP(A11,'PR Trending Data'!A12:A77,'PR Trending Data'!B12:Y77)} -> 0 | C11: 0 | D11: 0 | E11: 0 | F11: 0 | G11: 0 | H11: 0 | I11: 0 | J11: 0 | K11: 0 | L11: 0 | M11: 0 | N11: 0 | O11: 0 | P11: 0 | Q11: 0 | R11: 0 | S11: 0 | T11: 0 | U11: 0 | V11: 0 | W11: 0 | X11: 0 | Y11: 0 | Z11: =B11+D11+F11+H11+J11+L11+N11+P11+R11+T11+V11+X11 -> 0 | AA11: =C11+E11+G11+I11+K11+M11+O11+Q11+S11+U11+W11+Y11 -> 0
A12: P/R DON | B12: {=_xlfn.XLOOKUP(A12,'PR Trending Data'!A13:A78,'PR Trending Data'!B13:Y78)} -> 9212 | C12: 3.59 | D12: 7717 | E12: 3.21 | F12: 8952 | G12: 3.45 | H12: 8492 | I12: 3.77 | J12: 8997 | K12: 3.65 | L12: 8509 | M12: 3.68 | N12: 8817 | O12: 3.71 | P12: 8597 | Q12: 3.68 | R12: 8438 | S12: 3.43 | T12: 8719 | U12: 3.84 | V12: 8626 | W12: 4.02 | X12: 8871 | Y12: 3.62 | Z12: =B12+D12+F12+H12+J12+L12+N12+P12+R12+T12+V12+X12 -> 103947 | AA12: =C12+E12+G12+I12+K12+M12+O12+Q12+S12+U12+W12+Y12 -> 43.65
A13: P/R DON Covid | B13: {=_xlfn.XLOOKUP(A13,'PR Trending Data'!A14:A79,'PR Trending Data'!B14:Y79)} -> 0 | C13: 0 | D13: 0 | E13: 0 | F13: 0 | G13: 0 | H13: 0 | I13: 0 | J13: 0 | K13: 0 | L13: 0 | M13: 0 | N13: 1250 | O13: 0.53 | P13: 0 | Q13: 0 | R13: 0 | S13: 0 | T13: 321 | U13: 0.14 | V13: 429 | W13: 0.2 | X13: 0 | Y13: 0 | Z13: =B13+D13+F13+H13+J13+L13+N13+P13+R13+T13+V13+X13 -> 2000 | AA13: =C13+E13+G13+I13+K13+M13+O13+Q13+S13+U13+W13+Y13 -> 0.87
A14: P/R ADON | B14: {=_xlfn.XLOOKUP(A14,'PR Trending Data'!A15:A80,'PR Trending Data'!B15:Y80)} -> 7877 | C14: 3.07 | D14: 7354 | E14: 3.06 | F14: 7832 | G14: 3.02 | H14: 7552 | I14: 3.35 | J14: 8298 | K14: 3.36 | L14: 7532 | M14: 3.26 | N14: 7601 | O14: 3.2 | P14: 7638 | Q14: 3.27 | R14: 6659 | S14: 2.7 | T14: 1904 | U14: 0.84 | V14: 6738 | W14: 3.14 | X14: 8630 | Y14: 3.52 | Z14: =B14+D14+F14+H14+J14+L14+N14+P14+R14+T14+V14+X14 -> 85615 | AA14: =C14+E14+G14+I14+K14+M14+O14+Q14+S14+U14+W14+Y14 -> 35.79
A15: P/R ADON Covid | B15: {=_xlfn.XLOOKUP(A15,'PR Trending Data'!A16:A81,'PR Trending Data'!B16:Y81)} -> 0 | C15: 0 | D15: 0 | E15: 0 | F15: 0 | G15: 0 | H15: 0 | I15: 0 | J15: 0 | K15: 0 | L15: 0 | M15: 0 | N15: 0 | O15: 0 | P15: 0 | Q15: 0 | R15: 0 | S15: 0 | T15: 0 | U15: 0 | V15: 0 | W15: 0 | X15: 0 | Y15: 0 | Z15: =B15+D15+F15+H15+J15+L15+N15+P15+R15+T15+V15+X15 -> 0 | AA15: =C15+E15+G15+I15+K15+M15+O15+Q15+S15+U15+W15+Y15 -> 0
A16: P/R RN | B16: {=_xlfn.XLOOKUP(A16,'PR Trending Data'!A17:A82,'PR Trending Data'!B17:Y82)} -> 65236 | C16: 25.42 | D16: 60365 | E16: 25.14 | F16: 68632 | G16: 26.47 | H16: 69671 | I16: 30.92 | J16: 71475 | K16: 28.98 | L16: 69227 | M16: 29.97 | N16: 72869 | O16: 30.68 | P16: 66824 | Q16: 28.59 | R16: 64087 | S16: 26.03 | T16: 66427 | U16: 29.29 | V16: 64275 | W16: 29.97 | X16: 61682 | Y16: 25.17 | Z16: =B16+D16+F16+H16+J16+L16+N16+P16+R16+T16+V16+X16 -> 800770 | AA16: =C16+E16+G16+I16+K16+M16+O16+Q16+S16+U16+W16+Y16 -> 336.63
A17: P/R RN Covid | B17: {=_xlfn.XLOOKUP(A17,'PR Trending Data'!A18:A83,'PR Trending Data'!B18:Y83)} -> 0 | C17: 0 | D17: 0 | E17: 0 | F17: 0 | G17: 0 | H17: 0 | I17: 0 | J17: 0 | K17: 0 | L17: 0 | M17: 0 | N17: 0 | O17: 0 | P17: 0 | Q17: 0 | R17: 0 | S17: 0 | T17: 0 | U17: 0 | V17: 0 | W17: 0 | X17: 0 | Y17: 0 | Z17: =B17+D17+F17+H17+J17+L17+N17+P17+R17+T17+V17+X17 -> 0 | AA17: =C17+E17+G17+I17+K17+M17+O17+Q17+S17+U17+W17+Y17 -> 0
A18: P/R LPN | B18: {=_xlfn.XLOOKUP(A18,'PR Trending Data'!A19:A84,'PR Trending Data'!B19:Y84)} -> 0 | C18: 0 | D18: 0 | E18: 0 | F18: 0 | G18: 0 | H18: 0 | I18: 0 | J18: 0 | K18: 0 | L18: 12970 | M18: 5.61 | N18: -12970 | O18: -5.46 | P18: 0 | Q18: 0 | R18: 0 | S18: 0 | T18: 0 | U18: 0 | V18: 0 | W18: 0 | X18: 0 | Y18: 0 | Z18: =B18+D18+F18+H18+J18+L18+N18+P18+R18+T18+V18+X18 -> 0 | AA18: =C18+E18+G18+I18+K18+M18+O18+Q18+S18+U18+W18+Y18 -> 0.15
A19: P/R LPN Covid | B19: {=_xlfn.XLOOKUP(A19,'PR Trending Data'!A20:A85,'PR Trending Data'!B20:Y85)} -> 36740 | C19: 14.32 | D19: 36131 | E19: 15.05 | F19: 35983 | G19: 13.88 | H19: 33791 | I19: 15 | J19: 33989 | K19: 13.78 | L19: 27241 | M19: 11.79 | N19: 47661 | O19: 20.07 | P19: 34825 | Q19: 14.9 | R19: 35716 | S19: 14.51 | T19: 40897 | U19: 18.03 | V19: 39372 | W19: 18.36 | X19: 40479 | Y19: 16.52 | Z19: =B19+D19+F19+H19+J19+L19+N19+P19+R19+T19+V19+X19 -> 442825 | AA19: =C19+E19+G19+I19+K19+M19+O19+Q19+S19+U19+W19+Y19 -> 186.21
... A47: P/R Admissions Covid | B47: {=_xlfn.XLOOKUP(A47,'PR Trending Data'!A48:A113,'PR Trending Data'!B48:Y113)} -> 0 | C47: 0 | D47: 0 | E47: 0 | F47: 0 | G47: 0 | H47: 0 | I47: 0 | J47: 0 | K47: 0 | L47: 0 | M47: 0 | N47: 0 | O47: 0 | P47: 0 | Q47: 0 | R47: 0 | S47: 0 | T47: 0 | U47: 0 | V47: 0 | W47: 0 | X47: 0 | Y47: 0 | Z47: =B47+D47+F47+H47+J47+L47+N47+P47+R47+T47+V47+X47 -> 0 | AA47: =C47+E47+G47+I47+K47+M47+O47+Q47+S47+U47+W47+Y47 -> 0
A48: TOTAL Payroll Summary | B48: {=_xlfn.XLOOKUP(A48,'PR Trending Data'!A49:A114,'PR Trending Data'!B49:Y114)} -> 379332 | C48: 147.83 | D48: 332103 | E48: 138.32 | F48: 390919 | G48: 150.76 | H48: 373220 | I48: 165.65 | J48: 401243 | K48: 162.71 | L48: 412670 | M48: 178.65 | N48: 386222 | O48: 162.62 | P48: 365887 | Q48: 156.56 | R48: 378054 | S48: 153.56 | T48: 370281 | U48: 163.26 | V48: 373009 | W48: 173.9 | X48: 401772 | Y48: 163.92 | Z48: =SUM(Z8:Z47) -> 4564722 | AA48: =SUM(AA8:AA47) -> 1917.7
A49: Payroll Taxes Detail | B49: {=_xlfn.XLOOKUP(A49,'PR Trending Data'!A50:A115,'PR Trending Data'!B50:Y115)} -> 0 | C49: 0 | D49: 0 | E49: 0 | F49: 0 | G49: 0 | H49: 0 | I49: 0 | J49: 0 | K49: 0 | L49: 0 | M49: 0 | N49: 0 | O49: 0 | P49: 0 | Q49: 0 | R49: 0 | S49: 0 | T49: 0 | U49: 0 | V49: 0 | W49: 0 | X49: 0 | Y49: 0
A50: FICA | B50: {=_xlfn.XLOOKUP(A50,'PR Trending Data'!A51:A116,'PR Trending Data'!B51:Y116)} -> 28146 | C50: 10.97 | D50: 24576 | E50: 10.24 | F50: 27649 | G50: 10.66 | H50: 27609 | I50: 12.25 | J50: 29751 | K50: 12.06 | L50: 29195 | M50: 12.64 | N50: 28527 | O50: 12.01 | P50: 27223 | Q50: 11.65 | R50: 27430 | S50: 11.14 | T50: 22786 | U50: 10.05 | V50: 27048 | W50: 12.61 | X50: 28986 | Y50: 11.83 | Z50: =B50+D50+F50+H50+J50+L50+N50+P50+R50+T50+V50+X50 -> 328926 | AA50: =C50+E50+G50+I50+K50+M50+O50+Q50+S50+U50+W50+Y50 -> 138.11
A51: State Unemployment | B51: {=_xlfn.XLOOKUP(A51,'PR Trending Data'!A52:A117,'PR Trending Data'!B52:Y117)} -> 13556 | C51: 5.28 | D51: 10269 | E51: 4.28 | F51: 8818 | G51: 3.4 | H51: 6179 | I51: 2.74 | J51: 5508 | K51: 2.23 | L51: 3839 | M51: 1.66 | N51: 2743 | O51: 1.16 | P51: 2164 | Q51: 0.93 | R51: 2174 | S51: 0.88 | T51: 2092 | U51: 0.92 | V51: 1895 | W51: 0.88 | X51: 2237 | Y51: 0.91 | Z51: =B51+D51+F51+H51+J51+L51+N51+P51+R51+T51+V51+X51 -> 61474 | AA51: =C51+E51+G51+I51+K51+M51+O51+Q51+S51+U51+W51+Y51 -> 25.27
A52: Federal Unemployment | B52: {=_xlfn.XLOOKUP(A52,'PR Trending Data'!A53:A118,'PR Trending Data'!B53:Y118)} -> 1959 | C52: 0.76 | D52: 924 | E52: 0.38 | F52: 496 | G52: 0.19 | H52: 341 | I52: 0.15 | J52: 363 | K52: 0.15 | L52: 315 | M52: 0.14 | N52: 261 | O52: 0.11 | P52: 172 | Q52: 0.07 | R52: 134 | S52: 0.05 | T52: 150 | U52: 0.07 | V52: 184 | W52: 0.09 | X52: 961 | Y52: 0.39 | Z52: =B52+D52+F52+H52+J52+L52+N52+P52+R52+T52+V52+X52 -> 6260 | AA52: =C52+E52+G52+I52+K52+M52+O52+Q52+S52+U52+W52+Y52 -> 2.55
A53: Payroll Taxes - Other | B53: {=_xlfn.XLOOKUP(A53,'PR Trending Data'!A54:A119,'PR Trending Data'!B54:Y119)} -> 0 | C53: 0 | D53: 0 | E53: 0 | F53: 0 | G53: 0 | H53: 0 | I53: 0 | J53: 0 | K53: 0 | L53: 0 | M53: 0 | N53: 0 | O53: 0 | P53: 0 | Q53: 0 | R53: 0 | S53: 0 | T53: 0 | U53: 0 | V53: 0 | W53: 0 | X53: 0 | Y53: 0 | Z53: =B53+D53+F53+H53+J53+L53+N53+P53+R53+T53+V53+X53 -> 0 | AA53: =C53+E53+G53+I53+K53+M53+O53+Q53+S53+U53+W53+Y53 -> 0
A54: TOTAL Payroll Taxes Detail | B54: {=_xlfn.XLOOKUP(A54,'PR Trending Data'!A55:A120,'PR Trending Data'!B55:Y120)} -> 43661 | C54: 17.02 | D54: 35768 | E54: 14.9 | F54: 36963 | G54: 14.25 | H54: 34129 | I54: 15.15 | J54: 35621 | K54: 14.44 | L54: 33348 | M54: 14.44 | N54: 31531 | O54: 13.28 | P54: 29560 | Q54: 12.65 | R54: 29738 | S54: 12.08 | T54: 25028 | U54: 11.04 | V54: 29128 | W54: 13.58 | X54: 32183 | Y54: 13.13 | Z54: =SUM(Z50:Z53) -> 396660 | AA54: =SUM(AA50:AA53) -> 165.93
A55: Total Payroll | B55: {=_xlfn.XLOOKUP(A55,'PR Trending Data'!A56:A121,'PR Trending Data'!B56:Y121)} -> 422993 | C55: 164.85 | D55: 367871 | E55: 153.22 | F55: 427882 | G55: 165.01 | H55: 407349 | I55: 180.8 | J55: 436864 | K55: 177.15 | L55: 446019 | M55: 193.08 | N55: 417754 | O55: 175.9 | P55: 395447 | Q55: 169.21 | R55: 407792 | S55: 165.63 | T55: 395309 | U55: 174.3 | V55: 402137 | W55: 187.48 | X55: 433956 | Y55: 177.05 | Z55: =+Z54+Z48 -> 4961382 | AA55: =+AA54+AA48 -> 2083.63
A56: Agency Detail | B56: {=_xlfn.XLOOKUP(A56,'PR Trending Data'!A57:A122,'PR Trending Data'!B57:Y122)} -> 0 | C56: 0 | D56: 0 | E56: 0 | F56: 0 | G56: 0 | H56: 0 | I56: 0 | J56: 0 | K56: 0 | L56: 0 | M56: 0 | N56: 0 | O56: 0 | P56: 0 | Q56: 0 | R56: 0 | S56: 0 | T56: 0 | U56: 0 | V56: 0 | W56: 0 | X56: 0 | Y56: 0
A57: Agency Salaries - RN | B57: {=_xlfn.XLOOKUP(A57,'PR Trending Data'!A58:A123,'PR Trending Data'!B58:Y123)} -> 15000 | C57: 5.85 | D57: 2529 | E57: 1.05 | F57: 5652 | G57: 2.18 | H57: 2333 | I57: 1.04 | J57: 8661 | K57: 3.51 | L57: 3684 | M57: 1.59 | N57: 2170 | O57: 0.91 | P57: 2527 | Q57: 1.08 | R57: 14053 | S57: 5.71 | T57: 12299 | U57: 5.42 | V57: 0 | W57: 0 | X57: 8315 | Y57: 3.39 | Z57: =B57+D57+F57+H57+J57+L57+N57+P57+R57+T57+V57+X57 -> 77223 | AA57: =C57+E57+G57+I57+K57+M57+O57+Q57+S57+U57+W57+Y57 -> 31.73
A58: Covid Agency Salaries - RN | B58: {=_xlfn.XLOOKUP(A58,'PR Trending Data'!A59:A124,'PR Trending Data'!B59:Y124)} -> 2683 | C58: 1.05 | D58: 2226 | E58: 0.93 | F58: 0 | G58: 0 | H58: 95 | I58: 0.04 | J58: 0 | K58: 0 | L58: 0 | M58: 0 | N58: 0 | O58: 0 | P58: 0 | Q58: 0 | R58: 0 | S58: 0 | T58: 0 | U58: 0 | V58: 0 | W58: 0 | X58: 0 | Y58: 0 | Z58: =B58+D58+F58+H58+J58+L58+N58+P58+R58+T58+V58+X58 -> 5004 | AA58: =C58+E58+G58+I58+K58+M58+O58+Q58+S58+U58+W58+Y58 -> 2.02
A59: Agency Salaries - LPN | B59: {=_xlfn.XLOOKUP(A59,'PR Trending Data'!A60:A125,'PR Trending Data'!B60:Y125)} -> 7758 | C59: 3.02 | D59: 1974 | E59: 0.82 | F59: 3687 | G59: 1.42 | H59: 0 | I59: 0 | J59: 1264 | K59: 0.51 | L59: 193 | M59: 0.08 | N59: 882 | O59: 0.37 | P59: 0 | Q59: 0 | R59: 0 | S59: 0 | T59: 260 | U59: 0.11 | V59: 0 | W59: 0 | X59: 2399 | Y59: 0.98 | Z59: =B59+D59+F59+H59+J59+L59+N59+P59+R59+T59+V59+X59 -> 18417 | AA59: =C59+E59+G59+I59+K59+M59+O59+Q59+S59+U59+W59+Y59 -> 7.31
A60: Covid Agency Salaries - LPN | B60: {=_xlfn.XLOOKUP(A60,'PR Trending Data'!A61:A126,'PR Trending Data'!B61:Y126)} -> 0 | C60: 0 | D60: 0 | E60: 0 | F60: 0 | G60: 0 | H60: 0 | I60: 0 | J60: 0 | K60: 0 | L60: 0 | M60: 0 | N60: 0 | O60: 0 | P60: 0 | Q60: 0 | R60: 0 | S60: 0 | T60: 0 | U60: 0 | V60: 0 | W60: 0 | X60: 0 | Y60: 0 | Z60: =B60+D60+F60+H60+J60+L60+N60+P60+R60+T60+V60+X60 -> 0 | AA60: =C60+E60+G60+I60+K60+M60+O60+Q60+S60+U60+W60+Y60 -> 0
A61: Agency Salaries - CNA | B61: {=_xlfn.XLOOKUP(A61,'PR Trending Data'!A62:A127,'PR Trending Data'!B62:Y127)} -> 17063 | C61: 6.65 | D61: 18864 | E61: 7.86 | F61: 32475 | G61: 12.52 | H61: 10108 | I61: 4.49 | J61: 9671 | K61: 3.92 | L61: 7191 | M61: 3.11 | N61: 2546 | O61: 1.07 | P61: 2770 | Q61: 1.19 | R61: 21952 | S61: 8.92 | T61: 11843 | U61: 5.22 | V61: 2491 | W61: 1.16 | X61: 8728 | Y61: 3.56 | Z61: =B61+D61+F61+H61+J61+L61+N61+P61+R61+T61+V61+X61 -> 145702 | AA61: =C61+E61+G61+I61+K61+M61+O61+Q61+S61+U61+W61+Y61 -> 59.67
A62: Covid Agency Salaries - CNA | B62: {=_xlfn.XLOOKUP(A62,'PR Trending Data'!A63:A128,'PR Trending Data'!B63:Y128)} -> 504 | C62: 0.2 | D62: 8450 | E62: 3.52 | F62: 0 | G62: 0 | H62: 0 | I62: 0 | J62: 0 | K62: 0 | L62: 0 | M62: 0 | N62: 0 | O62: 0 | P62: 0 | Q62: 0 | R62: 0 | S62: 0 | T62: 0 | U62: 0 | V62: 0 | W62: 0 | X62: 0 | Y62: 0 | Z62: =B62+D62+F62+H62+J62+L62+N62+P62+R62+T62+V62+X62 -> 8954 | AA62: =C62+E62+G62+I62+K62+M62+O62+Q62+S62+U62+W62+Y62 -> 3.72
A63: TOTAL Agency Detail | B63: {=_xlfn.XLOOKUP(A63,'PR Trending Data'!A64:A129,'PR Trending Data'!B64:Y129)} -> 43008 | C63: 16.76 | D63: 34044 | E63: 14.18 | F63: 41815 | G63: 16.13 | H63: 12536 | I63: 5.56 | J63: 19596 | K63: 7.95 | L63: 11068 | M63: 4.79 | N63: 5598 | O63: 2.36 | P63: 5297 | Q63: 2.27 | R63: 36004 | S63: 14.62 | T63: 24402 | U63: 10.76 | V63: 2491 | W63: 1.16 | X63: 19442 | Y63: 7.93 | Z63: =SUM(Z57:Z62) -> 255300 | AA63: =SUM(AA57:AA62) -> 104.45
A64: Empire Detail | B64: {=_xlfn.XLOOKUP(A64,'PR Trending Data'!A65:A130,'PR Trending Data'!B65:Y130)} -> 0 | C64: 0 | D64: 0 | E64: 0 | F64: 0 | G64: 0 | H64: 0 | I64: 0 | J64: 0 | K64: 0 | L64: 0 | M64: 0 | N64: 0 | O64: 0 | P64: 0 | Q64: 0 | R64: 0 | S64: 0 | T64: 0 | U64: 0 | V64: 0 | W64: 0 | X64: 0 | Y64: 0
A65: Empire Staffing Salaries RN | B65: {=_xlfn.XLOOKUP(A65,'PR Trending Data'!A66:A131,'PR Trending Data'!B66:Y131)} -> 7307 | C65: 2.85 | D65: 5276 | E65: 2.2 | F65: 9591 | G65: 3.7 | H65: 2102 | I65: 0.93 | J65: 6920 | K65: 2.81 | L65: 10029 | M65: 4.34 | N65: 11586 | O65: 4.88 | P65: 3266 | Q65: 1.4 | R65: 12835 | S65: 5.21 | T65: 0 | U65: 0 | V65: 8223 | W65: 3.83 | X65: 18329 | Y65: 7.48 | Z65: =B65+D65+F65+H65+J65+L65+N65+P65+R65+T65+V65+X65 -> 95464 | AA65: =C65+E65+G65+I65+K65+M65+O65+Q65+S65+U65+W65+Y65 -> 39.63
A66: Empire Staffing Salaries LPN | B66: {=_xlfn.XLOOKUP(A66,'PR Trending Data'!A67:A132,'PR Trending Data'!B67:Y132)} -> 0 | C66: 0 | D66: 0 | E66: 0 | F66: 0 | G66: 0 | H66: 0 | I66: 0 | J66: 0 | K66: 0 | L66: 0 | M66: 0 | N66: 0 | O66: 0 | P66: 0 | Q66: 0 | R66: 0 | S66: 0 | T66: 0 | U66: 0 | V66: 0 | W66: 0 | X66: 0 | Y66: 0 | Z66: =B66+D66+F66+H66+J66+L66+N66+P66+R66+T66+V66+X66 -> 0 | AA66: =C66+E66+G66+I66+K66+M66+O66+Q66+S66+U66+W66+Y66 -> 0
A67: Empire Staffing Salaries CNA | B67: {=_xlfn.XLOOKUP(A67,'PR Trending Data'!A68:A133,'PR Trending Data'!B68:Y133)} -> 0 | C67: 0 | D67: 912 | E67: 0.38 | F67: 1097 | G67: 0.42 | H67: 1059 | I67: 0.47 | J67: 335 | K67: 0.14 | L67: 0 | M67: 0 | N67: 2224 | O67: 0.94 | P67: 351 | Q67: 0.15 | R67: 2633 | S67: 1.07 | T67: 0 | U67: 0 | V67: 1464 | W67: 0.68 | X67: 3137 | Y67: 1.28 | Z67: =B67+D67+F67+H67+J67+L67+N67+P67+R67+T67+V67+X67 -> 13212 | AA67: =C67+E67+G67+I67+K67+M67+O67+Q67+S67+U67+W67+Y67 -> 5.53
A68: TOTAL Empire Detail | B68: {=_xlfn.XLOOKUP(A68,'PR Trending Data'!A69:A134,'PR Trending Data'!B69:Y134)} -> 7307 | C68: 2.85 | D68: 6188 | E68: 2.58 | F68: 10688 | G68: 4.12 | H68: 3161 | I68: 1.4 | J68: 7255 | K68: 2.94 | L68: 10029 | M68: 4.34 | N68: 13810 | O68: 5.81 | P68: 3618 | Q68: 1.55 | R68: 15468 | S68: 6.28 | T68: 0 | U68: 0 | V68: 9687 | W68: 4.52 | X68: 21466 | Y68: 8.76 | Z68: =SUM(Z65:Z67) -> 108676 | AA68: =SUM(AA65:AA67) -> 45.16
A69: Total Labor | B69: {=_xlfn.XLOOKUP(A69,'PR Trending Data'!A70:A135,'PR Trending Data'!B70:Y135)} -> 379332 | C69: 147.83 | D69: 332103 | E69: 138.32 | F69: 390919 | G69: 150.76 | H69: 373220 | I69: 165.65 | J69: 401243 | K69: 162.71 | L69: 412670 | M69: 178.65 | N69: 386222 | O69: 162.62 | P69: 365887 | Q69: 156.56 | R69: 378054 | S69: 153.56 | T69: 370281 | U69: 163.26 | V69: 373009 | W69: 173.9 | X69: 401772 | Y69: 163.92 | Z69: =B69+D69+F69+H69+J69+L69+N69+P69+R69+T69+V69+X69 -> 4564712 | AA69: =C69+E69+G69+I69+K69+M69+O69+Q69+S69+U69+W69+Y69 -> 1917.74
A70: Total Labor and Agency | B70: {=_xlfn.XLOOKUP(A70,'PR Trending Data'!A71:A136,'PR Trending Data'!B71:Y136)} -> 422340 | C70: 164.59 | D70: 366147 | E70: 152.5 | F70: 432734 | G70: 166.89 | H70: 385756 | I70: 171.22 | J70: 420839 | K70: 170.66 | L70: 423738 | M70: 183.44 | N70: 391820 | O70: 164.98 | P70: 371184 | Q70: 158.83 | R70: 414058 | S70: 168.18 | T70: 394683 | U70: 174.02 | V70: 375501 | W70: 175.06 | X70: 421214 | Y70: 171.85 | Z70: =B70+D70+F70+H70+J70+L70+N70+P70+R70+T70+V70+X70 -> 4820014 | AA70: =C70+E70+G70+I70+K70+M70+O70+Q70+S70+U70+W70+Y70 -> 2022.22
A71: Total Labor and Empire | B71: {=_xlfn.XLOOKUP(A71,'PR Trending Data'!A72:A137,'PR Trending Data'!B72:Y137)} -> 386639 | C71: 150.68 | D71: 338291 | E71: 140.9 | F71: 401607 | G71: 154.88 | H71: 376381 | I71: 167.06 | J71: 408498 | K71: 165.65 | L71: 422699 | M71: 182.99 | N71: 400032 | O71: 168.43 | P71: 369505 | Q71: 158.11 | R71: 393522 | S71: 159.84 | T71: 370281 | U71: 163.26 | V71: 382697 | W71: 178.41 | X71: 423238 | Y71: 172.68 | Z71: =B71+D71+F71+H71+J71+L71+N71+P71+R71+T71+V71+X71 -> 4673390 | AA71: =C71+E71+G71+I71+K71+M71+O71+Q71+S71+U71+W71+Y71 -> 1962.89
A72: Total Labor + Agency + Empire | B72: {=_xlfn.XLOOKUP(A72,'PR Trending Data'!A73:A138,'PR Trending Data'!B73:Y138)} -> 429647 | C72: 167.44 | D72: 372334 | E72: 155.07 | F72: 443422 | G72: 171.01 | H72: 388917 | I72: 172.62 | J72: 428094 | K72: 173.6 | L72: 433767 | M72: 187.78 | N72: 405630 | O72: 170.79 | P72: 374802 | Q72: 160.38 | R72: 429527 | S72: 174.46 | T72: 394683 | U72: 174.02 | V72: 385188 | W72: 179.57 | X72: 442680 | Y72: 180.61 | Z72: =B72+D72+F72+H72+J72+L72+N72+P72+R72+T72+V72+X72 -> 4928691 | AA72: =C72+E72+G72+I72+K72+M72+O72+Q72+S72+U72+W72+Y72 -> 2067.35
A73: Grand Total Costs including Tax | B73: {=_xlfn.XLOOKUP(A73,'PR Trending Data'!A74:A139,'PR Trending Data'!B74:Y139)} -> 473308 | C73: 184.45 | D73: 408103 | E73: 169.97 | F73: 480384 | G73: 185.26 | H73: 423046 | I73: 187.77 | J73: 463715 | K73: 188.04 | L73: 467115 | M73: 202.21 | N73: 437162 | O73: 184.07 | P73: 404362 | Q73: 173.03 | R73: 459264 | S73: 186.54 | T73: 419712 | U73: 185.06 | V73: 414316 | W73: 193.15 | X73: 474863 | Y73: 193.74 | Z73: =B73+D73+F73+H73+J73+L73+N73+P73+R73+T73+V73+X73 -> 5325350 | AA73: =C73+E73+G73+I73+K73+M73+O73+Q73+S73+U73+W73+Y73 -> 2233.29

Sheet BS Data
A1: ?"Date: May 8 | B1: 2026" | C1: Allure of Peru | D1: Facility #IL6004303
A2: Time: 12:07:07 EDT | B2: Balance Sheet Analysis
A3: User: Roth - Tracy Morkunas | B3: As Of 12/31/2025
A5: Include Adjustment Periods: NO | B5: Include Closing Periods: NO
B7: CURRENT PERIOD_Actual $
A8: Current Assets
A9: Cash | B9: 22699
A10: Accounts Receivable | B10: 1715902
A11: Allowance for Doubtful Account | B11: -50489
A12: Prepaid Expense | B12: 156097
A13: Intercompany Receivable | B13: -611166
A14: Other Current Assets | B14: 1783
A15: TOTAL Current Assets | B15: 1234827
A16: Fixed Assets
A17: Building and Land | B17: 3416
A18: Equipment | B18: 131927
A19: Furniture and Fixtures | B19: 4749
A20: Leasehold Improvements | B20: 685794
A21: CIP - Leasehold Improvements | B21: 0
A22: Vehicles | B22: 1099
A23: Organization Costs | B23: 23124
A24: Loan Costs | B24: 0
A25: Less Accumulated Depreciation | B25: -180889
A26: Replacement Reserve | B26: 31590
A27: TOTAL Fixed Assets | B27: 700810
A28: Total Assets | B28: 1935637
A29: Current Liabilities
A30: Accounts Payable | B30: 782460
A31: Credit Card Payable | B31: 0
A32: Accrued Expenses | B32: 231834
A33: Accrued Payroll | B33: 116658
A34: Accrued Benefits | B34: 0
A35: Payroll Liabilites | B35: 0
A36: Line of Credit | B36: 850000
A37: Other Current Liabilities | B37: 1446
A38: Resident Security Deposits | B38: 0
A39: TOTAL Current Liabilities | B39: 1982397
A40: Long Term Liabilities | B40: 0
A41: TOTAL Liabilities | B41: 1982397
A42: Equity
A43: Equity | B43: 759644
A44: Distributions | B44: -1145000
A45: Net Income - (Loss) | B45: 338596
A46: Net Income | B46: 338596
A47: TOTAL Equity | B47: -46760
A48: Total Liabilities and Equity | B48: 1935637

Sheet P&L Data
A1: ?"Date: May 8 | B1: 2026" | C1: Allure of Peru | D1: Facility #IL6004303
A2: Time: 12:08:08 EDT | B2: Income Statement Detail
A3: User: Roth - Tracy Morkunas | B3: 1/1/2025 to 12/31/2025
A5: Include Adjustment Periods: NO | B5: Include Closing Periods: NO
B7: CURRENT PERIOD_Actual $ | C7: CURRENT PERIOD_Actual / Day | D7: YEAR TO DATE_Actual $ | E7: YEAR TO DATE_Actual / Day
A8: Revenue
A9: Medicaid | B9: 4650290 | C9: 279.75 | D9: 4650290 | E9: 279.75
A10: Hospice | B10: 404354 | C10: 278.29 | D10: 404354 | E10: 278.29
A11: Medicare A | B11: 2480638 | C11: 682.43 | D11: 2480638 | E11: 682.43
A12: Commercial Insurance | B12: 924175 | C12: 458.65 | D12: 924175 | E12: 458.65
A13: Private Pay | B13: 1446974 | C13: 295.24 | D13: 1446974 | E13: 295.24
A14: Veteran Affairs | B14: 0 | D14: 0
A15: Medicare / Managed Care B | B15: 297113 | D15: 297113
A16: Private Pay Independent Living | B16: 0 | D16: 0
A17: Home Care Income | B17: 0 | D17: 0
A18: Daily Training Program | B18: 0 | D18: 0
A19: Other | B19: 5276 | D19: 5276
A20: Stimulus Income | B20: 0 | D20: 0
A21: Incentive Payments | B21: 215428 | C21: 7.53 | D21: 215428 | E21: 7.53
A22: TOTAL Revenue | B22: 10424247 | C22: 364.14 | D22: 10424247 | E22: 364.14
A23: Patient Days
A24: Medicaid | B24: 16663 | D24: 16663
A25: Hospice | B25: 1453 | D25: 1453
A26: Medicare A | B26: 3635 | D26: 3635
A27: Commercial Insurance | B27: 2015 | D27: 2015
A28: Private Pay | B28: 4894 | D28: 4894
A29: Veteran Affairs | B29: 0 | D29: 0
A30: Independent Living | B30: 0 | D30: 0
A31: TOTAL Patient Days | B31: 28660 | D31: 28660
B32: 0 | D32: 0
A33: Nursing & Medical
A34: Director Of Nursing | B34: 105946 | C34: 3.7 | D34: 105946 | E34: 3.7
A35: Assistant Director Of Nursing | B35: 85613 | C35: 2.99 | D35: 85613 | E35: 2.99
A36: Payroll RN | B36: 800771 | C36: 27.97 | D36: 800771 | E36: 27.97
A37: Payroll LPN | B37: 442824 | C37: 15.47 | D37: 442824 | E37: 15.47
A38: Payroll Aides & Orderlies | B38: 1861774 | C38: 65.04 | D38: 1861774 | E38: 65.04
A39: Payroll Nursing Clerical | B39: 92496 | C39: 3.23 | D39: 92496 | E39: 3.23
A40: Payroll Medical Records | B40: 0 | C40: 0 | D40: 0 | E40: 0
A41: Contract RN | B41: 177691 | C41: 6.21 | D41: 177691 | E41: 6.21
A42: Contract LPN | B42: 18418 | C42: 0.64 | D42: 18418 | E42: 0.64
A43: Contract Aides & Orderlies | B43: 167869 | C43: 5.86 | D43: 167869 | E43: 5.86
A44: Medical Supplies | B44: 107643 | C44: 3.76 | D44: 107643 | E44: 3.76
A45: Covid-19 Medical Supplies | B45: 8298 | C45: 0.29 | D45: 8298 | E45: 0.29
... A55: TOTAL Nursing & Medical | B55: 4107575 | C55: 143.49 | D55: 4107575 | E55: 143.49
A56: Therapy & Ancillary Services
A57: Physical Therapy Services | B57: 273865 | C57: 9.57 | D57: 273865 | E57: 9.57
A58: Occupational Therapy Services | B58: 240239 | C58: 8.39 | D58: 240239 | E58: 8.39
A59: Speech Therapy Services | B59: 33775 | C59: 1.18 | D59: 33775 | E59: 1.18
A60: Pharmacy Consultant | B60: 14341 | C60: 0.5 | D60: 14341 | E60: 0.5
A61: RX Drugs | B61: 71025 | C61: 2.48 | D61: 71025 | E61: 2.48
A62: Drugs Managed Care | B62: 38945 | C62: 1.36 | D62: 38945 | E62: 1.36
A63: VA - Drugs | B63: 0 | D63: 0
A64: Radiology | B64: 5946 | C64: 0.21 | D64: 5946 | E64: 0.21
A65: Laboratory | B65: 17083 | C65: 0.6 | D65: 17083 | E65: 0.6
A66: TOTAL Therapy & Ancillary Services | B66: 695220 | C66: 24.29 | D66: 695220 | E66: 24.29
A67: Social Services
A68: Payroll Social Services | B68: 69813 | C68: 2.44 | D68: 69813 | E68: 2.44
A69: Payroll Admissions | B69: 39025 | C69: 1.36 | D69: 39025 | E69: 1.36
A70: Social Service Supplies | B70: 0 | C70: 0 | D70: 0 | E70: 0
A71: Social Service Consultant | B71: 5565 | C71: 0.19 | D71: 5565 | E71: 0.19
A72: TOTAL Social Services | B72: 114403 | C72: 4 | D72: 114403 | E72: 4
B73: 0 | D73: 0
A74: Leisure Time & Activities
A75: Payroll Activity | B75: 142657 | C75: 4.98 | D75: 142657 | E75: 4.98
A76: Activity Supplies | B76: 19289 | C76: 0.67 | D76: 19289 | E76: 0.67
A77: TOTAL Leisure Time & Activities | B77: 161946 | C77: 5.66 | D77: 161946 | E77: 5.66
A78: House & Plant Costs
A79: Payroll Housekeeping | B79: 133497 | C79: 4.66 | D79: 133497 | E79: 4.66
A80: Payroll Laundry | B80: 70169 | C80: 2.45 | D80: 70169 | E80: 2.45
A81: Payroll Maintenance | B81: 143776 | C81: 5.02 | D81: 143776 | E81: 5.02
A82: Payroll Security | B82: 0 | C82: 0 | D82: 0 | E82: 0
A83: Housekeeping Supplies | B83: 20397 | C83: 0.71 | D83: 20397 | E83: 0.71
A84: Covid-19 Housekeeping Supplies | B84: 0 | C84: 0 | D84: 0 | E84: 0
A85: Laundry Supplies | B85: 4667 | C85: 0.16 | D85: 4667 | E85: 0.16
A86: Linen Replacement | B86: 8525 | C86: 0.3 | D86: 8525 | E86: 0.3
A87: Maintenance Supplies | B87: 30250 | C87: 1.06 | D87: 30250 | E87: 1.06
A88: Maintenance Services | B88: 207209 | C88: 7.24 | D88: 207209 | E88: 7.24
A89: Lawn & Snow Removal Services | B89: 8600 | C89: 0.3 | D89: 8600 | E89: 0.3
A90: Scavenger | B90: 16218 | C90: 0.57 | D90: 16218 | E90: 0.57
... A94: TOTAL House & Plant Costs | B94: 733852 | C94: 25.63 | D94: 733852 | E94: 25.63
A95: Food & Nutrition
A96: Payroll Dietary | B96: 336433 | C96: 11.75 | D96: 336433 | E96: 11.75
A97: Food | B97: 229970 | C97: 8.03 | D97: 229970 | E97: 8.03
A98: Food Supplements | B98: 16972 | C98: 0.59 | D98: 16972 | E98: 0.59
A99: Dietary Supplies | B99: 27844 | C99: 0.97 | D99: 27844 | E99: 0.97
A100: Covid-19 Dietary Supplies | B100: 0 | C100: 0 | D100: 0 | E100: 0
A101: Dietary Consultant | B101: 760 | C101: 0.03 | D101: 760 | E101: 0.03
A102: TOTAL Food & Nutrition | B102: 611979 | C102: 21.38 | D102: 611979 | E102: 21.38
A103: Employee Welfare Costs
A104: Payroll Taxes | B104: 396658 | C104: 13.86 | D104: 396658 | E104: 13.86
A105: Workmans Comp Insurance | B105: 37669 | C105: 1.32 | D105: 37669 | E105: 1.32
A106: Employee Benefits | B106: 18006 | C106: 0.63 | D106: 18006 | E106: 0.63
A107: Employee Insurance | B107: 119935 | C107: 4.19 | D107: 119935 | E107: 4.19
A108: Education & Seminars | B108: 6635 | C108: 0.23 | D108: 6635 | E108: 0.23
A109: Pension | B109: 32297 | C109: 1.13 | D109: 32297 | E109: 1.13
A110: TOTAL Employee Welfare Costs | B110: 611200 | C110: 21.35 | D110: 611200 | E110: 21.35
A111: General & Administrative
A112: Payroll Administrative | B112: 150615 | C112: 5.26 | D112: 150615 | E112: 5.26
A113: Payroll Office | B113: 101094 | C113: 3.53 | D113: 101094 | E113: 3.53
A114: Payroll Marketing | B114: 0 | C114: 0 | D114: 0 | E114: 0
...

Sheet P&L Trending Data
A1: ?"Date: May 8 | B1: 2026" | C1: Allure of Peru | D1: Facility #IL6004303
A2: Time: 12:08:42 EDT | B2: Income Statement Trending Detail - GGM
A3: User: Roth - Tracy Morkunas
B4: 1/1/2025 to 12/31/2025
A6: Include Adjustment Periods: NO | B6: Include Closing Periods: NO
B8: January 25_Actual $ | C8: January 25_Actual / Day | D8: February 25_Actual $ | E8: February 25_Actual / Day | F8: March 25_Actual $ | G8: March 25_Actual / Day | H8: April 25_Actual $ | I8: April 25_Actual / Day | J8: May 25_Actual $ | K8: May 25_Actual / Day | L8: June 25_Actual $ | M8: June 25_Actual / Day | N8: July 25_Actual $ | O8: July 25_Actual / Day | P8: August 25_Actual $ | Q8: August 25_Actual / Day | R8: September 25_Actual $ | S8: September 25_Actual / Day | T8: October 25_Actual $ | U8: October 25_Actual / Day | V8: November 25_Actual $ | W8: November 25_Actual / Day | X8: December 25_Actual $ | Y8: December 25_Actual / Day | Z8: TOTALS_Actual $ | AA8: TOTALS_Actual / Day
A9: Revenue
A10: Medicaid | B10: 388276 | C10: 276.75 | D10: 408258 | E10: 279.82 | F10: 406113 | G10: 278.35 | H10: 370960 | I10: 282.53 | J10: 371972 | K10: 282.87 | L10: 407087 | M10: 282.11 | N10: 395127 | O10: 295.98 | P10: 413088 | Q10: 295.7 | R10: 410913 | S10: 296.05 | T10: 369135 | U10: 262.73 | V10: 320350 | W10: 261.3 | X10: 389012 | Y10: 262.85 | Z10: 4650290 | AA10: 279.75
A11: Hospice | B11: 23801 | C11: 276.76 | D11: 26023 | E11: 279.82 | F11: 33402 | G11: 278.35 | H11: 32504 | I11: 282.64 | J11: 37308 | K11: 282.64 | L11: 18649 | M11: 286.91 | N11: 27562 | O11: 296.37 | P11: 41492 | Q11: 296.37 | R11: 42085 | S11: 296.37 | T11: 37000 | U11: 262.41 | V11: 30470 | W11: 253.92 | X11: 54056 | Y11: 262.41 | Z11: 404354 | AA11: 278.29
A12: Medicare A | B12: 276629 | C12: 726.06 | D12: 190410 | E12: 721.25 | F12: 271459 | G12: 696.05 | H12: 231688 | I12: 675.47 | J12: 234861 | K12: 727.13 | L12: 188683 | M12: 681.16 | N12: 195908 | O12: 653.03 | P12: 150286 | Q12: 615.93 | R12: 180454 | S12: 649.11 | T12: 173470 | U12: 649.7 | V12: 165678 | W12: 676.24 | X12: 221112 | Y12: 684.56 | Z12: 2480638 | AA12: 682.43
A13: Commercial Insurance | B13: 106231 | C13: 440.79 | D13: 113904 | E13: 433.09 | F13: 112617 | G13: 415.56 | H13: 58193 | I13: 476.99 | J13: 45675 | K13: 400.66 | L13: 43336 | M13: 577.81 | N13: 52479 | O13: 460.34 | P13: 77254 | Q13: 508.25 | R13: 91873 | S13: 419.51 | T13: 53007 | U13: 486.3 | V13: 50226 | W13: 469.41 | X13: 119379 | Y13: 523.59 | Z13: 924175 | AA13: 458.65
A14: Private Pay | B14: 138594 | C14: 304.6 | D14: 98035 | E14: 304.46 | F14: 102135 | G14: 289.34 | H14: 103587 | I14: 287.74 | J14: 167586 | K14: 287.95 | L14: 140418 | M14: 312.04 | N14: 155881 | O14: 292.46 | P14: 123863 | Q14: 306.59 | R14: 130438 | S14: 299.86 | T14: 104916 | U14: 303.22 | V14: 120531 | W14: 269.64 | X14: 60990 | Y14: 285 | Z14: 1446974 | AA14: 295.24
A15: Veteran Affairs | B15: 0 | D15: 0 | F15: 0 | H15: 0 | J15: 0 | L15: 0 | N15: 0 | P15: 0 | R15: 0 | T15: 0 | V15: 0 | X15: 0 | Z15: 0
A16: Medicare / Managed Care B | B16: 22407 | D16: 1600 | F16: 38819 | H16: 21411 | J16: 26503 | L16: 27290 | N16: 31718 | P16: 29662 | R16: 24022 | T16: 32306 | V16: 18907 | X16: 22468 | Z16: 297113
A17: Private Pay Independent Living | B17: 0 | D17: 0 | F17: 0 | H17: 0 | J17: 0 | L17: 0 | N17: 0 | P17: 0 | R17: 0 | T17: 0 | V17: 0 | X17: 0 | Z17: 0
A18: Home Care Income | B18: 0 | D18: 0 | F18: 0 | H18: 0 | J18: 0 | L18: 0 | N18: 0 | P18: 0 | R18: 0 | T18: 0 | V18: 0 | X18: 0 | Z18: 0
A19: Daily Training Program | B19: 0 | D19: 0 | F19: 0 | H19: 0 | J19: 0 | L19: 0 | N19: 0 | P19: 0 | R19: 0 | T19: 0 | V19: 0 | X19: 0 | Z19: 0
A20: Other | B20: 313 | D20: 1116 | F20: 84 | H20: 82 | J20: 96 | L20: 114 | N20: 87 | P20: 1923 | R20: 139 | T20: 635 | V20: 578 | X20: 108 | Z20: 5276
A21: Stimulus Income | B21: 0 | D21: 0 | F21: 0 | H21: 0 | J21: 0 | L21: 0 | N21: 0 | P21: 0 | R21: 0 | T21: 0 | V21: 0 | X21: 0 | Z21: 0
A22: Incentive Payments | B22: 18506 | C22: 7.21 | D22: 18506 | E22: 7.71 | F22: 18506 | G22: 7.14 | H22: 16901 | I22: 7.5 | J22: 16901 | K22: 6.85 | L22: 16901 | M22: 7.32 | N22: 18546 | O22: 7.81 | P22: 18546 | Q22: 7.94 | R22: 18546 | S22: 7.53 | T22: 18546 | U22: 8.18 | V22: 17166 | W22: 8 | X22: 17856 | Y22: 7.29 | Z22: 215428 | AA22: 7.53
A23: TOTAL Revenue | B23: 974758 | C23: 379.87 | D23: 857852 | E23: 357.29 | F23: 983136 | G23: 379.15 | H23: 835326 | I23: 370.76 | J23: 900903 | K23: 365.33 | L23: 842479 | M23: 364.71 | N23: 877308 | O23: 369.39 | P23: 856113 | Q23: 366.33 | R23: 898468 | S23: 364.93 | T23: 789014 | U23: 347.89 | V23: 723906 | W23: 337.49 | X23: 884982 | Y23: 361.07 | Z23: 10424247 | AA23: 364.14
A24: Patient Days
A25: Medicaid | B25: 1445 | D25: 1459 | F25: 1452 | H25: 1313 | J25: 1315 | L25: 1449 | N25: 1335 | P25: 1397 | R25: 1388 | T25: 1405 | V25: 1225 | X25: 1480 | Z25: 16663
A26: Hospice | B26: 86 | D26: 93 | F26: 120 | H26: 115 | J26: 132 | L26: 65 | N26: 93 | P26: 140 | R26: 142 | T26: 141 | V26: 120 | X26: 206 | Z26: 1453
A27: Medicare A | B27: 381 | D27: 264 | F27: 390 | H27: 343 | J27: 323 | L27: 277 | N27: 300 | P27: 244 | R27: 278 | T27: 267 | V27: 245 | X27: 323 | Z27: 3635
A28: Commercial Insurance | B28: 241 | D28: 263 | F28: 271 | H28: 122 | J28: 114 | L28: 75 | N28: 114 | P28: 152 | R28: 219 | T28: 109 | V28: 107 | X28: 228 | Z28: 2015
A29: Private Pay | B29: 455 | D29: 322 | F29: 353 | H29: 360 | J29: 582 | L29: 450 | N29: 533 | P29: 404 | R29: 435 | T29: 340 | V29: 442 | X29: 218 | Z29: 4894
A30: Veteran Affairs | B30: 0 | D30: 0 | F30: 0 | H30: 0 | J30: 0 | L30: 0 | N30: 0 | P30: 0 | R30: 0 | T30: 0 | V30: 0 | X30: 0 | Z30: 0
A31: Independent Living | B31: 0 | D31: 0 | F31: 0 | H31: 0 | J31: 0 | L31: 0 | N31: 0 | P31: 0 | R31: 0 | T31: 0 | V31: 0 | X31: 0 | Z31: 0
A32: TOTAL Patient Days | B32: 2608 | D32: 2401 | F32: 2586 | H32: 2253 | J32: 2466 | L32: 2316 | N32: 2375 | P32: 2337 | R32: 2462 | T32: 2262 | V32: 2139 | X32: 2455 | Z32: 28660
A33: Nursing & Medical
A34: Director Of Nursing | B34: 9212 | C34: 3.59 | D34: 7717 | E34: 3.21 | F34: 8952 | G34: 3.45 | H34: 8492 | I34: 3.77 | J34: 8997 | K34: 3.65 | L34: 8509 | M34: 3.68 | N34: 10067 | O34: 4.24 | P34: 8597 | Q34: 3.68 | R34: 8438 | S34: 3.43 | T34: 9040 | U34: 3.99 | V34: 9054 | W34: 4.22 | X34: 8871 | Y34: 3.62 | Z34: 105946 | AA34: 3.7
A35: Assistant Director Of Nursing | B35: 7877 | C35: 3.07 | D35: 7354 | E35: 3.06 | F35: 7832 | G35: 3.02 | H35: 7552 | I35: 3.35 | J35: 8298 | K35: 3.36 | L35: 7532 | M35: 3.26 | N35: 7601 | O35: 3.2 | P35: 7638 | Q35: 3.27 | R35: 6659 | S35: 2.7 | T35: 1904 | U35: 0.84 | V35: 6738 | W35: 3.14 | X35: 8630 | Y35: 3.52 | Z35: 85613 | AA35: 2.99
A36: Payroll RN | B36: 65236 | C36: 25.42 | D36: 60365 | E36: 25.14 | F36: 68632 | G36: 26.47 | H36: 69671 | I36: 30.92 | J36: 71475 | K36: 28.98 | L36: 69227 | M36: 29.97 | N36: 72869 | O36: 30.68 | P36: 66824 | Q36: 28.59 | R36: 64087 | S36: 26.03 | T36: 66427 | U36: 29.29 | V36: 64275 | W36: 29.97 | X36: 61682 | Y36: 25.17 | Z36: 800771 | AA36: 27.97
A37: Payroll LPN | B37: 36740 | C37: 14.32 | D37: 36131 | E37: 15.05 | F37: 35983 | G37: 13.88 | H37: 33791 | I37: 15 | J37: 33989 | K37: 13.78 | L37: 40210 | M37: 17.41 | N37: 34691 | O37: 14.61 | P37: 34825 | Q37: 14.9 | R37: 35716 | S37: 14.51 | T37: 40897 | U37: 18.03 | V37: 39372 | W37: 18.36 | X37: 40479 | Y37: 16.52 | Z37: 442824 | AA37: 15.47
A38: Payroll Aides & Orderlies | B38: 158997 | C38: 61.96 | D38: 131266 | E38: 54.67 | F38: 156709 | G38: 60.44 | H38: 157935 | I38: 70.1 | J38: 171345 | K38: 69.48 | L38: 162985 | M38: 70.56 | N38: 155904 | O38: 65.64 | P38: 145993 | Q38: 62.47 | R38: 154712 | S38: 62.84 | T38: 142246 | U38: 62.72 | V38: 151314 | W38: 70.54 | X38: 172369 | Y38: 70.33 | Z38: 1861774 | AA38: 65.04
A39: Payroll Nursing Clerical | B39: 7723 | C39: 3.01 | D39: 7800 | E39: 3.25 | F39: 7670 | G39: 2.96 | H39: 7340 | I39: 3.26 | J39: 8444 | K39: 3.42 | L39: 7123 | M39: 3.08 | N39: 7715 | O39: 3.25 | P39: 7615 | Q39: 3.26 | R39: 7479 | S39: 3.04 | T39: 7624 | U39: 3.36 | V39: 7485 | W39: 3.49 | X39: 8478 | Y39: 3.46 | Z39: 92496 | AA39: 3.23
A40: Payroll Medical Records | B40: 0 | C40: 0 | D40: 0 | E40: 0 | F40: 0 | G40: 0 | H40: 0 | I40: 0 | J40: 0 | K40: 0 | L40: 0 | M40: 0 | N40: 0 | O40: 0 | P40: 0 | Q40: 0 | R40: 0 | S40: 0 | T40: 0 | U40: 0 | V40: 0 | W40: 0 | X40: 0 | Y40: 0 | Z40: 0 | AA40: 0
A41: Contract RN | B41: 24990 | C41: 9.74 | D41: 10031 | E41: 4.18 | F41: 15243 | G41: 5.88 | H41: 4530 | I41: 2.01 | J41: 15581 | K41: 6.32 | L41: 13713 | M41: 5.94 | N41: 13755 | O41: 5.79 | P41: 5793 | Q41: 2.48 | R41: 26888 | S41: 10.92 | T41: 12299 | U41: 5.42 | V41: 8223 | W41: 3.83 | X41: 26644 | Y41: 10.87 | Z41: 177691 | AA41: 6.21
A42: Contract LPN | B42: 7758 | C42: 3.02 | D42: 1974 | E42: 0.82 | F42: 3687 | G42: 1.42 | H42: 0 | I42: 0 | J42: 1264 | K42: 0.51 | L42: 193 | M42: 0.08 | N42: 882 | O42: 0.37 | P42: 0 | Q42: 0 | R42: 0 | S42: 0 | T42: 260 | U42: 0.11 | V42: 0 | W42: 0 | X42: 2399 | Y42: 0.98 | Z42: 18418 | AA42: 0.64
A43: Contract Aides & Orderlies | B43: 17567 | C43: 6.85 | D43: 28226 | E43: 11.76 | F43: 33572 | G43: 12.95 | H43: 11167 | I43: 4.96 | J43: 10005 | K43: 4.06 | L43: 7191 | M43: 3.11 | N43: 4771 | O43: 2.01 | P43: 3121 | Q43: 1.34 | R43: 24585 | S43: 9.99 | T43: 11843 | U43: 5.22 | V43: 3955 | W43: 1.84 | X43: 11865 | Y43: 4.84 | Z43: 167869 | AA43: 5.86
A44: Medical Supplies | B44: 9096 | C44: 3.54 | D44: 8183 | E44: 3.41 | F44: 11766 | G44: 4.54 | H44: 8005 | I44: 3.55 | J44: 9016 | K44: 3.66 | L44: 7306 | M44: 3.16 | N44: 8808 | O44: 3.71 | P44: 7412 | Q44: 3.17 | R44: 10819 | S44: 4.39 | T44: 8067 | U44: 3.56 | V44: 8778 | W44: 4.09 | X44: 10387 | Y44: 4.24 | Z44: 107643 | AA44: 3.76
A45: Covid-19 Medical Supplies | B45: 1662 | C45: 0.65 | D45: 372 | E45: 0.16 | F45: 0 | G45: 0 | H45: 158 | I45: 0.07 | J45: 320 | K45: 0.13 | L45: 30 | M45: 0.01 | N45: 285 | O45: 0.12 | P45: 384 | Q45: 0.16 | R45: 383 | S45: 0.16 | T45: 712 | U45: 0.31 | V45: 2534 | W45: 1.18 | X45: 1459 | Y45: 0.6 | Z45: 8298 | AA45: 0.29
... A55: TOTAL Nursing & Medical | B55: 365224 | C55: 142.33 | D55: 325396 | E55: 135.53 | F55: 380608 | G55: 146.78 | H55: 322574 | I55: 143.18 | J55: 355789 | K55: 144.28 | L55: 340922 | M55: 147.59 | N55: 348318 | O55: 146.66 | P55: 307417 | Q55: 131.54 | R55: 359100 | S55: 145.86 | T55: 318835 | U55: 140.58 | V55: 315529 | W55: 147.1 | X55: 367862 | Y55: 150.09 | Z55: 4107575 | AA55: 143.49
A56: Therapy & Ancillary Services
A57: Physical Therapy Services | B57: 28242 | C57: 11.01 | D57: 23273 | E57: 9.69 | F57: 25243 | G57: 9.74 | H57: 20942 | I57: 9.29 | J57: 21526 | K57: 8.73 | L57: 19019 | M57: 8.23 | N57: 22612 | O57: 9.52 | P57: 22122 | Q57: 9.47 | R57: 23626 | S57: 9.6 | T57: 22170 | U57: 9.78 | V57: 20119 | W57: 9.38 | X57: 24973 | Y57: 10.19 | Z57: 273865 | AA57: 9.57
A58: Occupational Therapy Services | B58: 23197 | C58: 9.04 | D58: 19030 | E58: 7.93 | F58: 23212 | G58: 8.95 | H58: 19320 | I58: 8.58 | J58: 20289 | K58: 8.23 | L58: 17772 | M58: 7.69 | N58: 19961 | O58: 8.4 | P58: 19396 | Q58: 8.3 | R58: 19165 | S58: 7.78 | T58: 19990 | U58: 8.81 | V58: 17380 | W58: 8.1 | X58: 21528 | Y58: 8.78 | Z58: 240239 | AA58: 8.39
A59: Speech Therapy Services | B59: 3409 | C59: 1.33 | D59: 2320 | E59: 0.97 | F59: 3156 | G59: 1.22 | H59: 2119 | I59: 0.94 | J59: 1956 | K59: 0.79 | L59: 2444 | M59: 1.06 | N59: 4217 | O59: 1.78 | P59: 4109 | Q59: 1.76 | R59: 3235 | S59: 1.31 | T59: 3345 | U59: 1.47 | V59: 2008 | W59: 0.94 | X59: 1457 | Y59: 0.59 | Z59: 33775 | AA59: 1.18
A60: Pharmacy Consultant | B60: 700 | C60: 0.27 | D60: 1512 | E60: 0.63 | F60: 1436 | G60: 0.55 | H60: 1356 | I60: 0.6 | J60: 1356 | K60: 0.55 | L60: 1300 | M60: 0.56 | N60: 1265 | O60: 0.53 | P60: 1340 | Q60: 0.57 | R60: 1292 | S60: 0.52 | T60: 1384 | U60: 0.61 | V60: 700 | W60: 0.33 | X60: 700 | Y60: 0.29 | Z60: 14341 | AA60: 0.5
A61: RX Drugs | B61: 8000 | C61: 3.12 | D61: 8176 | E61: 3.41 | F61: 13497 | G61: 5.21 | H61: 7056 | I61: 3.13 | J61: 12407 | K61: 5.03 | L61: 4554 | M61: 1.97 | N61: 5755 | O61: 2.42 | P61: 5131 | Q61: 2.2 | R61: 3564 | S61: 1.45 | T61: 2884 | U61: 1.27 | V61: 0 | W61: 0 | X61: 0 | Y61: 0 | Z61: 71025 | AA61: 2.48
A62: Drugs Managed Care | B62: 4000 | C62: 1.56 | D62: 6518 | E62: 2.71 | F62: 1000 | G62: 0.39 | H62: 2745 | I62: 1.22 | J62: 0 | K62: 0 | L62: 0 | M62: 0 | N62: 6057 | O62: 2.55 | P62: 6843 | Q62: 2.93 | R62: 5215 | S62: 2.12 | T62: 6566 | U62: 2.9 | V62: 0 | W62: 0 | X62: 0 | Y62: 0 | Z62: 38945 | AA62: 1.36
A63: VA - Drugs | B63: 0 | D63: 0 | F63: 0 | H63: 0 | J63: 0 | L63: 0 | N63: 0 | P63: 0 | R63: 0 | T63: 0 | V63: 0 | X63: 0 | Z63: 0
A64: Radiology | B64: 586 | C64: 0.23 | D64: 58 | E64: 0.02 | F64: 431 | G64: 0.17 | H64: 654 | I64: 0.29 | J64: 543 | K64: 0.22 | L64: 762 | M64: 0.33 | N64: 216 | O64: 0.09 | P64: 433 | Q64: 0.19 | R64: 760 | S64: 0.31 | T64: 378 | U64: 0.17 | V64: 245 | W64: 0.11 | X64: 880 | Y64: 0.36 | Z64: 5946 | AA64: 0.21
A65: Laboratory | B65: 774 | C65: 0.3 | D65: 4102 | E65: 1.71 | F65: 2142 | G65: 0.83 | H65: 685 | I65: 0.3 | J65: 1258 | K65: 0.51 | L65: 2600 | M65: 1.13 | N65: 47 | O65: 0.02 | P65: 1753 | Q65: 0.75 | R65: 1624 | S65: 0.66 | T65: 1454 | U65: 0.64 | V65: 605 | W65: 0.28 | X65: 40 | Y65: 0.02 | Z65: 17083 | AA65: 0.6
A66: TOTAL Therapy & Ancillary Services | B66: 68908 | C66: 26.85 | D66: 64989 | E66: 27.07 | F66: 70117 | G66: 27.04 | H66: 54877 | I66: 24.36 | J66: 59335 | K66: 24.06 | L66: 48450 | M66: 20.97 | N66: 60131 | O66: 25.32 | P66: 61126 | Q66: 26.16 | R66: 58481 | S66: 23.75 | T66: 58173 | U66: 25.65 | V66: 41056 | W66: 19.14 | X66: 49577 | Y66: 20.23 | Z66: 695220 | AA66: 24.29
A67: Social Services
A68: Payroll Social Services | B68: 5958 | C68: 2.32 | D68: 5176 | E68: 2.16 | F68: 5881 | G68: 2.27 | H68: 5760 | I68: 2.56 | J68: 5854 | K68: 2.37 | L68: 5563 | M68: 2.41 | N68: 5970 | O68: 2.51 | P68: 5762 | Q68: 2.47 | R68: 6067 | S68: 2.46 | T68: 6109 | U68: 2.69 | V68: 5845 | W68: 2.73 | X68: 5870 | Y68: 2.39 | Z68: 69813 | AA68: 2.44
A69: Payroll Admissions | B69: 0 | C69: 0 | D69: 0 | E69: 0 | F69: 5007 | G69: 1.93 | H69: 0 | I69: 0 | J69: 0 | K69: 0 | L69: 865 | M69: 0.37 | N69: 0 | O69: 0 | P69: 10570 | Q69: 4.52 | R69: 4636 | S69: 1.88 | T69: 5935 | U69: 2.62 | V69: 5935 | W69: 2.77 | X69: 6078 | Y69: 2.48 | Z69: 39025 | AA69: 1.36
A70: Social Service Supplies | B70: 0 | C70: 0 | D70: 0 | E70: 0 | F70: 0 | G70: 0 | H70: 0 | I70: 0 | J70: 0 | K70: 0 | L70: 0 | M70: 0 | N70: 0 | O70: 0 | P70: 0 | Q70: 0 | R70: 0 | S70: 0 | T70: 0 | U70: 0 | V70: 0 | W70: 0 | X70: 0 | Y70: 0 | Z70: 0 | AA70: 0
A71: Social Service Consultant | B71: 735 | C71: 0.29 | D71: 490 | E71: 0.2 | F71: 245 | G71: 0.09 | H71: 140 | I71: 0.06 | J71: 0 | K71: 0 | L71: 490 | M71: 0.21 | N71: 770 | O71: 0.32 | P71: 0 | Q71: 0 | R71: 770 | S71: 0.31 | T71: 840 | U71: 0.37 | V71: 0 | W71: 0 | X71: 1085 | Y71: 0.44 | Z71: 5565 | AA71: 0.19
A72: TOTAL Social Services | B72: 6693 | C72: 2.61 | D72: 5666 | E72: 2.36 | F72: 11133 | G72: 4.29 | H72: 5900 | I72: 2.62 | J72: 5854 | K72: 2.37 | L72: 6918 | M72: 2.99 | N72: 6740 | O72: 2.84 | P72: 16332 | Q72: 6.99 | R72: 11472 | S72: 4.66 | T72: 12884 | U72: 5.68 | V72: 11780 | W72: 5.49 | X72: 13033 | Y72: 5.32 | Z72: 114403 | AA72: 4
A73: Leisure Time & Activities
A74: Payroll Activity | B74: 11503 | C74: 4.48 | D74: 10884 | E74: 4.53 | F74: 11803 | G74: 4.55 | H74: 12040 | I74: 5.34 | J74: 12039 | K74: 4.88 | L74: 11998 | M74: 5.19 | N74: 12085 | O74: 5.09 | P74: 12009 | Q74: 5.14 | R74: 11764 | S74: 4.78 | T74: 11970 | U74: 5.28 | V74: 11860 | W74: 5.53 | X74: 12702 | Y74: 5.18 | Z74: 142657 | AA74: 4.98
A75: Activity Supplies | B75: 1008 | C75: 0.39 | D75: 1436 | E75: 0.6 | F75: 2736 | G75: 1.06 | H75: 946 | I75: 0.42 | J75: 1770 | K75: 0.72 | L75: 2096 | M75: 0.91 | N75: 936 | O75: 0.39 | P75: 1814 | Q75: 0.78 | R75: 1211 | S75: 0.49 | T75: 1291 | U75: 0.57 | V75: 1284 | W75: 0.6 | X75: 2760 | Y75: 1.13 | Z75: 19289 | AA75: 0.67
A76: TOTAL Leisure Time & Activities | B76: 12511 | C76: 4.88 | D76: 12320 | E76: 5.13 | F76: 14540 | G76: 5.61 | H76: 12986 | I76: 5.76 | J76: 13810 | K76: 5.6 | L76: 14094 | M76: 6.1 | N76: 13021 | O76: 5.48 | P76: 13823 | Q76: 5.91 | R76: 12975 | S76: 5.27 | T76: 13261 | U76: 5.85 | V76: 13144 | W76: 6.13 | X76: 15462 | Y76: 6.31 | Z76: 161946 | AA76: 5.66
A77: House & Plant Costs
A78: Payroll Housekeeping | B78: 10125 | C78: 3.95 | D78: 7116 | E78: 2.96 | F78: 7596 | G78: 2.93 | H78: 7423 | I78: 3.29 | J78: 10263 | K78: 4.16 | L78: 11343 | M78: 4.91 | N78: 11976 | O78: 5.04 | P78: 12031 | Q78: 5.15 | R78: 10548 | S78: 4.28 | T78: 13059 | U78: 5.76 | V78: 15390 | W78: 7.17 | X78: 16629 | Y78: 6.78 | Z78: 133497 | AA78: 4.66
A79: Payroll Laundry | B79: 6134 | C79: 2.39 | D79: 5539 | E79: 2.31 | F79: 7460 | G79: 2.88 | H79: 5610 | I79: 2.49 | J79: 5575 | K79: 2.26 | L79: 5347 | M79: 2.31 | N79: 5608 | O79: 2.36 | P79: 5467 | Q79: 2.34 | R79: 6371 | S79: 2.59 | T79: 5931 | U79: 2.62 | V79: 5481 | W79: 2.56 | X79: 5645 | Y79: 2.3 | Z79: 70169 | AA79: 2.45
A80: Payroll Maintenance | B80: 10874 | C80: 4.24 | D80: 7612 | E80: 3.17 | F80: 19147 | G80: 7.38 | H80: 9814 | I80: 4.36 | J80: 13985 | K80: 5.67 | L80: 25889 | M80: 11.21 | N80: 16046 | O80: 6.76 | P80: -1433 | Q80: -0.61 | R80: 14114 | S80: 5.73 | T80: 11113 | U80: 4.9 | V80: 7486 | W80: 3.49 | X80: 9129 | Y80: 3.72 | Z80: 143776 | AA80: 5.02
A81: Payroll Security | B81: 0 | C81: 0 | D81: 0 | E81: 0 | F81: 0 | G81: 0 | H81: 0 | I81: 0 | J81: 0 | K81: 0 | L81: 0 | M81: 0 | N81: 0 | O81: 0 | P81: 0 | Q81: 0 | R81: 0 | S81: 0 | T81: 0 | U81: 0 | V81: 0 | W81: 0 | X81: 0 | Y81: 0 | Z81: 0 | AA81: 0
A82: Housekeeping Supplies | B82: 2074 | C82: 0.81 | D82: 1885 | E82: 0.78 | F82: 1324 | G82: 0.51 | H82: 1679 | I82: 0.75 | J82: 1929 | K82: 0.78 | L82: 1259 | M82: 0.54 | N82: 1315 | O82: 0.55 | P82: 2583 | Q82: 1.11 | R82: 1501 | S82: 0.61 | T82: 1516 | U82: 0.67 | V82: 1519 | W82: 0.71 | X82: 1815 | Y82: 0.74 | Z82: 20397 | AA82: 0.71
A83: Covid-19 Housekeeping Supplies | B83: 0 | C83: 0 | D83: 0 | E83: 0 | F83: 0 | G83: 0 | H83: 0 | I83: 0 | J83: 0 | K83: 0 | L83: 0 | M83: 0 | N83: 0 | O83: 0 | P83: 0 | Q83: 0 | R83: 0 | S83: 0 | T83: 0 | U83: 0 | V83: 0 | W83: 0 | X83: 0 | Y83: 0 | Z83: 0 | AA83: 0
A84: Laundry Supplies | B84: 767 | C84: 0.3 | D84: 360 | E84: 0.15 | F84: 373 | G84: 0.14 | H84: 338 | I84: 0.15 | J84: 370 | K84: 0.15 | L84: 348 | M84: 0.15 | N84: 356 | O84: 0.15 | P84: 608 | Q84: 0.26 | R84: 457 | S84: 0.19 | T84: 0 | U84: 0 | V84: 321 | W84: 0.15 | X84: 368 | Y84: 0.15 | Z84: 4667 | AA84: 0.16
A85: Linen Replacement | B85: 1386 | C85: 0.54 | D85: 480 | E85: 0.2 | F85: 175 | G85: 0.07 | H85: 1139 | I85: 0.51 | J85: 783 | K85: 0.32 | L85: 506 | M85: 0.22 | N85: 464 | O85: 0.2 | P85: 156 | Q85: 0.07 | R85: 1237 | S85: 0.5 | T85: 275 | U85: 0.12 | V85: 1028 | W85: 0.48 | X85: 896 | Y85: 0.37 | Z85: 8525 | AA85: 0.3
A86: Maintenance Supplies | B86: 4214 | C86: 1.64 | D86: 857 | E86: 0.36 | F86: 1519 | G86: 0.59 | H86: 1930 | I86: 0.86 | J86: 2080 | K86: 0.84 | L86: 6002 | M86: 2.6 | N86: 2199 | O86: 0.93 | P86: 2526 | Q86: 1.08 | R86: 1924 | S86: 0.78 | T86: 3238 | U86: 1.43 | V86: 2338 | W86: 1.09 | X86: 1423 | Y86: 0.58 | Z86: 30250 | AA86: 1.06
A87: Maintenance Services | B87: 4664 | C87: 1.82 | D87: 9838 | E87: 4.1 | F87: 8537 | G87: 3.29 | H87: 3775 | I87: 1.68 | J87: 5261 | K87: 2.13 | L87: 9813 | M87: 4.25 | N87: 7832 | O87: 3.3 | P87: 12358 | Q87: 5.29 | R87: 11690 | S87: 4.75 | T87: 14930 | U87: 6.58 | V87: 2820 | W87: 1.31 | X87: 115691 | Y87: 47.2 | Z87: 207209 | AA87: 7.24
A88: Lawn & Snow Removal Services | B88: 0 | C88: 0 | D88: 0 | E88: 0 | F88: 1350 | G88: 0.52 | H88: 320 | I88: 0.14 | J88: 0 | K88: 0 | L88: 400 | M88: 0.17 | N88: 0 | O88: 0 | P88: 2320 | Q88: 0.99 | R88: 400 | S88: 0.16 | T88: 240 | U88: 0.11 | V88: 0 | W88: 0 | X88: 3570 | Y88: 1.46 | Z88: 8600 | AA88: 0.3
A89: Scavenger | B89: 949 | C89: 0.37 | D89: 665 | E89: 0.28 | F89: 1933 | G89: 0.75 | H89: 1146 | I89: 0.51 | J89: 1021 | K89: 0.41 | L89: 989 | M89: 0.43 | N89: 565 | O89: 0.24 | P89: 2716 | Q89: 1.16 | R89: 1265 | S89: 0.51 | T89: 2419 | U89: 1.07 | V89: 1545 | W89: 0.72 | X89: 1005 | Y89: 0.41 | Z89: 16218 | AA89: 0.57
... A93: TOTAL House & Plant Costs | B93: 52158 | C93: 20.33 | D93: 38718 | E93: 16.13 | F93: 55679 | G93: 21.47 | H93: 38854 | I93: 17.25 | J93: 52868 | K93: 21.44 | L93: 67346 | M93: 29.15 | N93: 52594 | O93: 22.14 | P93: 49029 | Q93: 20.98 | R93: 57766 | S93: 23.46 | T93: 58976 | U93: 26 | V93: 44924 | W93: 20.94 | X93: 164941 | Y93: 67.3 | Z93: 733852 | AA93: 25.63
A94: Food & Nutrition
A95: Payroll Dietary | B95: 30789 | C95: 12 | D95: 27795 | E95: 11.58 | F95: 28398 | G95: 10.95 | H95: 27975 | I95: 12.42 | J95: 30931 | K95: 12.54 | L95: 32852 | M95: 14.22 | N95: 27171 | O95: 11.44 | P95: 28137 | Q95: 12.04 | R95: 27808 | S95: 11.29 | T95: 26559 | U95: 11.71 | V95: 23191 | W95: 10.81 | X95: 24827 | Y95: 10.13 | Z95: 336433 | AA95: 11.75
A96: Food | B96: 20999 | C96: 8.18 | D96: 17824 | E96: 7.42 | F96: 17292 | G96: 6.67 | H96: 18014 | I96: 8 | J96: 20361 | K96: 8.26 | L96: 18023 | M96: 7.8 | N96: 17811 | O96: 7.5 | P96: 27496 | Q96: 11.77 | R96: 16725 | S96: 6.79 | T96: 19302 | U96: 8.51 | V96: 18234 | W96: 8.5 | X96: 17889 | Y96: 7.3 | Z96: 229970 | AA96: 8.03
A97: Food Supplements | B97: 1328 | C97: 0.52 | D97: 600 | E97: 0.25 | F97: 1386 | G97: 0.53 | H97: 1457 | I97: 0.65 | J97: 1933 | K97: 0.78 | L97: 1093 | M97: 0.47 | N97: 1749 | O97: 0.74 | P97: 1258 | Q97: 0.54 | R97: 1558 | S97: 0.63 | T97: 1554 | U97: 0.69 | V97: 1811 | W97: 0.84 | X97: 1243 | Y97: 0.51 | Z97: 16972 | AA97: 0.59
A98: Dietary Supplies | B98: 1982 | C98: 0.77 | D98: 2310 | E98: 0.96 | F98: 2253 | G98: 0.87 | H98: 1398 | I98: 0.62 | J98: 1914 | K98: 0.78 | L98: 5400 | M98: 2.34 | N98: 1490 | O98: 0.63 | P98: 1973 | Q98: 0.84 | R98: 2284 | S98: 0.93 | T98: 1537 | U98: 0.68 | V98: 3564 | W98: 1.66 | X98: 1739 | Y98: 0.71 | Z98: 27844 | AA98: 0.97
A99: Covid-19 Dietary Supplies | B99: 0 | C99: 0 | D99: 0 | E99: 0 | F99: 0 | G99: 0 | H99: 0 | I99: 0 | J99: 0 | K99: 0 | L99: 0 | M99: 0 | N99: 0 | O99: 0 | P99: 0 | Q99: 0 | R99: 0 | S99: 0 | T99: 0 | U99: 0 | V99: 0 | W99: 0 | X99: 0 | Y99: 0 | Z99: 0 | AA99: 0
A100: Dietary Consultant | B100: -625 | C100: -0.24 | D100: 53 | E100: 0.02 | F100: 54 | G100: 0.02 | H100: 55 | I100: 0.02 | J100: 53 | K100: 0.02 | L100: 53 | M100: 0.02 | N100: 53 | O100: 0.02 | P100: 634 | Q100: 0.27 | R100: 53 | S100: 0.02 | T100: 126 | U100: 0.06 | V100: 126 | W100: 0.06 | X100: 127 | Y100: 0.05 | Z100: 760 | AA100: 0.03
A101: TOTAL Food & Nutrition | B101: 54473 | C101: 21.23 | D101: 48582 | E101: 20.23 | F101: 49383 | G101: 19.04 | H101: 48899 | I101: 21.7 | J101: 55191 | K101: 22.38 | L101: 57421 | M101: 24.86 | N101: 48274 | O101: 20.33 | P101: 59498 | Q101: 25.46 | R101: 48427 | S101: 19.67 | T101: 49078 | U101: 21.64 | V101: 46926 | W101: 21.88 | X101: 45826 | Y101: 18.7 | Z101: 611979 | AA101: 21.38
A102: Employee Welfare Costs
A103: Payroll Taxes | B103: 43661 | C103: 17.02 | D103: 35768 | E103: 14.9 | F103: 36963 | G103: 14.25 | H103: 34129 | I103: 15.15 | J103: 35621 | K103: 14.44 | L103: 33348 | M103: 14.44 | N103: 31531 | O103: 13.28 | P103: 29560 | Q103: 12.65 | R103: 29738 | S103: 12.08 | T103: 25028 | U103: 11.04 | V103: 29128 | W103: 13.58 | X103: 32183 | Y103: 13.13 | Z103: 396658 | AA103: 13.86
A104: Workmans Comp Insurance | B104: 2748 | C104: 1.07 | D104: 1939 | E104: 0.81 | F104: 2295 | G104: 0.89 | H104: 6660 | I104: 2.96 | J104: 2256 | K104: 0.91 | L104: 4063 | M104: 1.76 | N104: 2009 | O104: 0.85 | P104: 2033 | Q104: 0.87 | R104: 1988 | S104: 0.81 | T104: 2442 | U104: 1.08 | V104: 2490 | W104: 1.16 | X104: 6748 | Y104: 2.75 | Z104: 37669 | AA104: 1.32
A105: Employee Benefits | B105: 480 | C105: 0.19 | D105: -833 | E105: -0.35 | F105: 331 | G105: 0.13 | H105: 1663 | I105: 0.74 | J105: 2339 | K105: 0.95 | L105: -871 | M105: -0.38 | N105: 161 | O105: 0.07 | P105: 695 | Q105: 0.3 | R105: 435 | S105: 0.18 | T105: 8143 | U105: 3.59 | V105: 4568 | W105: 2.13 | X105: 894 | Y105: 0.36 | Z105: 18006 | AA105: 0.63
A106: Employee Insurance | B106: -18713 | C106: -7.29 | D106: 9590 | E106: 3.99 | F106: 15316 | G106: 5.91 | H106: 7535 | I106: 3.34 | J106: 17326 | K106: 7.03 | L106: 12098 | M106: 5.24 | N106: 13951 | O106: 5.87 | P106: 13405 | Q106: 5.74 | R106: 14323 | S106: 5.82 | T106: 7063 | U106: 3.11 | V106: 12788 | W106: 5.96 | X106: 15253 | Y106: 6.22 | Z106: 119935 | AA106: 4.19
A107: Education & Seminars | B107: 545 | C107: 0.21 | D107: 0 | E107: 0 | F107: 0 | G107: 0 | H107: 1070 | I107: 0.47 | J107: 0 | K107: 0 | L107: 0 | M107: 0 | N107: 5005 | O107: 2.11 | P107: 455 | Q107: 0.19 | R107: -440 | S107: -0.18 | T107: 0 | U107: 0 | V107: 0 | W107: 0 | X107: 0 | Y107: 0 | Z107: 6635 | AA107: 0.23
A108: Pension | B108: 2473 | C108: 0.96 | D108: 4006 | E108: 1.67 | F108: 6772 | G108: 2.61 | H108: -495 | I108: -0.22 | J108: 1006 | K108: 0.41 | L108: 4932 | M108: 2.13 | N108: 3549 | O108: 1.49 | P108: 3309 | Q108: 1.42 | R108: 3410 | S108: 1.38 | T108: -1126 | U108: -0.5 | V108: -307 | W108: -0.14 | X108: 4766 | Y108: 1.94 | Z108: 32297 | AA108: 1.13
A109: TOTAL Employee Welfare Costs | B109: 31194 | C109: 12.16 | D109: 50470 | E109: 21.02 | F109: 61677 | G109: 23.79 | H109: 50563 | I109: 22.44 | J109: 58548 | K109: 23.74 | L109: 53571 | M109: 23.19 | N109: 56207 | O109: 23.67 | P109: 49458 | Q109: 21.16 | R109: 49454 | S109: 20.09 | T109: 41549 | U109: 18.32 | V109: 48667 | W109: 22.69 | X109: 59844 | Y109: 24.42 | Z109: 611200 | AA109: 21.35
A110: General & Administrative
A111: Payroll Administrative | B111: 12143 | C111: 4.73 | D111: 10719 | E111: 4.46 | F111: 10354 | G111: 3.99 | H111: 12475 | I111: 5.54 | J111: 12135 | K111: 4.92 | L111: 12059 | M111: 5.22 | N111: 11541 | O111: 4.86 | P111: 12268 | Q111: 5.25 | R111: 10491 | S111: 4.26 | T111: 12133 | U111: 5.35 | V111: 10847 | W111: 5.06 | X111: 23449 | Y111: 9.57 | Z111: 150615 | AA111: 5.26
A112: Payroll Office | B112: 6021 | C112: 2.35 | D112: 6629 | E112: 2.76 | F112: 9495 | G112: 3.66 | H112: 7342 | I112: 3.26 | J112: 7915 | K112: 3.21 | L112: 11168 | M112: 4.83 | N112: 6978 | O112: 2.94 | P112: 9585 | Q112: 4.1 | R112: 9165 | S112: 3.72 | T112: 9333 | U112: 4.12 | V112: 8737 | W112: 4.07 | X112: 8725 | Y112: 3.56 | Z112: 101094 | AA112: 3.53
A113: Payroll Marketing | B113: 0 | C113: 0 | D113: 0 | E113: 0 | F113: 0 | G113: 0 | H113: 0 | I113: 0 | J113: 0 | K113: 0 | L113: 0 | M113: 0 | N113: 0 | O113: 0 | P113: 0 | Q113: 0 | R113: 0 | S113: 0 | T113: 0 | U113: 0 | V113: 0 | W113: 0 | X113: 0 | Y113: 0 | Z113: 0 | AA113: 0
A114: Marketing Consultant | B114: 850 | C114: 0.33 | D114: 850 | E114: 0.35 | F114: 850 | G114: 0.33 | H114: 1942 | I114: 0.86 | J114: 850 | K114: 0.34 | L114: 850 | M114: 0.37 | N114: 850 | O114: 0.36 | P114: 850 | Q114: 0.36 | R114: 850 | S114: 0.35 | T114: 850 | U114: 0.37 | V114: 850 | W114: 0.4 | X114: 850 | Y114: 0.35 | Z114: 11292 | AA114: 0.39
...

Sheet PR Trending Data
A1: ?"Date: May 8 | B1: 2026" | C1: Allure of Peru | D1: Facility #IL6004303
A2: Time: 12:09:08 EDT | B2: Payroll Summary Detail-GGM
A3: User: Roth - Tracy Morkunas | B3: 1/1/2025 to 12/31/2025
A5: Include Adjustment Periods: NO | B5: Include Closing Periods: NO
B7: January 25_Actual $ | C7: January 25_Actual / Day | D7: February 25_Actual $ | E7: February 25_Actual / Day | F7: March 25_Actual $ | G7: March 25_Actual / Day | H7: April 25_Actual $ | I7: April 25_Actual / Day | J7: May 25_Actual $ | K7: May 25_Actual / Day | L7: June 25_Actual $ | M7: June 25_Actual / Day | N7: July 25_Actual $ | O7: July 25_Actual / Day | P7: August 25_Actual $ | Q7: August 25_Actual / Day | R7: September 25_Actual $ | S7: September 25_Actual / Day | T7: October 25_Actual $ | U7: October 25_Actual / Day | V7: November 25_Actual $ | W7: November 25_Actual / Day | X7: December 25_Actual $ | Y7: December 25_Actual / Day | Z7: TOTALS_Actual $ | AA7: TOTALS_Actual / Day
A8: Payroll Summary
A9: P/R Administrator | B9: 10221 | C9: 3.98 | D9: 9232 | E9: 3.85 | F9: 10241 | G9: 3.95 | H9: 10188 | I9: 4.52 | J9: 10528 | K9: 4.27 | L9: 10188 | M9: 4.41 | N9: 10528 | O9: 4.43 | P9: 10528 | Q9: 4.5 | R9: 10188 | S9: 4.14 | T9: 10528 | U9: 4.64 | V9: 10188 | W9: 4.75 | X9: 11658 | Y9: 4.76 | Z9: 124215 | AA9: 4.34
A10: P/R Administrator Covid | B10: 1922 | C10: 0.75 | D10: 1487 | E10: 0.62 | F10: 113 | G10: 0.04 | H10: 2287 | I10: 1.02 | J10: 1608 | K10: 0.65 | L10: 1871 | M10: 0.81 | N10: 1014 | O10: 0.43 | P10: 1741 | Q10: 0.74 | R10: 303 | S10: 0.12 | T10: 1606 | U10: 0.71 | V10: 659 | W10: 0.31 | X10: 0 | Y10: 0 | Z10: 14610 | AA10: 0.51
A11: P/R Assistant Admin Covid | B11: 0 | C11: 0 | D11: 0 | E11: 0 | F11: 0 | G11: 0 | H11: 0 | I11: 0 | J11: 0 | K11: 0 | L11: 0 | M11: 0 | N11: 0 | O11: 0 | P11: 0 | Q11: 0 | R11: 0 | S11: 0 | T11: 0 | U11: 0 | V11: 0 | W11: 0 | X11: 0 | Y11: 0 | Z11: 0 | AA11: 0
A12: P/R Assistant Administrator | B12: 0 | C12: 0 | D12: 0 | E12: 0 | F12: 0 | G12: 0 | H12: 0 | I12: 0 | J12: 0 | K12: 0 | L12: 0 | M12: 0 | N12: 0 | O12: 0 | P12: 0 | Q12: 0 | R12: 0 | S12: 0 | T12: 0 | U12: 0 | V12: 0 | W12: 0 | X12: 0 | Y12: 0 | Z12: 0 | AA12: 0
A13: P/R DON | B13: 9212 | C13: 3.59 | D13: 7717 | E13: 3.21 | F13: 8952 | G13: 3.45 | H13: 8492 | I13: 3.77 | J13: 8997 | K13: 3.65 | L13: 8509 | M13: 3.68 | N13: 8817 | O13: 3.71 | P13: 8597 | Q13: 3.68 | R13: 8438 | S13: 3.43 | T13: 8719 | U13: 3.84 | V13: 8626 | W13: 4.02 | X13: 8871 | Y13: 3.62 | Z13: 103946 | AA13: 3.63
A14: P/R DON Covid | B14: 0 | C14: 0 | D14: 0 | E14: 0 | F14: 0 | G14: 0 | H14: 0 | I14: 0 | J14: 0 | K14: 0 | L14: 0 | M14: 0 | N14: 1250 | O14: 0.53 | P14: 0 | Q14: 0 | R14: 0 | S14: 0 | T14: 321 | U14: 0.14 | V14: 429 | W14: 0.2 | X14: 0 | Y14: 0 | Z14: 2000 | AA14: 0.07
A15: P/R ADON | B15: 7877 | C15: 3.07 | D15: 7354 | E15: 3.06 | F15: 7832 | G15: 3.02 | H15: 7552 | I15: 3.35 | J15: 8298 | K15: 3.36 | L15: 7532 | M15: 3.26 | N15: 7601 | O15: 3.2 | P15: 7638 | Q15: 3.27 | R15: 6659 | S15: 2.7 | T15: 1904 | U15: 0.84 | V15: 6738 | W15: 3.14 | X15: 8630 | Y15: 3.52 | Z15: 85613 | AA15: 2.99
A16: P/R ADON Covid | B16: 0 | C16: 0 | D16: 0 | E16: 0 | F16: 0 | G16: 0 | H16: 0 | I16: 0 | J16: 0 | K16: 0 | L16: 0 | M16: 0 | N16: 0 | O16: 0 | P16: 0 | Q16: 0 | R16: 0 | S16: 0 | T16: 0 | U16: 0 | V16: 0 | W16: 0 | X16: 0 | Y16: 0 | Z16: 0 | AA16: 0
A17: P/R RN | B17: 65236 | C17: 25.42 | D17: 60365 | E17: 25.14 | F17: 68632 | G17: 26.47 | H17: 69671 | I17: 30.92 | J17: 71475 | K17: 28.98 | L17: 69227 | M17: 29.97 | N17: 72869 | O17: 30.68 | P17: 66824 | Q17: 28.59 | R17: 64087 | S17: 26.03 | T17: 66427 | U17: 29.29 | V17: 64275 | W17: 29.97 | X17: 61682 | Y17: 25.17 | Z17: 800771 | AA17: 27.97
A18: P/R RN Covid | B18: 0 | C18: 0 | D18: 0 | E18: 0 | F18: 0 | G18: 0 | H18: 0 | I18: 0 | J18: 0 | K18: 0 | L18: 0 | M18: 0 | N18: 0 | O18: 0 | P18: 0 | Q18: 0 | R18: 0 | S18: 0 | T18: 0 | U18: 0 | V18: 0 | W18: 0 | X18: 0 | Y18: 0 | Z18: 0 | AA18: 0
A19: P/R LPN | B19: 0 | C19: 0 | D19: 0 | E19: 0 | F19: 0 | G19: 0 | H19: 0 | I19: 0 | J19: 0 | K19: 0 | L19: 12970 | M19: 5.61 | N19: -12970 | O19: -5.46 | P19: 0 | Q19: 0 | R19: 0 | S19: 0 | T19: 0 | U19: 0 | V19: 0 | W19: 0 | X19: 0 | Y19: 0 | Z19: 0 | AA19: 0
A20: P/R LPN Covid | B20: 36740 | C20: 14.32 | D20: 36131 | E20: 15.05 | F20: 35983 | G20: 13.88 | H20: 33791 | I20: 15 | J20: 33989 | K20: 13.78 | L20: 27241 | M20: 11.79 | N20: 47661 | O20: 20.07 | P20: 34825 | Q20: 14.9 | R20: 35716 | S20: 14.51 | T20: 40897 | U20: 18.03 | V20: 39372 | W20: 18.36 | X20: 40479 | Y20: 16.52 | Z20: 442824 | AA20: 15.47
... A49: TOTAL Payroll Summary | B49: 379332 | C49: 147.83 | D49: 332103 | E49: 138.32 | F49: 390919 | G49: 150.76 | H49: 373220 | I49: 165.65 | J49: 401243 | K49: 162.71 | L49: 412670 | M49: 178.65 | N49: 386222 | O49: 162.62 | P49: 365887 | Q49: 156.56 | R49: 378054 | S49: 153.56 | T49: 370281 | U49: 163.26 | V49: 373009 | W49: 173.9 | X49: 401772 | Y49: 163.92 | Z49: 4564714 | AA49: 159.45
A50: Payroll Taxes Detail
A51: FICA | B51: 28146 | C51: 10.97 | D51: 24576 | E51: 10.24 | F51: 27649 | G51: 10.66 | H51: 27609 | I51: 12.25 | J51: 29751 | K51: 12.06 | L51: 29195 | M51: 12.64 | N51: 28527 | O51: 12.01 | P51: 27223 | Q51: 11.65 | R51: 27430 | S51: 11.14 | T51: 22786 | U51: 10.05 | V51: 27048 | W51: 12.61 | X51: 28986 | Y51: 11.83 | Z51: 328926 | AA51: 11.49
A52: State Unemployment | B52: 13556 | C52: 5.28 | D52: 10269 | E52: 4.28 | F52: 8818 | G52: 3.4 | H52: 6179 | I52: 2.74 | J52: 5508 | K52: 2.23 | L52: 3839 | M52: 1.66 | N52: 2743 | O52: 1.16 | P52: 2164 | Q52: 0.93 | R52: 2174 | S52: 0.88 | T52: 2092 | U52: 0.92 | V52: 1895 | W52: 0.88 | X52: 2237 | Y52: 0.91 | Z52: 61473 | AA52: 2.15
A53: Federal Unemployment | B53: 1959 | C53: 0.76 | D53: 924 | E53: 0.38 | F53: 496 | G53: 0.19 | H53: 341 | I53: 0.15 | J53: 363 | K53: 0.15 | L53: 315 | M53: 0.14 | N53: 261 | O53: 0.11 | P53: 172 | Q53: 0.07 | R53: 134 | S53: 0.05 | T53: 150 | U53: 0.07 | V53: 184 | W53: 0.09 | X53: 961 | Y53: 0.39 | Z53: 6259 | AA53: 0.22
A54: Payroll Taxes - Other | B54: 0 | C54: 0 | D54: 0 | E54: 0 | F54: 0 | G54: 0 | H54: 0 | I54: 0 | J54: 0 | K54: 0 | L54: 0 | M54: 0 | N54: 0 | O54: 0 | P54: 0 | Q54: 0 | R54: 0 | S54: 0 | T54: 0 | U54: 0 | V54: 0 | W54: 0 | X54: 0 | Y54: 0 | Z54: 0 | AA54: 0
A55: TOTAL Payroll Taxes Detail | B55: 43661 | C55: 17.02 | D55: 35768 | E55: 14.9 | F55: 36963 | G55: 14.25 | H55: 34129 | I55: 15.15 | J55: 35621 | K55: 14.44 | L55: 33348 | M55: 14.44 | N55: 31531 | O55: 13.28 | P55: 29560 | Q55: 12.65 | R55: 29738 | S55: 12.08 | T55: 25028 | U55: 11.04 | V55: 29128 | W55: 13.58 | X55: 32183 | Y55: 13.13 | Z55: 396658 | AA55: 13.86
A56: Total Payroll | B56: 422993 | C56: 164.85 | D56: 367871 | E56: 153.22 | F56: 427882 | G56: 165.01 | H56: 407349 | I56: 180.8 | J56: 436864 | K56: 177.15 | L56: 446019 | M56: 193.08 | N56: 417754 | O56: 175.9 | P56: 395447 | Q56: 169.21 | R56: 407792 | S56: 165.63 | T56: 395309 | U56: 174.3 | V56: 402137 | W56: 187.48 | X56: 433956 | Y56: 177.05 | Z56: 4961372 | AA56: 173.31
A57: Agency Detail
A58: Agency Salaries - RN | B58: 15000 | C58: 5.85 | D58: 2529 | E58: 1.05 | F58: 5652 | G58: 2.18 | H58: 2333 | I58: 1.04 | J58: 8661 | K58: 3.51 | L58: 3684 | M58: 1.59 | N58: 2170 | O58: 0.91 | P58: 2527 | Q58: 1.08 | R58: 14053 | S58: 5.71 | T58: 12299 | U58: 5.42 | V58: 0 | W58: 0 | X58: 8315 | Y58: 3.39 | Z58: 77223 | AA58: 2.7
A59: Covid Agency Salaries - RN | B59: 2683 | C59: 1.05 | D59: 2226 | E59: 0.93 | F59: 0 | G59: 0 | H59: 95 | I59: 0.04 | J59: 0 | K59: 0 | L59: 0 | M59: 0 | N59: 0 | O59: 0 | P59: 0 | Q59: 0 | R59: 0 | S59: 0 | T59: 0 | U59: 0 | V59: 0 | W59: 0 | X59: 0 | Y59: 0 | Z59: 5004 | AA59: 0.17
A60: Agency Salaries - LPN | B60: 7758 | C60: 3.02 | D60: 1974 | E60: 0.82 | F60: 3687 | G60: 1.42 | H60: 0 | I60: 0 | J60: 1264 | K60: 0.51 | L60: 193 | M60: 0.08 | N60: 882 | O60: 0.37 | P60: 0 | Q60: 0 | R60: 0 | S60: 0 | T60: 260 | U60: 0.11 | V60: 0 | W60: 0 | X60: 2399 | Y60: 0.98 | Z60: 18418 | AA60: 0.64
A61: Covid Agency Salaries - LPN | B61: 0 | C61: 0 | D61: 0 | E61: 0 | F61: 0 | G61: 0 | H61: 0 | I61: 0 | J61: 0 | K61: 0 | L61: 0 | M61: 0 | N61: 0 | O61: 0 | P61: 0 | Q61: 0 | R61: 0 | S61: 0 | T61: 0 | U61: 0 | V61: 0 | W61: 0 | X61: 0 | Y61: 0 | Z61: 0 | AA61: 0
A62: Agency Salaries - CNA | B62: 17063 | C62: 6.65 | D62: 18864 | E62: 7.86 | F62: 32475 | G62: 12.52 | H62: 10108 | I62: 4.49 | J62: 9671 | K62: 3.92 | L62: 7191 | M62: 3.11 | N62: 2546 | O62: 1.07 | P62: 2770 | Q62: 1.19 | R62: 21952 | S62: 8.92 | T62: 11843 | U62: 5.22 | V62: 2491 | W62: 1.16 | X62: 8728 | Y62: 3.56 | Z62: 145702 | AA62: 5.09
A63: Covid Agency Salaries - CNA | B63: 504 | C63: 0.2 | D63: 8450 | E63: 3.52 | F63: 0 | G63: 0 | H63: 0 | I63: 0 | J63: 0 | K63: 0 | L63: 0 | M63: 0 | N63: 0 | O63: 0 | P63: 0 | Q63: 0 | R63: 0 | S63: 0 | T63: 0 | U63: 0 | V63: 0 | W63: 0 | X63: 0 | Y63: 0 | Z63: 8954 | AA63: 0.31
A64: TOTAL Agency Detail | B64: 43008 | C64: 16.76 | D64: 34044 | E64: 14.18 | F64: 41815 | G64: 16.13 | H64: 12536 | I64: 5.56 | J64: 19596 | K64: 7.95 | L64: 11068 | M64: 4.79 | N64: 5598 | O64: 2.36 | P64: 5297 | Q64: 2.27 | R64: 36004 | S64: 14.62 | T64: 24402 | U64: 10.76 | V64: 2491 | W64: 1.16 | X64: 19442 | Y64: 7.93 | Z64: 255302 | AA64: 8.92
A65: Empire Detail
A66: Empire Staffing Salaries RN | B66: 7307 | C66: 2.85 | D66: 5276 | E66: 2.2 | F66: 9591 | G66: 3.7 | H66: 2102 | I66: 0.93 | J66: 6920 | K66: 2.81 | L66: 10029 | M66: 4.34 | N66: 11586 | O66: 4.88 | P66: 3266 | Q66: 1.4 | R66: 12835 | S66: 5.21 | T66: 0 | U66: 0 | V66: 8223 | W66: 3.83 | X66: 18329 | Y66: 7.48 | Z66: 95463 | AA66: 3.33
A67: Empire Staffing Salaries LPN | B67: 0 | C67: 0 | D67: 0 | E67: 0 | F67: 0 | G67: 0 | H67: 0 | I67: 0 | J67: 0 | K67: 0 | L67: 0 | M67: 0 | N67: 0 | O67: 0 | P67: 0 | Q67: 0 | R67: 0 | S67: 0 | T67: 0 | U67: 0 | V67: 0 | W67: 0 | X67: 0 | Y67: 0 | Z67: 0 | AA67: 0
A68: Empire Staffing Salaries CNA | B68: 0 | C68: 0 | D68: 912 | E68: 0.38 | F68: 1097 | G68: 0.42 | H68: 1059 | I68: 0.47 | J68: 335 | K68: 0.14 | L68: 0 | M68: 0 | N68: 2224 | O68: 0.94 | P68: 351 | Q68: 0.15 | R68: 2633 | S68: 1.07 | T68: 0 | U68: 0 | V68: 1464 | W68: 0.68 | X68: 3137 | Y68: 1.28 | Z68: 13213 | AA68: 0.46
A69: TOTAL Empire Detail | B69: 7307 | C69: 2.85 | D69: 6188 | E69: 2.58 | F69: 10688 | G69: 4.12 | H69: 3161 | I69: 1.4 | J69: 7255 | K69: 2.94 | L69: 10029 | M69: 4.34 | N69: 13810 | O69: 5.81 | P69: 3618 | Q69: 1.55 | R69: 15468 | S69: 6.28 | T69: 0 | U69: 0 | V69: 9687 | W69: 4.52 | X69: 21466 | Y69: 8.76 | Z69: 108676 | AA69: 3.8
A70: Total Labor | B70: 379332 | C70: 147.83 | D70: 332103 | E70: 138.32 | F70: 390919 | G70: 150.76 | H70: 373220 | I70: 165.65 | J70: 401243 | K70: 162.71 | L70: 412670 | M70: 178.65 | N70: 386222 | O70: 162.62 | P70: 365887 | Q70: 156.56 | R70: 378054 | S70: 153.56 | T70: 370281 | U70: 163.26 | V70: 373009 | W70: 173.9 | X70: 401772 | Y70: 163.92 | Z70: 4564714 | AA70: 159.45
A71: Total Labor and Agency | B71: 422340 | C71: 164.59 | D71: 366147 | E71: 152.5 | F71: 432734 | G71: 166.89 | H71: 385756 | I71: 171.22 | J71: 420839 | K71: 170.66 | L71: 423738 | M71: 183.44 | N71: 391820 | O71: 164.98 | P71: 371184 | Q71: 158.83 | R71: 414058 | S71: 168.18 | T71: 394683 | U71: 174.02 | V71: 375501 | W71: 175.06 | X71: 421214 | Y71: 171.85 | Z71: 4820015 | AA71: 168.37
A72: Total Labor and Empire | B72: 386639 | C72: 150.68 | D72: 338291 | E72: 140.9 | F72: 401607 | G72: 154.88 | H72: 376381 | I72: 167.06 | J72: 408498 | K72: 165.65 | L72: 422699 | M72: 182.99 | N72: 400032 | O72: 168.43 | P72: 369505 | Q72: 158.11 | R72: 393522 | S72: 159.84 | T72: 370281 | U72: 163.26 | V72: 382697 | W72: 178.41 | X72: 423238 | Y72: 172.68 | Z72: 4673390 | AA72: 163.25
A73: Total Labor + Agency + Empire | B73: 429647 | C73: 167.44 | D73: 372334 | E73: 155.07 | F73: 443422 | G73: 171.01 | H73: 388917 | I73: 172.62 | J73: 428094 | K73: 173.6 | L73: 433767 | M73: 187.78 | N73: 405630 | O73: 170.79 | P73: 374802 | Q73: 160.38 | R73: 429527 | S73: 174.46 | T73: 394683 | U73: 174.02 | V73: 385188 | W73: 179.57 | X73: 442680 | Y73: 180.61 | Z73: 4928691 | AA73: 172.17
A74: Grand Total Costs including Tax | B74: 473308 | C74: 184.45 | D74: 408103 | E74: 169.97 | F74: 480384 | G74: 185.26 | H74: 423046 | I74: 187.77 | J74: 463715 | K74: 188.04 | L74: 467115 | M74: 202.21 | N74: 437162 | O74: 184.07 | P74: 404362 | Q74: 173.03 | R74: 459264 | S74: 186.54 | T74: 419712 | U74: 185.06 | V74: 414316 | W74: 193.15 | X74: 474863 | Y74: 193.74 | Z74: 5325349 | AA74: 186.03

Sheet DTF Data
A1: Intercompany Receivable - Accounts | C1: Balance
A3: Due to/From Prior Owner | C3: $0.00
A4: Due to/from Waverly | C4: $0.00
A5: Due To/From Allure | C5: $938,209.79
A6: Due To/From Affiliate | C6: ($157,039.88)
A7: Due To/From Galesburg | C7: $0.00
A8: Due To/From Galesburg Prop | C8: $0.00
A9: Due To/From Geneseo SNF | C9: ($600,000.00)
A10: Due To/From Geneseo ILF | C10: $0.00
A11: Due To/From Geneseo Prop | C11: $0.00
A12: Due To/From Knox County | C12: $0.00
A13: Due To/From Lake Storey | C13: $0.00
... A53: Due To/From Zion SLF Prop | C53: $0.00

Sheet DTF & QuickCalc
A1: Intercompany Receivable - Accounts | C1: Calculation | D1: Intercompany Payable | E1: Intercompany Receivable
A3: Due to/From Prior Owner | B3: =VLOOKUP(A3,'DTF Data'!$A$1:$C$53,3,FALSE) -> $0.00 | C3: =VALUE(SUBSTITUTE(SUBSTITUTE(SUBSTITUTE(SUBSTITUTE(SUBSTITUTE(TRIM(CLEAN(B3)),CHAR(160),""),"$",""),",",""),"(","-"),")","")) -> 0 | D3: =(IF(C3<0,C3,0)) -> 0 | E3: =IF(C3>0,C3,0) -> 0
A4: Due to/from Waverly | B4: =VLOOKUP(A4,'DTF Data'!$A$1:$C$53,3,FALSE) -> $0.00 | C4: =VALUE(SUBSTITUTE(SUBSTITUTE(SUBSTITUTE(SUBSTITUTE(SUBSTITUTE(TRIM(CLEAN(B4)),CHAR(160),""),"$",""),",",""),"(","-"),")","")) -> 0 | D4: =(IF(C4<0,C4,0)) -> 0 | E4: =IF(C4>0,C4,0) -> 0
A5: Due To/From Allure | B5: =VLOOKUP(A5,'DTF Data'!$A$1:$C$53,3,FALSE) -> $938,209.79 | C5: =VALUE(SUBSTITUTE(SUBSTITUTE(SUBSTITUTE(SUBSTITUTE(SUBSTITUTE(TRIM(CLEAN(B5)),CHAR(160),""),"$",""),",",""),"(","-"),")","")) -> 938209.79 | D5: =(IF(C5<0,C5,0)) -> 0 | E5: =IF(C5>0,C5,0) -> 938209.79
A6: Due To/From Affiliate | B6: =VLOOKUP(A6,'DTF Data'!$A$1:$C$53,3,FALSE) -> ($157,039.88) | C6: =VALUE(SUBSTITUTE(SUBSTITUTE(SUBSTITUTE(SUBSTITUTE(SUBSTITUTE(TRIM(CLEAN(B6)),CHAR(160),""),"$",""),",",""),"(","-"),")","")) -> -157039.88 | D6: =(IF(C6<0,C6,0)) -> -157039.88 | E6: =IF(C6>0,C6,0) -> 0
A7: Due To/From Galesburg | B7: =VLOOKUP(A7,'DTF Data'!$A$1:$C$53,3,FALSE) -> $0.00 | C7: =VALUE(SUBSTITUTE(SUBSTITUTE(SUBSTITUTE(SUBSTITUTE(SUBSTITUTE(TRIM(CLEAN(B7)),CHAR(160),""),"$",""),",",""),"(","-"),")","")) -> 0 | D7: =(IF(C7<0,C7,0)) -> 0 | E7: =IF(C7>0,C7,0) -> 0
A8: Due To/From Galesburg Prop | B8: =VLOOKUP(A8,'DTF Data'!$A$1:$C$53,3,FALSE) -> $0.00 | C8: =VALUE(SUBSTITUTE(SUBSTITUTE(SUBSTITUTE(SUBSTITUTE(SUBSTITUTE(TRIM(CLEAN(B8)),CHAR(160),""),"$",""),",",""),"(","-"),")","")) -> 0 | D8: =(IF(C8<0,C8,0)) -> 0 | E8: =IF(C8>0,C8,0) -> 0
A9: Due To/From Geneseo SNF | B9: =VLOOKUP(A9,'DTF Data'!$A$1:$C$53,3,FALSE) -> ($600,000.00) | C9: =VALUE(SUBSTITUTE(SUBSTITUTE(SUBSTITUTE(SUBSTITUTE(SUBSTITUTE(TRIM(CLEAN(B9)),CHAR(160),""),"$",""),",",""),"(","-"),")","")) -> -600000 | D9: =(IF(C9<0,C9,0)) -> -600000 | E9: =IF(C9>0,C9,0) -> 0
A10: Due To/From Geneseo ILF | B10: =VLOOKUP(A10,'DTF Data'!$A$1:$C$53,3,FALSE) -> $0.00 | C10: =VALUE(SUBSTITUTE(SUBSTITUTE(SUBSTITUTE(SUBSTITUTE(SUBSTITUTE(TRIM(CLEAN(B10)),CHAR(160),""),"$",""),",",""),"(","-"),")","")) -> 0 | D10: =(IF(C10<0,C10,0)) -> 0 | E10: =IF(C10>0,C10,0) -> 0
A11: Due To/From Geneseo Prop | B11: =VLOOKUP(A11,'DTF Data'!$A$1:$C$53,3,FALSE) -> $0.00 | C11: =VALUE(SUBSTITUTE(SUBSTITUTE(SUBSTITUTE(SUBSTITUTE(SUBSTITUTE(TRIM(CLEAN(B11)),CHAR(160),""),"$",""),",",""),"(","-"),")","")) -> 0 | D11: =(IF(C11<0,C11,0)) -> 0 | E11: =IF(C11>0,C11,0) -> 0
A12: Due To/From Knox County | B12: =VLOOKUP(A12,'DTF Data'!$A$1:$C$53,3,FALSE) -> $0.00 | C12: =VALUE(SUBSTITUTE(SUBSTITUTE(SUBSTITUTE(SUBSTITUTE(SUBSTITUTE(TRIM(CLEAN(B12)),CHAR(160),""),"$",""),",",""),"(","-"),")","")) -> 0 | D12: =(IF(C12<0,C12,0)) -> 0 | E12: =IF(C12>0,C12,0) -> 0
A13: Due To/From Lake Storey | B13: =VLOOKUP(A13,'DTF Data'!$A$1:$C$53,3,FALSE) -> $0.00 | C13: =VALUE(SUBSTITUTE(SUBSTITUTE(SUBSTITUTE(SUBSTITUTE(SUBSTITUTE(TRIM(CLEAN(B13)),CHAR(160),""),"$",""),",",""),"(","-"),")","")) -> 0 | D13: =(IF(C13<0,C13,0)) -> 0 | E13: =IF(C13>0,C13,0) -> 0
A14: Due To/From Lake Storey Prop | B14: =VLOOKUP(A14,'DTF Data'!$A$1:$C$53,3,FALSE) -> $0.00 | C14: =VALUE(SUBSTITUTE(SUBSTITUTE(SUBSTITUTE(SUBSTITUTE(SUBSTITUTE(TRIM(CLEAN(B14)),CHAR(160),""),"$",""),",",""),"(","-"),")","")) -> 0 | D14: =(IF(C14<0,C14,0)) -> 0 | E14: =IF(C14>0,C14,0) -> 0
... A53: Due To/From Zion SLF Prop | B53: =VLOOKUP(A53,'DTF Data'!$A$1:$C$53,3,FALSE) -> $0.00 | C53: =VALUE(SUBSTITUTE(SUBSTITUTE(SUBSTITUTE(SUBSTITUTE(SUBSTITUTE(TRIM(CLEAN(B53)),CHAR(160),""),"$",""),",",""),"(","-"),")","")) -> 0 | D53: =(IF(C53<0,C53,0)) -> 0 | E53: =IF(C53>0,C53,0) -> 0
D54: =SUM(D3:D53) -> -1890825.7 | E54: =SUM(E3:E53) -> 1279660.1 | F54: =SUM(D54:E54) -> -611165.58
A57: Intercompany Receivable | B57: =E54 -> 1279660.1
A58: Intercompany Payable | B58: =D54*-1 -> 1890825.7
A62: Quick Calculations
A63: ='BS Data'!A33 -> Accrued Payroll | B63: ='BS Data'!B33 -> 116658
A64: ='BS Data'!A34 -> Accrued Benefits | B64: ='BS Data'!B34 -> 0
A65: ='BS Data'!A35 -> Payroll Liabilites | B65: ='BS Data'!B35 -> 0
A66: Payroll Accruals and Liabilities | B66: =SUM(B63:B65) -> 116658
A71: Date Calculation
A72: =DATEVALUE("1"&LEFT('P&L Trending Data'!B8,FIND("_",'P&L Trending Data'!B8)-1)) -> 45658
